Workbook

Sheet Workshop #1
B3: Company Background and Industry Analysis
B5: Workshop 1
B6: Mathilde Sison, Averie Forshaw
B7: BUS 438
B8: Prof. Mahdi Rastad
A10: 3 | B10: a | C10: Primary SIC: Courier services and express delivery services
B12: b | C12: UPS runs an integrated delivery and logistics model, earning most of its revenue from domestic and international shipping fees for parcels and freight, priced by speed, distance, weight, and volume. It layers on higher-margin value‑added services including insurance, customs brokerage, supply chain contracts, and e‑commerce logistics.
B14: c(i) | C14: Headquarters: 55 Glenlake Parkway, NE, Atlanta, GA 30328, USA
B16: c(ii) | C16: Subsidaries: US, NAM, Europe, Asia-Pacific, Latin America, Middle East, parts of Africa
B18: c(iii) | C18: UPS operates globally.
B20: d | C20: Number of Employees: 490,000
A22: 4 | B22: a | C22: Most Recent (12/31/24)
C23: Total Assets: 70,070,000
C24: Total Equity: 16,718,000
C25: Total Revenue: 91,070,000
B27: b

Sheet Workshop #2
B3: Financial Statements and Performance Analysis
B5: Workshop 2
B6: Mathilde Sison, Averie Forshaw
B7: BUS 438
B8: Prof. Mahdi Rastad
B11: UPS Current Stock Price: | D11: 108.03
A13: 2 | C13: 2016 | D13: 2017 | E13: 2018 | F13: 2019 | G13: 2020 | H13: 2021 | I13: 2022 | J13: 2023 | K13: 2024 | L13: 2025 | M13: 2026
B14: Average Yearly Share Price | C14: =AVERAGE(Stock!$B111:$B122) -> 106.34167 | D14: =AVERAGE(Stock!B99:B110) -> 112.42333 | E14: =AVERAGE(Stock!B87:B98) -> 112.59333 | F14: =AVERAGE(Stock!B75:B86) -> 111.63833 | G14: =AVERAGE(Stock!B63:B74) -> 130.21417 | H14: =AVERAGE(Stock!B51:B62) -> 192.04333 | I14: =AVERAGE(Stock!B39:B50) -> 187.845 | J14: =AVERAGE(Stock!B27:B38) -> 170.855 | K14: =AVERAGE(Stock!B15:B26) -> 137.76583 | L14: =AVERAGE(Stock!B3:B14) -> 98.796667 | M14: =AVERAGE(Stock!B2) -> 106.58
A17: 3 | B17: a Standardized Annual Income Statement as a % of Total Revenue
E19: 44196 | F19: 44561 | G19: 44926 | H19: 45291 | I19: 45657
B20: Sales | E20: =Financials!B4/Financials!$B$4 -> 1 | F20: =Financials!C4/Financials!$C$4 -> 1 | G20: =Financials!D4/Financials!$D$4 -> 1 | H20: =Financials!E4/Financials!$E$4 -> 1 | I20: =Financials!F4/Financials!$F$4 -> 1
B21: Cost of Goods Sold (COGS) incl. D&A | E21: =Financials!B5/Financials!$B$4 -> 0.7420054 | F21: =Financials!C5/Financials!$C$4 -> 0.82066582 | G21: =Financials!D5/Financials!$D$4 -> 0.79926825 | H21: =Financials!E5/Financials!$E$4 -> 0.80488181 | I21: =Financials!F5/Financials!$F$4 -> 0.81233085
B22: COGS excluding D&A | E22: =Financials!B6/Financials!$B$4 -> 0.71005069 | F22: =Financials!C6/Financials!$C$4 -> 0.79028641 | G22: =Financials!D6/Financials!$D$4 -> 0.76739908 | H22: =Financials!E6/Financials!$E$4 -> 0.76778886 | I22: =Financials!F6/Financials!$F$4 -> 0.77262526
B23: Depreciation & Amortization Expense | E23: =Financials!B7/Financials!$B$4 -> 0.031954709 | F23: =Financials!C7/Financials!$C$4 -> 0.030379408 | G23: =Financials!D7/Financials!$D$4 -> 0.031869164 | H23: =Financials!E7/Financials!$E$4 -> 0.037092953 | I23: =Financials!F7/Financials!$F$4 -> 0.039705591
B24: Depreciation | E24: =Financials!B8/Financials!$B$4 -> 0.027027667 | F24: =Financials!C8/Financials!$C$4 -> 0.025492778 | G24: =Financials!D8/Financials!$D$4 -> 0.026620949 | H24: =Financials!E8/Financials!$E$4 -> 0.030514078 | I24: =Financials!F8/Financials!$F$4 -> 0.032576408
B25: Amortization of Intangibles | E25: =Financials!B9/Financials!$B$4 -> 0.0049270419 | F25: =Financials!C9/Financials!$C$4 -> 0.0048866302 | G25: =Financials!D9/Financials!$D$4 -> 0.0052482156 | H25: =Financials!E9/Financials!$E$4 -> 0.0065788749 | I25: =Financials!F9/Financials!$F$4 -> 0.0071291834
B26: Gross Income | E26: =Financials!B10/Financials!$B$4 -> 0.2579946 | F26: =Financials!C10/Financials!$C$4 -> 0.17933418 | G26: =Financials!D10/Financials!$D$4 -> 0.20073175 | H26: =Financials!E10/Financials!$E$4 -> 0.19511819 | I26: =Financials!F10/Financials!$F$4 -> 0.18766915
B27: SG&A Expense | E27: =Financials!B11/Financials!$B$4 -> 0.16518619 | F27: =Financials!C11/Financials!$C$4 -> 0.044494054 | G27: =Financials!D11/Financials!$D$4 -> 0.071095827 | H27: =Financials!E11/Financials!$E$4 -> 0.091850791 | I27: =Financials!F11/Financials!$F$4 -> 0.09553986
B28: Other SG&A | E28: =Financials!B12/Financials!$B$4 -> 0.16518619 | F28: =Financials!C12/Financials!$C$4 -> 0.044494054 | G28: =Financials!D12/Financials!$D$4 -> 0.071095827 | H28: =Financials!E12/Financials!$E$4 -> 0.091850791 | I28: =Financials!F12/Financials!$F$4 -> 0.09553986
B29: Other Operating Expense | E29: =Financials!B13/Financials!$B$4 -> 0 | F29: =Financials!C13/Financials!$C$4 -> 0 | G29: =Financials!D13/Financials!$D$4 -> 0 | H29: =Financials!E13/Financials!$E$4 -> 0 | I29: =Financials!F13/Financials!$F$4 -> -0.003421568
B30: EBIT (Operating Income) | E30: =Financials!B14/Financials!$B$4 -> 0.092808414 | F30: =Financials!C14/Financials!$C$4 -> 0.13484013 | G30: =Financials!D14/Financials!$D$4 -> 0.12963592 | H30: =Financials!E14/Financials!$E$4 -> 0.1032674 | I30: =Financials!F14/Financials!$F$4 -> 0.095550861
B31: Nonoperating Income - Net | E31: =Financials!B15/Financials!$B$4 -> -0.058958689 | F31: =Financials!C15/Financials!$C$4 -> 0.047220279 | G31: =Financials!D15/Financials!$D$4 -> 0.027280725 | H31: =Financials!E15/Financials!$E$4 -> 0.0046614139 | I31: =Financials!F15/Financials!$F$4 -> 0.00018703105
... B66: Depreciation & Amortization Expense | E66: =Financials!B50/Financials!$B$4 -> 0.031954709 | F66: =Financials!C50/Financials!$C$4 -> 0.030379408 | G66: =Financials!D50/Financials!$D$4 -> 0.031869164 | H66: =Financials!E50/Financials!$E$4 -> 0.037092953 | I66: =Financials!F50/Financials!$F$4 -> 0.039705591
B73: b Standardized Annual Balance Sheet as a % of Total Assets
E75: 44196 | F75: 44561 | G75: 44926 | H75: 45291 | I75: 45657
B76: Cash & Short-Term Investments | E76: =Financials!B55/Financials!$B$88 -> 0.10120497 | F76: =Financials!C55/Financials!$C$88 -> 0.15262589 | G76: =Financials!D55/Financials!$D$88 -> 0.10678533 | H76: =Financials!E55/Financials!$E$88 -> 0.085693721 | I76: =Financials!F55/Financials!$F$88 -> 0.090166976
B77: Cash Only | E77: =Financials!B56/Financials!$B$88 -> 0.094699398 | F77: =Financials!C56/Financials!$C$88 -> 0.14775593 | G77: =Financials!D56/Financials!$D$88 -> 0.078763849 | H77: =Financials!E56/Financials!$E$88 -> 0.045246059 | I77: =Financials!F56/Financials!$F$88 -> 0.087227059
B78: Total Short Term Investments | E78: =Financials!B57/Financials!$B$88 -> 0.0065055762 | F78: =Financials!C57/Financials!$C$88 -> 0.0048699661 | G78: =Financials!D57/Financials!$D$88 -> 0.028021484 | H78: =Financials!E57/Financials!$E$88 -> 0.040447662 | I78: =Financials!F57/Financials!$F$88 -> 0.0029399172
B79: Short-Term Receivables | E79: =Financials!B58/Financials!$B$88 -> 0.17672414 | F79: =Financials!C58/Financials!$C$88 -> 0.18507312 | G79: =Financials!D58/Financials!$D$88 -> 0.18124684 | H79: =Financials!E58/Financials!$E$88 -> 0.16163541 | I79: =Financials!F58/Financials!$F$88 -> 0.15952619
B80: Accounts Receivables, Net | E80: =Financials!B59/Financials!$B$88 -> 0.17672414 | F80: =Financials!C59/Financials!$C$88 -> 0.18507312 | G80: =Financials!D59/Financials!$D$88 -> 0.18124684 | H80: =Financials!E59/Financials!$E$88 -> 0.16163541 | I80: =Financials!F59/Financials!$F$88 -> 0.15952619
B81: Accounts Receivables, Gross | E81: =Financials!B60/Financials!$B$88 -> 0.17893539 | F81: =Financials!C60/Financials!$C$88 -> 0.18691737 | G81: =Financials!D60/Financials!$D$88 -> 0.18329959 | H81: =Financials!E60/Financials!$E$88 -> 0.16341364 | I81: =Financials!F60/Financials!$F$88 -> 0.1614671
B82: Bad Debt/Doubtful Accounts | E82: =Financials!B61/Financials!$B$88 -> -0.002211255 | F82: =Financials!C61/Financials!$C$88 -> -0.0018442475 | G82: =Financials!D61/Financials!$D$88 -> -0.0020527529 | H82: =Financials!E61/Financials!$E$88 -> -0.0017782294 | I82: =Financials!F61/Financials!$F$88 -> -0.0019409162
B83: Other Receivables | E83: =Financials!B62/Financials!$B$88 -> 0 | F83: =Financials!C62/Financials!$C$88 -> 0 | G83: =Financials!D62/Financials!$D$88 -> 0 | H83: =Financials!E62/Financials!$E$88 -> 0 | I83: =Financials!F62/Financials!$F$88 -> 0
B84: Inventories | E84: =Financials!B63/Financials!$B$88 -> 0.0099346238 | F84: =Financials!C63/Financials!$C$88 -> 0.010330668 | G84: =Financials!D63/Financials!$D$88 -> 0.012499297 | H84: =Financials!E63/Financials!$E$88 -> 0.013195591 | I84: =Financials!F63/Financials!$F$88 -> 0.011788212
B85: Raw Materials | E85: =Financials!B64/Financials!$B$88 -> 0.0099346238 | F85: =Financials!C64/Financials!$C$88 -> 0.010330668 | G85: =Financials!D64/Financials!$D$88 -> 0 | H85: =Financials!E64/Financials!$E$88 -> 0 | I85: =Financials!F64/Financials!$F$88 -> 0
B86: Other Current Assets | E86: =Financials!B65/Financials!$B$88 -> 0.036069094 | F86: =Financials!C65/Financials!$C$88 -> 0.011223975 | G86: =Financials!D65/Financials!$D$88 -> 0.011838479 | H86: =Financials!E65/Financials!$E$88 -> 0.013449624 | I86: =Financials!F65/Financials!$F$88 -> 0.014100186
B87: Miscellaneous Current Assets | E87: =Financials!B66/Financials!$B$88 -> 0.036069094 | F87: =Financials!C66/Financials!$C$88 -> 0.011223975 | G87: =Financials!D66/Financials!$D$88 -> 0.011838479 | H87: =Financials!E66/Financials!$E$88 -> 0.013449624 | I87: =Financials!F66/Financials!$F$88 -> 0.014100186
... B136: Total Liabilities & Shareholders' Equity | E136: =Financials!B115/Financials!$B$88 -> 1 | F136: =Financials!C115/Financials!$C$88 -> 1 | G136: =Financials!D115/Financials!$D$88 -> 1 | H136: =Financials!E115/Financials!$E$88 -> 1 | I136: =Financials!F115/Financials!$F$88 -> 1
A138: 4 | B138: Standardized Annual Income Statement: Categorical Growth Rates
E141: 2020-2021 | F141: 2021-2022 | G141: 2022-2023 | H141: 2023-2024
B142: Sales | E142: =(Financials!C4-Financials!B4)/Financials!B4 -> 0.15126966 | F142: =(Financials!D4-Financials!C4)/Financials!C4 -> 0.029114028 | G142: =(Financials!E4-Financials!D4)/Financials!D4 -> -0.092858428 | H142: =(Financials!F4-Financials!E4)/Financials!E4 -> 0.0016419637
B143: Cost of Goods Sold (COGS) incl. D&A | E143: =(Financials!C5-Financials!B5)/Financials!B5 -> 0.27331641 | F143: =(Financials!D5-Financials!C5)/Financials!C5 -> 0.0022815023 | G143: =(Financials!E5-Financials!D5)/Financials!D5 -> -0.08648723 | H143: =(Financials!F5-Financials!E5)/Financials!E5 -> 0.010911979
B144: COGS excluding D&A | E144: =(Financials!C6-Financials!B6)/Financials!B6 -> 0.28136311 | F144: =(Financials!D6-Financials!C6)/Financials!C6 -> -0.00068993348 | G144: =(Financials!E6-Financials!D6)/Financials!D6 -> -0.092397676 | H144: =(Financials!F6-Financials!E6)/Financials!E6 -> 0.0079514303
B145: Depreciation & Amortization Expense | E145: =(Financials!C7-Financials!B7)/Financials!B7 -> 0.094514455 | F145: =(Financials!D7-Financials!C7)/Financials!C7 -> 0.079580088 | G145: =(Financials!E7-Financials!D7)/Financials!D7 -> 0.055834379 | H145: =(Financials!F7-Financials!E7)/Financials!E7 -> 0.072192513
B146: Depreciation | E146: =(Financials!C8-Financials!B8)/Financials!B8 -> 0.085889571 | F146: =(Financials!D8-Financials!C8)/Financials!C8 -> 0.074656981 | G146: =(Financials!E8-Financials!D8)/Financials!D8 -> 0.039804732 | H146: =(Financials!F8-Financials!E8)/Financials!E8 -> 0.069339112
B147: Amortization of Intangibles | E147: =(Financials!C9-Financials!B9)/Financials!B9 -> 0.14182692 | F147: =(Financials!D9-Financials!C9)/Financials!C9 -> 0.10526316 | G147: =(Financials!E9-Financials!D9)/Financials!D9 -> 0.13714286 | H147: =(Financials!F9-Financials!E9)/Financials!E9 -> 0.085427136
B148: Gross Income | E148: =(Financials!C10-Financials!B10)/Financials!B10 -> -0.19974292 | F148: =(Financials!D10-Financials!C10)/Financials!C10 -> 0.15190454 | G148: =(Financials!E10-Financials!D10)/Financials!D10 -> -0.11822709 | H148: =(Financials!F10-Financials!E10)/Financials!E10 -> -0.036597763
B149: SG&A Expense | E149: =(Financials!C11-Financials!B11)/Financials!B11 -> -0.68989747 | F149: =(Financials!D11-Financials!C11)/Financials!C11 -> 0.64439306 | G149: =(Financials!E11-Financials!D11)/Financials!D11 -> 0.17196288 | H149: =(Financials!F11-Financials!E11)/Financials!E11 -> 0.041871626
B150: Other SG&A | E150: =(Financials!C12-Financials!B12)/Financials!B12 -> -0.68989747 | F150: =(Financials!D12-Financials!C12)/Financials!C12 -> 0.64439306 | G150: =(Financials!E12-Financials!D12)/Financials!D12 -> 0.17196288 | H150: =(Financials!F12-Financials!E12)/Financials!E12 -> 0.041871626
B151: Other Operating Expense | E151: - | F151: - | G151: - | H151: -
B152: EBIT (Operating Income) | E152: =(Financials!C14-Financials!B14)/Financials!B14 -> 0.67266462 | F152: =(Financials!D14-Financials!C14)/Financials!C14 -> -0.01060502 | G152: =(Financials!E14-Financials!D14)/Financials!D14 -> -0.27737508 | H152: =(Financials!F14-Financials!E14)/Financials!E14 -> -0.073204567
B153: Nonoperating Income - Net | E153: =(Financials!C15-Financials!B15)/Financials!B15 -> -1.9220571 | F153: =(Financials!D15-Financials!C15)/Financials!C15 -> -0.40544662 | G153: =(Financials!E15-Financials!D15)/Financials!D15 -> -0.84499817 | H153: =(Financials!F15-Financials!E15)/Financials!E15 -> -0.95981087
B154: Nonoperating Interest Income | E154: - | F154: - | G154: - | H154: -
B155: Other Income (Expense) | E155: =(Financials!C17-Financials!B17)/Financials!B17 -> -1.9220571 | F155: =(Financials!D17-Financials!C17)/Financials!C17 -> -0.40544662 | G155: =(Financials!E17-Financials!D17)/Financials!D17 -> -0.84499817 | H155: =(Financials!F17-Financials!E17)/Financials!E17 -> -0.95981087
B156: Interest Expense | E156: =(Financials!C18-Financials!B18)/Financials!B18 -> -0.0014619883 | F156: =(Financials!D18-Financials!C18)/Financials!C18 -> 0.016105417 | G156: =(Financials!E18-Financials!D18)/Financials!D18 -> 0.1167147 | H156: =(Financials!F18-Financials!E18)/Financials!E18 -> 0.11096774
B157: Gross Interest Expense | E157: =(Financials!C19-Financials!B19)/Financials!B19 -> -0.038910506 | F157: =(Financials!D19-Financials!C19)/Financials!C19 -> 0.01754386 | G157: =(Financials!E19-Financials!D19)/Financials!D19 -> 0.18435013 | H157: =(Financials!F19-Financials!E19)/Financials!E19 -> 0.099664054
B158: Interest Capitalized | E158: =(Financials!C20-Financials!B20)/Financials!B20 -> -0.33333333 | F158: =(Financials!D20-Financials!C20)/Financials!C20 -> 0.034482759 | G158: =(Financials!E20-Financials!D20)/Financials!D20 -> 0.96666667 | H158: =(Financials!F20-Financials!E20)/Financials!E20 -> 0.025423729
B159: Unusual Expense - Net | E159: =(Financials!C21-Financials!B21)/Financials!B21 -> 0.26969697 | F159: =(Financials!D21-Financials!C21)/Financials!C21 -> -0.575179 | G159: =(Financials!E21-Financials!D21)/Financials!D21 -> 1.505618 | H159: =(Financials!F21-Financials!E21)/Financials!E21 -> -0.10538117
B160: Impairments | E160: - | F160: - | G160: - | H160: -
B161: Other Intangibles | E161: - | F161: - | G161: - | H161: -
B162: Restructuring Expense | E162: =(Financials!C24-Financials!B24)/Financials!B24 -> 0.091954023 | F162: =(Financials!D24-Financials!C24)/Financials!C24 -> -0.53157895 | G162: =(Financials!E24-Financials!D24)/Financials!D24 -> 1.4438202 | H162: =(Financials!F24-Financials!E24)/Financials!E24 -> -0.25977011
B163: Unrealized Valuation Gain/Loss | E163: =(Financials!C25-Financials!B25)/Financials!B25 -> -3.1666667 | F163: =(Financials!D25-Financials!C25)/Financials!C25 -> -1 | G163: - | H163: =(Financials!F25-Financials!E25)/Financials!E25 -> -0.45454545
B164: Hedges/Derivatives | E164: =(Financials!C26-Financials!B26)/Financials!B26 -> -3.1666667 | F164: =(Financials!D26-Financials!C26)/Financials!C26 -> -1 | G164: - | H164: =(Financials!F26-Financials!E26)/Financials!E26 -> -0.45454545
B165: Pretax Income | E165: =(Financials!C27-Financials!B27)/Financials!B27 -> 7.9994577 | F165: =(Financials!D27-Financials!C27)/Financials!C27 -> -0.10665863 | G165: =(Financials!E27-Financials!D27)/Financials!D27 -> -0.42172007 | H165: =(Financials!F27-Financials!E27)/Financials!E27 -> -0.13192581
B166: Income Taxes | E166: =(Financials!C28-Financials!B28)/Financials!B28 -> 6.3952096 | F166: =(Financials!D28-Financials!C28)/Financials!C28 -> -0.11551957 | G166: =(Financials!E28-Financials!D28)/Financials!D28 -> -0.4308819 | H166: =(Financials!F28-Financials!E28)/Financials!E28 -> -0.10991957
B167: Income Taxes - Current Domestic | E167: =(Financials!C29-Financials!B29)/Financials!B29 -> 0.68477103 | F167: =(Financials!D29-Financials!C29)/Financials!C29 -> 0.44058154 | G167: =(Financials!E29-Financials!D29)/Financials!D29 -> -0.47038175 | H167: =(Financials!F29-Financials!E29)/Financials!E29 -> 0.048053024
B168: Income Taxes - Current Foreign | E168: =(Financials!C30-Financials!B30)/Financials!B30 -> 0.13809524 | F168: =(Financials!D30-Financials!C30)/Financials!C30 -> -0.023012552 | G168: =(Financials!E30-Financials!D30)/Financials!D30 -> -0.017130621 | H168: =(Financials!F30-Financials!E30)/Financials!E30 -> -0.10675381
B169: Income Taxes - Deferred Domestic | E169: =(Financials!C31-Financials!B31)/Financials!B31 -> -2.7918552 | F169: =(Financials!D31-Financials!C31)/Financials!C31 -> -0.72727273 | G169: =(Financials!E31-Financials!D31)/Financials!D31 -> -0.60648148 | H169: =(Financials!F31-Financials!E31)/Financials!E31 -> -0.95294118
B170: Income Taxes - Deferred Foreign | E170: =(Financials!C32-Financials!B32)/Financials!B32 -> 1.3461538 | F170: =(Financials!D32-Financials!C32)/Financials!C32 -> 0.62295082 | G170: =(Financials!E32-Financials!D32)/Financials!D32 -> -0.70707071 | H170: =(Financials!F32-Financials!E32)/Financials!E32 -> -1.7931034
B171: Consolidated Net Income | E171: =(Financials!C33-Financials!B33)/Financials!B33 -> 8.5979151 | F171: =(Financials!D33-Financials!C33)/Financials!C33 -> -0.10411171 | G171: =(Financials!E33-Financials!D33)/Financials!D33 -> -0.41912019 | H171: =(Financials!F33-Financials!E33)/Financials!E33 -> -0.13804413
B172: Net Income | E172: =(Financials!C34-Financials!B34)/Financials!B34 -> 8.5979151 | F172: =(Financials!D34-Financials!C34)/Financials!C34 -> -0.10411171 | G172: =(Financials!E34-Financials!D34)/Financials!D34 -> -0.41912019 | H172: =(Financials!F34-Financials!E34)/Financials!E34 -> -0.13804413
B173: Net Income available to Common | E173: =(Financials!C35-Financials!B35)/Financials!B35 -> 8.5979151 | F173: =(Financials!D35-Financials!C35)/Financials!C35 -> -0.10411171 | G173: =(Financials!E35-Financials!D35)/Financials!D35 -> -0.41912019 | H173: =(Financials!F35-Financials!E35)/Financials!E35 -> -0.13804413
B174: Per Share | E174: - | F174: - | G174: - | H174: -
B175: EPS (recurring) | E175: =(Financials!C37-Financials!B37)/Financials!B37 -> 7.3088918 | F175: =(Financials!D37-Financials!C37)/Financials!C37 -> -0.11155628 | G175: =(Financials!E37-Financials!D37)/Financials!D37 -> -0.38808446 | H175: =(Financials!F37-Financials!E37)/Financials!E37 -> -0.1325569
B176: EPS (basic) | E176: =(Financials!C38-Financials!B38)/Financials!B38 -> 8.521175 | F176: =(Financials!D38-Financials!C38)/Financials!C38 -> -0.10102859 | G176: =(Financials!E38-Financials!D38)/Financials!D38 -> -0.41100292 | H176: =(Financials!F38-Financials!E38)/Financials!E38 -> -0.13401032
B177: Basic Shares Outstanding | E177: =(Financials!C39-Financials!B39)/Financials!B39 -> 0.0080738178 | F177: =(Financials!D39-Financials!C39)/Financials!C39 -> -0.0034324943 | G177: =(Financials!E39-Financials!D39)/Financials!D39 -> -0.013777268 | H177: =(Financials!F39-Financials!E39)/Financials!E39 -> -0.0046565774
B178: Total Shares Outstanding | E178: =(Financials!C40-Financials!B40)/Financials!B40 -> 0.0057803468 | F178: =(Financials!D40-Financials!C40)/Financials!C40 -> -0.012873563 | G178: =(Financials!E40-Financials!D40)/Financials!D40 -> -0.0069864928 | H178: =(Financials!F40-Financials!E40)/Financials!E40 -> 0.0012898687
B179: EPS (diluted) | E179: =(Financials!C41-Financials!B41)/Financials!B41 -> 8.5214346 | F179: =(Financials!D41-Financials!C41)/Financials!C41 -> -0.10104148 | G179: =(Financials!E41-Financials!D41)/Financials!D41 -> -0.40898793 | H179: =(Financials!F41-Financials!E41)/Financials!E41 -> -0.133
B180: Diluted Shares Outstanding | E180: =(Financials!C42-Financials!B42)/Financials!B42 -> 0.0080367394 | F180: =(Financials!D42-Financials!C42)/Financials!C42 -> -0.0034168565 | G180: =(Financials!E42-Financials!D42)/Financials!D42 -> -0.017142857 | H180: =(Financials!F42-Financials!E42)/Financials!E42 -> -0.0046511628
B181: Total Shares Outstanding | E181: =(Financials!C43-Financials!B43)/Financials!B43 -> 0.0057803468 | F181: =(Financials!D43-Financials!C43)/Financials!C43 -> -0.012873563 | G181: =(Financials!E43-Financials!D43)/Financials!D43 -> -0.0069864928 | H181: =(Financials!F43-Financials!E43)/Financials!E43 -> 0.0012898687
B182: Earnings Persistence | E182: =(Financials!C44-Financials!B44)/Financials!B44 -> -0.012264515 | F182: =(Financials!D44-Financials!C44)/Financials!C44 -> -0.0035674667 | G182: =(Financials!E44-Financials!D44)/Financials!D44 -> 0.087165539 | H182: =(Financials!F44-Financials!E44)/Financials!E44 -> -0.0020015128
B183: Dividends per Share | E183: =(Financials!C45-Financials!B45)/Financials!B45 -> 0.0099009901 | F183: =(Financials!D45-Financials!C45)/Financials!C45 -> 0.49019608 | G183: =(Financials!E45-Financials!D45)/Financials!D45 -> 0.065789474 | H183: =(Financials!F45-Financials!E45)/Financials!E45 -> 0.0061728395
B184: Payout Ratio | E184: =(Financials!C46-Financials!B46)/Financials!B46 -> -0.89393395 | F184: =(Financials!D46-Financials!C46)/Financials!C46 -> 0.65769169 | G184: =(Financials!E46-Financials!D46)/Financials!D46 -> 0.80332946 | H184: =(Financials!F46-Financials!E46)/Financials!E46 -> 0.1605223
B185: EBITDA | E185: - | F185: - | G185: - | H185: -
B186: EBITDA | E186: =(Financials!C48-Financials!B48)/Financials!B48 -> 0.52458705 | F186: =(Financials!D48-Financials!C48)/Financials!C48 -> 0.0059775841 | G186: =(Financials!E48-Financials!D48)/Financials!D48 -> -0.21162416 | H186: =(Financials!F48-Financials!E48)/Financials!E48 -> -0.034780561
B187: EBIT | E187: =(Financials!C49-Financials!B49)/Financials!B49 -> 0.67266462 | F187: =(Financials!D49-Financials!C49)/Financials!C49 -> -0.01060502 | G187: =(Financials!E49-Financials!D49)/Financials!D49 -> -0.27737508 | H187: =(Financials!F49-Financials!E49)/Financials!E49 -> -0.073204567
B188: Depreciation & Amortization Expense | E188: =(Financials!C50-Financials!B50)/Financials!B50 -> 0.094514455 | F188: =(Financials!D50-Financials!C50)/Financials!C50 -> 0.079580088 | G188: =(Financials!E50-Financials!D50)/Financials!D50 -> 0.055834379 | H188: =(Financials!F50-Financials!E50)/Financials!E50 -> 0.072192513
B191: Standardized Annual Balance Sheet: Categorical Growth Rates
E193: 2020-2021 | F193: 2021-2022 | G193: 2022-2023 | H193: 2023-2024
B194: Cash & Short-Term Investments | E194: =(Financials!C55-Financials!B55)/Financials!B55 -> 0.67716909 | F194: =(Financials!D55-Financials!C55)/Financials!C55 -> -0.28301709 | G194: =(Financials!E55-Financials!D55)/Financials!D55 -> -0.20052666 | H194: =(Financials!F55-Financials!E55)/Financials!E55 -> 0.040513834
B195: Cash Only | E195: =(Financials!C56-Financials!B56)/Financials!B56 -> 0.73519459 | F195: =(Financials!D56-Financials!C56)/Financials!C56 -> -0.45372989 | G195: =(Financials!E56-Financials!D56)/Financials!D56 -> -0.42770439 | H195: =(Financials!F56-Financials!E56)/Financials!E56 -> 0.90642545
B196: Total Short Term Investments | E196: =(Financials!C57-Financials!B57)/Financials!B57 -> -0.16748768 | F196: =(Financials!D57-Financials!C57)/Financials!C57 -> 4.8964497 | G196: =(Financials!E57-Financials!D57)/Financials!D57 -> 0.43803312 | H196: =(Financials!F57-Financials!E57)/Financials!E57 -> -0.92812282
B197: Short-Term Receivables | E197: =(Financials!C58-Financials!B58)/Financials!B58 -> 0.16465681 | F197: =(Financials!D58-Financials!C58)/Financials!C58 -> 0.00358116 | G197: =(Financials!E58-Financials!D58)/Financials!D58 -> -0.11155069 | H197: =(Financials!F58-Financials!E58)/Financials!E58 -> -0.024011176
B198: Accounts Receivables, Net | E198: =(Financials!C59-Financials!B59)/Financials!B59 -> 0.16465681 | F198: =(Financials!D59-Financials!C59)/Financials!C59 -> 0.00358116 | G198: =(Financials!E59-Financials!D59)/Financials!D59 -> -0.11155069 | H198: =(Financials!F59-Financials!E59)/Financials!E59 -> -0.024011176
B199: Accounts Receivables, Gross | E199: =(Financials!C60-Financials!B60)/Financials!B60 -> 0.16172652 | F199: =(Financials!D60-Financials!C60)/Financials!C60 -> 0.0049333231 | G199: =(Financials!E60-Financials!D60)/Financials!D60 -> -0.11183554 | H199: =(Financials!F60-Financials!E60)/Financials!E60 -> -0.02288626
B200: Bad Debt/Doubtful Accounts | E200: =(Financials!C61-Financials!B61)/Financials!B61 -> -0.072463768 | F200: =(Financials!D61-Financials!C61)/Financials!C61 -> 0.140625 | G200: =(Financials!E61-Financials!D61)/Financials!D61 -> -0.1369863 | H200: =(Financials!F61-Financials!E61)/Financials!E61 -> 0.079365079
B201: Other Receivables | E201: - | F201: - | G201: - | H201: -
B202: Inventories | E202: =(Financials!C63-Financials!B63)/Financials!B63 -> 0.15645161 | F202: =(Financials!D63-Financials!C63)/Financials!C63 -> 0.23988842 | G202: =(Financials!E63-Financials!D63)/Financials!D63 -> 0.051743532 | H202: =(Financials!F63-Financials!E63)/Financials!E63 -> -0.11657754
B203: Raw Materials | E203: =(Financials!C64-Financials!B64)/Financials!B64 -> 0.15645161 | F203: =(Financials!D64-Financials!C64)/Financials!C64 -> -1 | G203: - | H203: -
B204: Other Current Assets | E204: =(Financials!C65-Financials!B65)/Financials!B65 -> -0.65393159 | F204: =(Financials!D65-Financials!C65)/Financials!C65 -> 0.080872914 | G204: =(Financials!E65-Financials!D65)/Financials!D65 -> 0.13182898 | H204: =(Financials!F65-Financials!E65)/Financials!E65 -> 0.036726128
...

Sheet Workshop #3
A3: Valuation Using Multiples of Comparable Firms
A5: Workshop 3
A6: Mathilde Sison, Averie Forshaw
A7: BUS 438
A8: Prof. Mahdi Rastad
A11: 2 | B11: Unadjusted Valuation Based on All Comparables
G12: EV/Sales | I12: EV/EBITDA | K12: P/E Ratio
B13: Median Value for all Comparable Firms | G13: =MEDIAN('Comparable Firms'!AZ5:AZ122) -> 1.17 | I13: =MEDIAN('Comparable Firms'!AX5:AX122) -> 9.12 | K13: =MEDIAN('Comparable Firms'!AO5:AO122) -> 16.815
A14: a | B14: UPS's Estimated Enterprise Value (in $000,000's) | G14: =G13*'Comparable Firms'!BY4 -> 104695.11 | I14: =I13*'Comparable Firms'!BZ4 -> 105974.4
A15: b | B15: UPS's Estimated Share Price | K15: =K13*Financials!F38 -> 113.71312
A30: 3 | B30: Unadjusted Valuation Based on Closest Comparables:
G31: EV/Sales | I31: EV/EBITDA | K31: P/E Ratio
B32: Median Value for Closest Comparable Firms | G32: =MEDIAN('Selective Comparable Firms'!AZ5:AZ9) -> 1.37 | I32: =MEDIAN('Selective Comparable Firms'!AX5:AX9) -> 11.36 | K32: =MEDIAN('Selective Comparable Firms'!AO5:AO9) -> 20.15
A33: a | B33: UPS's Estimated Enterprise Value (in $000,000's) | G33: =G32*'Selective Comparable Firms'!BY4 -> 122591.71 | I33: =I32*'Selective Comparable Firms'!BZ4 -> 132003.2
A34: b | B34: UPS's Estimated Share Price | K34: =K32*Financials!F38 -> 136.26639
A49: 8 | B49: Scatter Plots
A63: 9 | B63: Regression Results: Full Model
B65: SUMMARY OUTPUT
B67: Regression Statistics
B68: Multiple R | C68: 0.31708423
B69: R Square | C69: 0.10054241
B70: Adjusted R Square | C70: 0.036295439
B71: Standard Error | C71: 5.1827689
B72: Observations | C72: 46
B74: ANOVA
C75: df | D75: SS | E75: MS | F75: F | G75: Significance F
B76: Regression | C76: 3 | D76: 126.10769 | E76: 42.035897 | F76: 1.5649362 | G76: 0.21207129
B77: Residual | C77: 42 | D77: 1128.1659 | E77: 26.861093
B78: Total | C78: 45 | D78: 1254.2736
C80: Coefficients | D80: Standard Error | E80: t Stat | F80: P-value | G80: Lower 95% | H80: Upper 95% | I80: Lower 95.0% | J80: Upper 95.0%
B81: Intercept | C81: 6.1760073 | D81: 2.2737444 | E81: 2.7162276 | F81: 0.0095463067 | G81: 1.5874054 | H81: 10.764609 | I81: 1.5874054 | J81: 10.764609
B82: Historical growth in Revenues - Last 3 years | C82: 13.208067 | D82: 9.9502185 | E82: 1.3274148 | F82: 0.19154205 | G82: -6.8722865 | H82: 33.288421 | I82: -6.8722865 | J82: 33.288421
B83: Beta | C83: 3.2694495 | D83: 1.6733004 | E83: 1.9538927 | F83: 0.057394805 | G83: -0.10740752 | H83: 6.6463065 | I83: -0.10740752 | J83: 6.6463065
B84: Payout ratio | C84: 0.73061509 | D84: 2.8662392 | E84: 0.25490374 | F84: 0.80004151 | G84: -5.0536898 | H84: 6.51492 | I84: -5.0536898 | J84: 6.51492
A93: 10 | B93: Modified Regression Model: Reduced Model
B95: Dropped Payout Ratio
B96: SUMMARY OUTPUT
B98: Regression Statistics
B99: Multiple R | C99: 0.31488237
B100: R Square | C100: 0.099150907
B101: Adjusted R Square | C101: 0.05725095
B102: Standard Error | C102: 5.1261102
B103: Observations | C103: 46
B105: ANOVA
C106: df | D106: SS | E106: MS | F106: F | G106: Significance F
B107: Regression | C107: 2 | D107: 124.36237 | E107: 62.181183 | F107: 2.3663725 | G107: 0.10593
B108: Residual | C108: 43 | D108: 1129.9112 | E108: 26.277006
B109: Total | C109: 45 | D109: 1254.2736
C111: Coefficients | D111: Standard Error | E111: t Stat | F111: P-value | G111: Lower 95% | H111: Upper 95% | I111: Lower 95.0% | J111: Upper 95.0%
B112: Intercept | C112: 6.5390938 | D112: 1.7529063 | E112: 3.7304298 | F112: 0.0005552937 | G112: 3.0040214 | H112: 10.074166 | I112: 3.0040214 | J112: 10.074166
B113: Historical growth in Revenues - Last 3 years | C113: 12.328443 | D113: 9.2306459 | E113: 1.3355992 | F113: 0.18870718 | G113: -6.2869283 | H113: 30.943815 | I113: -6.2869283 | J113: 30.943815
B114: Beta | C114: 3.2214963 | D114: 1.6445151 | E114: 1.9589339 | F114: 0.056625678 | G114: -0.094984473 | H114: 6.537977 | I114: -0.094984473 | J114: 6.537977
A116: 11 | B116: Valuation Based on Model Forecast for Adjusted Multiple
C119: Coefficients
B120: Intercept | C120: 6.5390938
B121: Historical growth in Revenues - Last 3 years | C121: 12.328443
B122: Beta | C122: 3.2214963
B126: UPS Values
B127: Historical growth in Revenues - Last 3 years | C127: ='CF Multiples Final'!C1 -> -0.0398
B128: Beta | C128: ='CF Multiples Final'!D1 -> 0.78
B130: Adjusted EV/ EBITDA for UPS: | D130: =C120+(C121*C127)+(C122*C128) -> 8.5611888
B131: Raw EV/ EBITDA for UPS: | D131: ='CF Multiples Final'!B1 -> 8.55
B133: % Difference: | D133: =(D130-D131)/D131 -> 0.0013086336
A136: 12 | B136: Comparison of Adjusted vs. Unadjusted Valuation
B138: UPS's EV/ EBITDA (Raw) | D138: ='CF Multiples Final'!B1 -> 8.55
B139: UPS's Share Price (Raw) | D139: ='Workshop #2'!D11 -> 108.03
B140: UPS's Growth (Raw) | D140: ='CF Multiples Final'!C1 -> -0.0398
B141: UPS's Beta (Raw) | D141: ='CF Multiples Final'!D1 -> 0.78
B143: UPS's EV/ EBITDA (Adjusted) | D143: =D130 -> 8.5611888
B144: UPS's EV in $000,000's (Adjusted) | D144: =D143*'Comparable Firms'!BZ4 -> 99481.014
B145: UPS's Share Price (Adjusted) | D145: =D144/Financials!F39 -> 116.35206
F147: % Difference from Valuation Based on All Comparables | G147: % Difference from Valuation Based on Close Comparables
B148: UPS's Share Price (Adjusted)= | E148: =D145 -> 116.35206 | F148: =(D145-K15)/K15 -> 0.023207034 | H148: =(D145-K34)/K34 -> -0.14614262
F149: EV/ Sales EV Est. | G149: EV/ EBITDA EV Est. | H149: EV/ Sales Est. | I149: EV/EBITDA EV Est.
B150: UPS's EV in $000,000's (Adjusted)= | E150: =D144 -> 99481.014 | F150: =(D144-G14)/G14 -> -0.049802669 | G150: =(D144-I14)/I14 -> -0.061273156 | H150: =(D144-G33)/G33 -> -0.18851761 | I150: =(D144-I33)/I33 -> -0.24637422

Sheet Workshop #4
A3: Forcasting Growth
A5: Workshop 4
A6: Mathilde Sison, Averie Forshaw
A7: BUS 438
A8: Prof. Mahdi Rastad
B11: 3
B12: a | C12: First Guess Confidence Interval for 10-Year CAGR: | I12: [2%, 8%] | J12: Source: WS4 Exhibit 5.1
C13: median Estimate of 10-Year Industry CAGR: | I13: 0.05 | J13: Source: WS4 Exhibit 5.1
B16: b(i) | C16: Portfolio Momentum: E-commerce and global trade support moderate industry growth
B17: b(ii) | C17: Mergers & Acquisitions: UPS uses limited M&A, not a major growth driver
B18: b(iii) | C18: Market Share Performance: Highly competitive industry, large share gains are unlikely
B19: Conclusion: | C19: Growth is moderate, so 8% upper bound may be too high [2%, 6%]
B22: c | C22: Growth Sustainability: UPS does not depend on new product launches, as it provides recurring logistics services. Growth is sustainable but moderate and tied to economic cycles.
B25: d | C25: Growth Stability: Based on Exhibit 5.9, transportation growth over the last 40 years roughly ranges from: 2% to 10%. The spread is fairly wide spread, meaning growth is not very stable.
C27: Exhibit 5.9 Range of Median Industry Growth (40 Years) | I27: [2%, 10%]
B29: e | C29: Growth Convergence: Based on Exhibit 5.10 the firms with moderate growth (5-10%) tend to maintain about 5% growth short term. Over time, growth decays and converges toward industry medians. UPS's short term growth is estimated at approximately 5%, while long term growth is expected to converge towards 2-3%
C31: Exhibit 5.10 Short-Term Growth Estimate | I31: 0.05
C32: Exhibit 5.10 Long-Term Growth Estimate | I32: 2-3%
B34: f | C34: Analysts Estimates: Yahoo!Finance reports strong next-year growth (12.68%), but this is only short-term. UPS's 2026 revenue guidance implies only about 1% growth. Adjusting analyst optimism downward and considering long-term convergence, a reasonable growth estimate is 3-6% with a point estimate of 4%.
C36: Analysts Final Confidence Interval | I36: [3%, 6%]
C37: Analysts Final Point Estimate | I37: 0.04
B40: 4
B41: b(I,ii,iii)
B81: c
D87: Arithmetic | E87: Geometric | F87: Std. Dev. | G87: Range
B88: d(i,ii,iii) | C88: Revenue Growth | D88: =AVERAGE('UPS - Income Statement - Annual'!AH5:AH29) -> 0.046718153 | E88: =('UPS - Income Statement - Annual'!B6/'UPS - Income Statement - Annual'!AA6)^(1/25)-1 -> 0.044618152 | F88: =STDEV('UPS - Income Statement - Annual'!AH5:AH29) -> 0.066711607 | G88: =(MAX('UPS - Income Statement - Annual'!AH5:AH29)-MIN('UPS - Income Statement - Annual'!AH5:AH29)) -> 0.28419519
C89: EBIT Growth | D89: =AVERAGE('UPS - Income Statement - Annual'!AK5:AK29) -> 0.4874218 | E89: =('UPS - Income Statement - Annual'!B16/'UPS - Income Statement - Annual'!AA16)^(1/25)-1 -> 0.022486546 | F89: =STDEV('UPS - Income Statement - Annual'!AK5:AK29) -> 1.8729447 | G89: =(MAX('UPS - Income Statement - Annual'!AK5:AK29)-MIN('UPS - Income Statement - Annual'!AK5:AK29)) -> 9.2243049
C90: EPS Growth | D90: =AVERAGE('UPS - Income Statement - Annual'!AN5:AN29) -> 0.74519584 | E90: =('UPS - Income Statement - Annual'!B24/'UPS - Income Statement - Annual'!AA24)^(1/25)-1 -> 0.038682477 | F90: =STDEV('UPS - Income Statement - Annual'!AN5:AN29) -> 2.3746326 | G90: =(MAX('UPS - Income Statement - Annual'!AN5:AN29)-MIN('UPS - Income Statement - Annual'!AN5:AN29)) -> 9.4846578
C92: Geometric Average is More reliable because it reflects compounded growth.
B95: e(i) | C95: SUMMARY OUTPUT
C96: Ln(Revenue) vs. Time
C98: Regression Statistics
C99: Multiple R | D99: 0.9753217
C100: R Square | D100: 0.95125242
C101: Adjusted R Square | D101: 0.94922127
C102: Standard Error | D102: 0.083233744
C103: Observations | D103: 26
C105: ANOVA
D106: df | E106: SS | F106: MS | G106: F | H106: Significance F
C107: Regression | D107: 1 | E107: 3.2445376 | F107: 3.2445376 | G107: 468.33212 | H107: 2.9699467e-17
C108: Residual | D108: 24 | E108: 0.16626855 | F108: 0.0069278562
C109: Total | D109: 25 | E109: 3.4108061
D111: Coefficients | E111: Standard Error | F111: t Stat | G111: P-value | H111: Lower 95% | I111: Upper 95% | J111: Lower 95.0% | K111: Upper 95.0%
C112: Intercept | D112: -83.857097 | E112: 4.3801643 | F112: -19.144738 | G112: 4.8172527e-16 | H112: -92.897312 | I112: -74.816882 | J112: -92.897312 | K112: -74.816882
C113: Year | D113: 0.04710082 | E113: 0.002176464 | F113: 21.640982 | G113: 2.9699467e-17 | H113: 0.042608819 | I113: 0.051592821 | J113: 0.042608819 | K113: 0.051592821
B115: e(ii) | C115: Slope Coefficient | E115: =D113 -> 0.04710082 | F115: (Average Historical Compounded Average Growth Rate)
C116: Confidence Interval (Lower 95%, Upper 95%) | G116: =J113 -> 0.042608819 | I116: =K113 -> 0.051592821
B119: 5 | G119: 2025
C120: Total Dividends ($000,000's) | G120: ='UPS - Income Statement - Annual'!B32*'UPS - Income Statement - Annual'!B27 -> 5569.44
C121: Net Income ($000,000's) | G121: ='UPS - Income Statement - Annual'!B22 -> 5572
C122: Retention Ratio | G122: =1-(G120/G121) -> 0.00045944006
C123: ROA | G123: =G121/'UPS - Balance Sheet - Annual'!C22 -> 0.07952048
C124: ROE | G124: =G121/'UPS - Balance Sheet - Annual'!C47 -> 0.33329346
B125: (a) | C125: Internal Growth Rate: | G125: =G123*G122 -> 3.6534894e-05
B126: (b) | C126: Sustainable Growth Rate: | G126: =G124*G122 -> 0.00015312836
B129: 6
B130: (a) | C130: Summary- Est. Growth Rates | F130: Medium-Term | H130: Long-Term
E131: 3a | F131: 0.05
E132: 3e | F132: 0.05 | H132: 2-3%
E133: 3f | F133: 0.04
E134: 4d | F134: =E88 -> 0.044618152
E135: 4e | F135: =EXP(E115)-1 -> 0.048227686
C136: Int. Growth Rate | E136: 5a | H136: =G125 -> 3.6534894e-05
C137: Sust. Growth Rate | E137: 5b | H137: =G126 -> 0.00015312836
C139: Forecasted Medium-Term Growth Rate (g1) | G139: 0.04
C140: Forecasted Long-Term Growth Rate (g2) | G140: ='Workshop #8'!D131 -> 0.025

Sheet Workshop #5
B2: Capital Budgeting and Pro-Forma Analysis
B4: Workshop 5
B5: Mathilde Sison, Averie Forshaw
B6: BUS 438
B7: Prof. Mahdi Rastad
B9: 1 | D9: 2020 | E9: 2021 | F9: 2022 | G9: 2023 | H9: 2024
C10: Taxable Income | D10: =Financials!B34+Financials!B28 -> 1844 | E10: =Financials!C34+Financials!C28 -> 16595 | F10: =Financials!D34+Financials!D28 -> 14825 | G10: =Financials!E34+Financials!E28 -> 8573 | H10: =Financials!F34+Financials!F28 -> 7442
C11: Taxation | D11: =Financials!B28 -> 501 | E11: =Financials!C28 -> 3705 | F11: =Financials!D28 -> 3277 | G11: =Financials!E28 -> 1865 | H11: =Financials!F28 -> 1660
C12: Tax Rate | D12: =D11/D10 -> 0.27169197 | E12: =E11/E10 -> 0.22326002 | F12: =F11/F10 -> 0.22104553 | G12: =G11/G10 -> 0.21754345 | H12: =H11/H10 -> 0.22305832
B14: a(i) | C14: Medium-Term Growth Rate (g1) | G14: ='Workshop #4'!G139 -> 0.04
C15: Long-Term Growth Rate (g2) | G15: ='Workshop #4'!G140 -> 0.025
C16: Growth Rate Being Used | G16: =G14 -> 0.04
C17: Average Tax-Rate (2020-2024) | G17: =AVERAGE(D12:H12) -> 0.23131986
C18: Target Payout Ratio | G18: =AVERAGE('Workshop #2'!C280:G280) -> 1.0307268
C19: Cost of Debt | G19: ='Workshop #6'!E199 -> 0.048738912
C20: Risk-Free Rate | G20: ='Workshop #6'!D28 -> 0.0426
C22: Original Forecast | M22: 1st Revision
C23: Income Statement | D23: % of Sales | H23: Forecasted Years | M23: Income Statement | N23: % of Sales | R23: Forecasted Years
C24: Report Date | E24: =2024 -> 2024 | F24: 2025 | G24: 2026 | H24: 2027 | I24: 2028 | J24: 2029 | M24: Report Date | O24: =E24 -> 2024 | P24: =F24 -> 2025 | Q24: =G24 -> 2026 | R24: =H24 -> 2027 | S24: =I24 -> 2028 | T24: =J24 -> 2029
C25: Sales | D25: =E25/$E$25 -> 1 | E25: =Financials!$F$4 -> 90894 | F25: =E25*(1+$G$16) -> 94529.76 | G25: =F25*(1+$G$16) -> 98310.95 | H25: =G25*(1+$G$16) -> 102243.39 | I25: =H25*(1+$G$16) -> 106333.12 | J25: =I25*(1+$G$16) -> 110586.45 | M25: Sales | N25: =O25/$E$25 -> 1 | O25: =Financials!$F$4 -> 90894 | P25: =O25*(1+$G$16) -> 94529.76 | Q25: =P25*(1+$G$16) -> 98310.95 | R25: =Q25*(1+$G$16) -> 102243.39 | S25: =R25*(1+$G$16) -> 106333.12 | T25: =S25*(1+$G$16) -> 110586.45
C26: COGS | D26: =E26/$E$25 -> 0.81233085 | E26: =Financials!$F$5 -> 73836 | F26: =F$25*$D26 -> 76789.44 | G26: =G$25*$D26 -> 79861.018 | H26: =H$25*$D26 -> 83055.458 | I26: =I$25*$D26 -> 86377.677 | J26: =J$25*$D26 -> 89832.784 | M26: COGS | N26: =O26/$E$25 -> 0.81233085 | O26: =Financials!$F$5 -> 73836 | P26: =P$25*$D26 -> 76789.44 | Q26: =Q$25*$D26 -> 79861.018 | R26: =R$25*$D26 -> 83055.458 | S26: =S$25*$D26 -> 86377.677 | T26: =T$25*$D26 -> 89832.784
C27: Gross Income | D27: =E27/$E$25 -> 0.18766915 | E27: =E25-E26 -> 17058 | F27: =F25-F26 -> 17740.32 | G27: =G25-G26 -> 18449.933 | H27: =H25-H26 -> 19187.93 | I27: =I25-I26 -> 19955.447 | J27: =J25-J26 -> 20753.665 | M27: Gross Income | N27: =O27/$E$25 -> 0.18766915 | O27: =O25-O26 -> 17058 | P27: =P25-P26 -> 17740.32 | Q27: =Q25-Q26 -> 18449.933 | R27: =R25-R26 -> 19187.93 | S27: =S25-S26 -> 19955.447 | T27: =T25-T26 -> 20753.665
C28: Depreciation & Amortizaton | D28: =E28/$E$25 -> 0.039705591 | E28: =Financials!$F$8+Financials!$F$9 -> 3609 | F28: =F$25*$D28 -> 3753.36 | G28: =G$25*$D28 -> 3903.4944 | H28: =H$25*$D28 -> 4059.6342 | I28: =I$25*$D28 -> 4222.0195 | J28: =J$25*$D28 -> 4390.9003 | M28: Depreciation & Amortizaton | N28: =O28/$E$25 -> 0.039705591 | O28: =Financials!$F$8+Financials!$F$9 -> 3609 | P28: =P$25*$D28 -> 3753.36 | Q28: =Q$25*$D28 -> 3903.4944 | R28: =R$25*$D28 -> 4059.6342 | S28: =S$25*$D28 -> 4222.0195 | T28: =T$25*$D28 -> 4390.9003
C29: SG&A | D29: =E29/$E$25 -> 0.09553986 | E29: =Financials!$F$11 -> 8684 | F29: =F$25*$D29 -> 9031.36 | G29: =G$25*$D29 -> 9392.6144 | H29: =H$25*$D29 -> 9768.319 | I29: =I$25*$D29 -> 10159.052 | J29: =J$25*$D29 -> 10565.414 | M29: SG&A | N29: =O29/$E$25 -> 0.09553986 | O29: =Financials!$F$11 -> 8684 | P29: =P$25*$D29 -> 9031.36 | Q29: =Q$25*$D29 -> 9392.6144 | R29: =R$25*$D29 -> 9768.319 | S29: =S$25*$D29 -> 10159.052 | T29: =T$25*$D29 -> 10565.414
C30: Other Operating Expense | D30: =E30/$E$25 -> 0.003421568 | E30: =-Financials!$F$13 -> 311 | F30: =F$25*$D30 -> 323.44 | G30: =G$25*$D30 -> 336.3776 | H30: =H$25*$D30 -> 349.8327 | I30: =I$25*$D30 -> 363.82601 | J30: =J$25*$D30 -> 378.37905 | M30: Other Operating Expense | N30: =O30/$E$25 -> 0.003421568 | O30: =-Financials!$F$13 -> 311 | P30: =P$25*$D30 -> 323.44 | Q30: =Q$25*$D30 -> 336.3776 | R30: =R$25*$D30 -> 349.8327 | S30: =S$25*$D30 -> 363.82601 | T30: =T$25*$D30 -> 378.37905
C31: Operating Income (EBIT) | D31: =E31/$E$25 -> 0.095550861 | E31: =E27-E29+E30 -> 8685 | F31: =F27-F29+F30 -> 9032.4 | G31: =G27-G29+G30 -> 9393.696 | H31: =H27-H29+H30 -> 9769.4438 | I31: =I27-I29+I30 -> 10160.222 | J31: =J27-J29+J30 -> 10566.63 | M31: Operating Income (EBIT) | N31: =O31/$E$25 -> 0.095550861 | O31: =O27-O29+O30 -> 8685 | P31: =P27-P29+P30 -> 9032.4 | Q31: =Q27-Q29+Q30 -> 9393.696 | R31: =R27-R29+R30 -> 9769.4438 | S31: =S27-S29+S30 -> 10160.222 | T31: =T27-T29+T30 -> 10566.63
C32: Other Income (Expense) | D32: =E32/$E$25 -> 0.00018703105 | E32: =Financials!$F$17 -> 17 | F32: =F$25*$D32 -> 17.68 | G32: =G$25*$D32 -> 18.3872 | H32: =H$25*$D32 -> 19.122688 | I32: =I$25*$D32 -> 19.887596 | J32: =J$25*$D32 -> 20.683099 | M32: Other Income (Expense) | N32: =O32/$E$25 -> 0.00018703105 | O32: =Financials!$F$17 -> 17 | P32: =P$25*$D32 -> 17.68 | Q32: =Q$25*$D32 -> 18.3872 | R32: =R$25*$D32 -> 19.122688 | S32: =S$25*$D32 -> 19.887596 | T32: =T$25*$D32 -> 20.683099
C33: Interest Expense | D33: =E33/$E$25 -> 0.0094725724 | E33: =Financials!$F$18 -> 861 | F33: =$E$33 -> 861 | G33: =$E$33 -> 861 | H33: =$E$33 -> 861 | I33: =$E$33 -> 861 | J33: =$E$33 -> 861 | M33: Interest Expense | N33: =O33/$E$25 -> 0.0094725724 | O33: =Financials!$F$18 -> 861 | P33: =(O60+O63)*$G$19-(O45-E45)*$G$20 -> 1250.2506 | Q33: =(P60+P63)*$G$19-(P45-F45)*$G$20 -> 590.47192 | R33: =(Q60+Q63)*$G$19-(Q45-G45)*$G$20 -> 671.51927 | S33: =(R60+R63)*$G$19-(R45-H45)*$G$20 -> 763.09752 | T33: =(S60+S63)*$G$19-(S45-I45)*$G$20 -> 858.3389
C34: Unusual Expense | D34: =E34/$E$25 -> 0.0043897287 | E34: =Financials!$F$21 -> 399 | F34: =F$25*$D34 -> 414.96 | G34: =G$25*$D34 -> 431.5584 | H34: =H$25*$D34 -> 448.82074 | I34: =I$25*$D34 -> 466.77357 | J34: =J$25*$D34 -> 485.44451 | M34: Unusual Expense | N34: =O34/$E$25 -> 0.0043897287 | O34: =Financials!$F$21 -> 399 | P34: =P$25*$D34 -> 414.96 | Q34: =Q$25*$D34 -> 431.5584 | R34: =R$25*$D34 -> 448.82074 | S34: =S$25*$D34 -> 466.77357 | T34: =T$25*$D34 -> 485.44451
C35: Earnings Before Tax | D35: =E35/$E$25 -> 0.081875591 | E35: =E31+E32-E33-E34 -> 7442 | F35: =F31+F32-F33-F34 -> 7774.12 | G35: =G31+G32-G33-G34 -> 8119.5248 | H35: =H31+H32-H33-H34 -> 8478.7458 | I35: =I31+I32-I33-I34 -> 8852.3356 | J35: =J31+J32-J33-J34 -> 9240.869 | M35: Earnings Before Tax | N35: =O35/$E$25 -> 0.081875591 | O35: =O31+O32-O33-O34 -> 7442 | P35: =P31+P32-P33-P34 -> 7384.8694 | Q35: =Q31+Q32-Q33-Q34 -> 8390.0529 | R35: =R31+R32-R33-R34 -> 8668.2265 | S35: =S31+S32-S33-S34 -> 8950.2381 | T35: =T31+T32-T33-T34 -> 9243.5302
C36: Income Tax | D36: =E36/$E$25 -> 0.018263032 | E36: =Financials!$F$28 -> 1660 | F36: =F$25*$D36 -> 1726.4 | G36: =G$25*$D36 -> 1795.456 | H36: =H$25*$D36 -> 1867.2742 | I36: =I$25*$D36 -> 1941.9652 | J36: =J$25*$D36 -> 2019.6438 | M36: Income Tax | N36: =O36/$E$25 -> 0.018263032 | O36: =Financials!$F$28 -> 1660 | P36: =P$25*$D36 -> 1726.4 | Q36: =Q$25*$D36 -> 1795.456 | R36: =R$25*$D36 -> 1867.2742 | S36: =S$25*$D36 -> 1941.9652 | T36: =T$25*$D36 -> 2019.6438
C37: Net Income | D37: =E37/$E$25 -> 0.06361256 | E37: =E35-E36 -> 5782 | F37: =F35-F36 -> 6047.72 | G37: =G35-G36 -> 6324.0688 | H37: =H35-H36 -> 6611.4716 | I37: =I35-I36 -> 6910.3704 | J37: =J35-J36 -> 7221.2252 | M37: Net Income | N37: =O37/$E$25 -> 0.06361256 | O37: =O35-O36 -> 5782 | P37: =P35-P36 -> 5658.4694 | Q37: =Q35-Q36 -> 6594.5969 | R37: =R35-R36 -> 6800.9523 | S37: =S35-S36 -> 7008.2729 | T37: =T35-T36 -> 7223.8863
C39: Dividends | D39: =E39/$E$25 -> 0.05939886 | E39: =-Financials!$F$150 -> 5399 | F39: =F$25*$D39 -> 5614.96 | G39: =G$25*$D39 -> 5839.5584 | H39: =H$25*$D39 -> 6073.1407 | I39: =I$25*$D39 -> 6316.0664 | J39: =J$25*$D39 -> 6568.709 | M39: Dividends | N39: =O39/$E$25 -> 0.05939886 | O39: =-Financials!$F$150 -> 5399 | P39: =P$25*$D39 -> 5614.96 | Q39: =Q$25*$D39 -> 5839.5584 | R39: =R$25*$D39 -> 6073.1407 | S39: =S$25*$D39 -> 6316.0664 | T39: =T$25*$D39 -> 6568.709
C40: Incremental Retained Earnings | D40: =E40/$E$25 -> 0.22974014 | E40: =Financials!$F$107 -> 20882 | F40: =F$25*$D40 -> 21717.28 | G40: =G$25*$D40 -> 22585.971 | H40: =H$25*$D40 -> 23489.41 | I40: =I$25*$D40 -> 24428.986 | J40: =J$25*$D40 -> 25406.146 | M40: Incremental Retained Earnings | N40: =O40/$E$25 -> 0.22974014 | O40: =Financials!$F$107 -> 20882 | P40: =P$25*$D40 -> 21717.28 | Q40: =Q$25*$D40 -> 22585.971 | R40: =R$25*$D40 -> 23489.41 | S40: =S$25*$D40 -> 24428.986 | T40: =T$25*$D40 -> 25406.146
M41: Diff in Incr. Ret. Earnings | O41: =O40-E40 -> 0 | P41: =P40-F40 -> 0 | Q41: =Q40-G40 -> 0 | R41: =R40-H40 -> 0 | S41: =S40-I40 -> 0 | T41: =T40-J40 -> 0
C43: Balance Sheet | M43: Balance Sheet
C44: Report Date | E44: 2024 | F44: 2025 | G44: 2026 | H44: 2027 | I44: 2028 | J44: 2029 | M44: Report Date | O44: =E44 -> 2024 | P44: =F44 -> 2025 | Q44: =G44 -> 2026 | R44: =H44 -> 2027 | S44: =I44 -> 2028 | T44: =J44 -> 2029
C45: Cash & ST Investments | D45: =E45/$E$25 -> 0.069509539 | E45: =Financials!$F$55 -> 6318 | F45: =F$25*$D45 -> 6570.72 | G45: =G$25*$D45 -> 6833.5488 | H45: =H$25*$D45 -> 7106.8908 | I45: =I$25*$D45 -> 7391.1664 | J45: =J$25*$D45 -> 7686.813 | M45: Cash & ST Investments | N45: =O45/$E$25 -> 0.069509539 | O45: =Financials!$F$55 -> 6318 | P45: =P$25*$D45 -> 6570.72 | Q45: =Q$25*$D45 -> 6833.5488 | R45: =R$25*$D45 -> 7106.8908 | S45: =S$25*$D45 -> 7391.1664 | T45: =T$25*$D45 -> 7686.813
C46: Receivables ST | D46: =E46/$E$25 -> 0.12447466 | E46: =Financials!$F$60 -> 11314 | F46: =F$25*$D46 -> 11766.56 | G46: =G$25*$D46 -> 12237.222 | H46: =H$25*$D46 -> 12726.711 | I46: =I$25*$D46 -> 13235.78 | J46: =J$25*$D46 -> 13765.211 | M46: Receivables ST | N46: =O46/$E$25 -> 0.12447466 | O46: =Financials!$F$60 -> 11314 | P46: =P$25*$D46 -> 11766.56 | Q46: =Q$25*$D46 -> 12237.222 | R46: =R$25*$D46 -> 12726.711 | S46: =S$25*$D46 -> 13235.78 | T46: =T$25*$D46 -> 13765.211
C47: Bad Debt | D47: =E47/$E$25 -> 0.0014962484 | E47: =-Financials!$F$61 -> 136 | F47: =F$25*$D47 -> 141.44 | G47: =G$25*$D47 -> 147.0976 | H47: =H$25*$D47 -> 152.9815 | I47: =I$25*$D47 -> 159.10076 | J47: =J$25*$D47 -> 165.46479 | M47: Bad Debt | N47: =O47/$E$25 -> 0.0014962484 | O47: =-Financials!$F$61 -> 136 | P47: =P$25*$D47 -> 141.44 | Q47: =Q$25*$D47 -> 147.0976 | R47: =R$25*$D47 -> 152.9815 | S47: =S$25*$D47 -> 159.10076 | T47: =T$25*$D47 -> 165.46479
C48: Inventories | D48: =E48/$E$25 -> 0.0090875085 | E48: =Financials!$F$63 -> 826 | F48: =F$25*$D48 -> 859.04 | G48: =G$25*$D48 -> 893.4016 | H48: =H$25*$D48 -> 929.13766 | I48: =I$25*$D48 -> 966.30317 | J48: =J$25*$D48 -> 1004.9553 | M48: Inventories | N48: =O48/$E$25 -> 0.0090875085 | O48: =Financials!$F$63 -> 826 | P48: =P$25*$D48 -> 859.04 | Q48: =Q$25*$D48 -> 893.4016 | R48: =R$25*$D48 -> 929.13766 | S48: =S$25*$D48 -> 966.30317 | T48: =T$25*$D48 -> 1004.9553
C49: Other Current Assets | D49: =E49/$E$25 -> 0.010869804 | E49: =Financials!$F$65 -> 988 | F49: =F$25*$D49 -> 1027.52 | G49: =G$25*$D49 -> 1068.6208 | H49: =H$25*$D49 -> 1111.3656 | I49: =I$25*$D49 -> 1155.8203 | J49: =J$25*$D49 -> 1202.0531 | M49: Other Current Assets | N49: =O49/$E$25 -> 0.010869804 | O49: =Financials!$F$65 -> 988 | P49: =P$25*$D49 -> 1027.52 | Q49: =Q$25*$D49 -> 1068.6208 | R49: =R$25*$D49 -> 1111.3656 | S49: =S$25*$D49 -> 1155.8203 | T49: =T$25*$D49 -> 1202.0531
C50: Total Current Assets | D50: =E50/$E$25 -> 0.21244527 | E50: =E45+E46-E47+E48+E49 -> 19310 | F50: =F45+F46-F47+F48+F49 -> 20082.4 | G50: =G45+G46-G47+G48+G49 -> 20885.696 | H50: =H45+H46-H47+H48+H49 -> 21721.124 | I50: =I45+I46-I47+I48+I49 -> 22589.969 | J50: =J45+J46-J47+J48+J49 -> 23493.568 | M50: Total Current Assets | N50: =O50/$E$25 -> 0.21244527 | O50: =O45+O46-O47+O48+O49 -> 19310 | P50: =P45+P46-P47+P48+P49 -> 20082.4 | Q50: =Q45+Q46-Q47+Q48+Q49 -> 20885.696 | R50: =R45+R46-R47+R48+R49 -> 21721.124 | S50: =S45+S46-S47+S48+S49 -> 22589.969 | T50: =T45+T46-T47+T48+T49 -> 23493.568
C51: Gross PP&E | D51: =E51/$E$25 -> 0.85203644 | E51: =Financials!$F$69 -> 77445 | F51: =F$25*$D51 -> 80542.8 | G51: =G$25*$D51 -> 83764.512 | H51: =H$25*$D51 -> 87115.092 | I51: =I$25*$D51 -> 90599.696 | J51: =J$25*$D51 -> 94223.684 | M51: Gross PP&E | N51: =O51/$E$25 -> 0.85203644 | O51: =Financials!$F$69 -> 77445 | P51: =P$25*$D51 -> 80542.8 | Q51: =Q$25*$D51 -> 83764.512 | R51: =R$25*$D51 -> 87115.092 | S51: =S$25*$D51 -> 90599.696 | T51: =T$25*$D51 -> 94223.684
C52: Accumulated Depr | D52: =E52/$E$25 -> 0.39735296 | E52: =Financials!$F$77 -> 36117 | F52: =F$25*$D52 -> 37561.68 | G52: =G$25*$D52 -> 39064.147 | H52: =H$25*$D52 -> 40626.713 | I52: =I$25*$D52 -> 42251.782 | J52: =J$25*$D52 -> 43941.853 | M52: Accumulated Depr | N52: =O52/$E$25 -> 0.39735296 | O52: =Financials!$F$77 -> 36117 | P52: =P$25*$D52 -> 37561.68 | Q52: =Q$25*$D52 -> 39064.147 | R52: =R$25*$D52 -> 40626.713 | S52: =S$25*$D52 -> 42251.782 | T52: =T$25*$D52 -> 43941.853
C53: Net PP&E | D53: =E53/$E$25 -> 0.45468348 | E53: =E51-E52 -> 41328 | F53: =F51-F52 -> 42981.12 | G53: =G51-G52 -> 44700.365 | H53: =H51-H52 -> 46488.379 | I53: =I51-I52 -> 48347.915 | J53: =J51-J52 -> 50281.831 | M53: Net PP&E | N53: =O53/$E$25 -> 0.45468348 | O53: =O51-O52 -> 41328 | P53: =P51-P52 -> 42981.12 | Q53: =Q51-Q52 -> 44700.365 | R53: =R51-R52 -> 46488.379 | S53: =S51-S52 -> 48347.915 | T53: =T51-T52 -> 50281.831
C54: Intangible Assets | D54: =E54/$E$25 -> 0.081017449 | E54: =Financials!$F$81 -> 7364 | F54: =F$25*$D54 -> 7658.56 | G54: =G$25*$D54 -> 7964.9024 | H54: =H$25*$D54 -> 8283.4985 | I54: =I$25*$D54 -> 8614.8384 | J54: =J$25*$D54 -> 8959.432 | M54: Intangible Assets | N54: =O54/$E$25 -> 0.081017449 | O54: =Financials!$F$81 -> 7364 | P54: =P$25*$D54 -> 7658.56 | Q54: =Q$25*$D54 -> 7964.9024 | R54: =R$25*$D54 -> 8283.4985 | S54: =S$25*$D54 -> 8614.8384 | T54: =T$25*$D54 -> 8959.432
C55: Other Assets | D55: =E55/$E$25 -> 0.016029661 | E55: =Financials!$F$85 -> 1457 | F55: =F$25*$D55 -> 1515.28 | G55: =G$25*$D55 -> 1575.8912 | H55: =H$25*$D55 -> 1638.9268 | I55: =I$25*$D55 -> 1704.4839 | J55: =J$25*$D55 -> 1772.6633 | M55: Other Assets | N55: =O55/$E$25 -> 0.016029661 | O55: =Financials!$F$85 -> 1457 | P55: =P$25*$D55 -> 1515.28 | Q55: =Q$25*$D55 -> 1575.8912 | R55: =R$25*$D55 -> 1638.9268 | S55: =S$25*$D55 -> 1704.4839 | T55: =T$25*$D55 -> 1772.6633
C56: Long-Term Investments | D56: =E56/$E$25 -> 0.0054899113 | E56: =Financials!$F$78 -> 499 | F56: =F$25*$D56 -> 518.96 | G56: =G$25*$D56 -> 539.7184 | H56: =H$25*$D56 -> 561.30714 | I56: =I$25*$D56 -> 583.75942 | J56: =J$25*$D56 -> 607.1098 | M56: Long-Term Investments | N56: =O56/$E$25 -> 0.0054899113 | O56: =Financials!$F$78 -> 499 | P56: =P$25*$D56 -> 518.96 | Q56: =Q$25*$D56 -> 539.7184 | R56: =R$25*$D56 -> 561.30714 | S56: =S$25*$D56 -> 583.75942 | T56: =T$25*$D56 -> 607.1098
C57: Deferred Tax Assets | D57: =E57/$E$25 -> 0.0012322045 | E57: =Financials!$F$84 -> 112 | F57: =F$25*$D57 -> 116.48 | G57: =G$25*$D57 -> 121.1392 | H57: =H$25*$D57 -> 125.98477 | I57: =I$25*$D57 -> 131.02416 | J57: =J$25*$D57 -> 136.26513 | M57: Deferred Tax Assets | N57: =O57/$E$25 -> 0.0012322045 | O57: =Financials!$F$84 -> 112 | P57: =P$25*$D57 -> 116.48 | Q57: =Q$25*$D57 -> 121.1392 | R57: =R$25*$D57 -> 125.98477 | S57: =S$25*$D57 -> 131.02416 | T57: =T$25*$D57 -> 136.26513
C58: Total Assets | D58: =E58/$E$25 -> 0.77089797 | E58: =SUM(E50,E53:E57) -> 70070 | F58: =SUM(F50,F53:F57) -> 72872.8 | G58: =SUM(G50,G53:G57) -> 75787.712 | H58: =SUM(H50,H53:H57) -> 78819.22 | I58: =SUM(I50,I53:I57) -> 81971.989 | J58: =SUM(J50,J53:J57) -> 85250.869 | M58: Total Assets | N58: =O58/$E$25 -> 0.77089797 | O58: =SUM(O50,O53:O57) -> 70070 | P58: =SUM(P50,P53:P57) -> 72872.8 | Q58: =SUM(Q50,Q53:Q57) -> 75787.712 | R58: =SUM(R50,R53:R57) -> 78819.22 | S58: =SUM(S50,S53:S57) -> 81971.989 | T58: =SUM(T50,T53:T57) -> 85250.869
C59: Accounts Payable | D59: =E59/$E$25 -> 0.069333509 | E59: =Financials!$F$90 -> 6302 | F59: =F$25*$D59 -> 6554.08 | G59: =G$25*$D59 -> 6816.2432 | H59: =H$25*$D59 -> 7088.8929 | I59: =I$25*$D59 -> 7372.4486 | J59: =J$25*$D59 -> 7667.3466 | M59: Accounts Payable | N59: =O59/$E$25 -> 0.069333509 | O59: =Financials!$F$90 -> 6302 | P59: =P$25*$D59 -> 6554.08 | Q59: =Q$25*$D59 -> 6816.2432 | R59: =R$25*$D59 -> 7088.8929 | S59: =S$25*$D59 -> 7372.4486 | T59: =T$25*$D59 -> 7667.3466
C60: ST Debt | D60: =E60/$E$25 -> 0.028285695 | E60: =Financials!$F$89 -> 2571 | F60: =$E$60 -> 2571 | G60: =$E$60 -> 2571 | H60: =$E$60 -> 2571 | I60: =$E$60 -> 2571 | J60: =$E$60 -> 2571 | M60: ST Debt | N60: =O60/$E$25 -> 0.028285695 | O60: =Financials!$F$89 -> 2571 | P60: =$E$60 -> 2571 | Q60: =$E$60 -> 2571 | R60: =$E$60 -> 2571 | S60: =$E$60 -> 2571 | T60: =$E$60 -> 2571
C61: Other Current Liabilities | D61: =E61/$E$25 -> 0.083261821 | E61: =Financials!$F$91 -> 7568 | F61: =$E$61 -> 7568 | G61: =$E$61 -> 7568 | H61: =$E$61 -> 7568 | I61: =$E$61 -> 7568 | J61: =$E$61 -> 7568 | M61: Other Current Liabilities | N61: =O61/$E$25 -> 0.083261821 | O61: =Financials!$F$91 -> 7568 | P61: =$E$61 -> 7568 | Q61: =$E$61 -> 7568 | R61: =$E$61 -> 7568 | S61: =$E$61 -> 7568 | T61: =$E$61 -> 7568
C62: Total Current Liabilities | D62: =E62/$E$25 -> 0.18088103 | E62: =SUM(E59:E61) -> 16441 | F62: =SUM(F59:F61) -> 16693.08 | G62: =SUM(G59:G61) -> 16955.243 | H62: =SUM(H59:H61) -> 17227.893 | I62: =SUM(I59:I61) -> 17511.449 | J62: =SUM(J59:J61) -> 17806.347 | M62: Total Current Liabilities | N62: =O62/$E$25 -> 0.18088103 | O62: =SUM(O59:O61) -> 16441 | P62: =SUM(P59:P61) -> 16693.08 | Q62: =SUM(Q59:Q61) -> 16955.243 | R62: =SUM(R59:R61) -> 17227.893 | S62: =SUM(S59:S61) -> 17511.449 | T62: =SUM(T59:T61) -> 17806.347
C63: LT Debt | D63: =E63/$E$25 -> 0.25393315 | E63: =Financials!$F$95 -> 23081 | F63: =$E$63 -> 23081 | G63: =$E$63 -> 23081 | H63: =$E$63 -> 23081 | I63: =$E$63 -> 23081 | J63: =$E$63 -> 23081 | M63: LT Debt | N63: =O63/$E$25 -> 0.25393315 | O63: =Financials!$F$95 -> 23081 | P63: =F63+F70 -> 9544 | Q63: =G63+G70 -> 11206.888 | R63: =H63+H70 -> 13085.844 | S63: =I63+I70 -> 15039.957 | T63: =J63+J70 -> 17072.236
C64: Provisions for Risk & Charges | D64: =E64/$E$25 -> 0.084306995 | E64: =Financials!$F$98 -> 7663 | F64: =$E$63 -> 23081 | G64: =$E$63 -> 23081 | H64: =$E$63 -> 23081 | I64: =$E$63 -> 23081 | J64: =$E$63 -> 23081 | M64: Provisions for Risk & Charges | N64: =O64/$E$25 -> 0.084306995 | O64: =Financials!$F$98 -> 7663 | P64: =$E$63 -> 23081 | Q64: =$E$63 -> 23081 | R64: =$E$63 -> 23081 | S64: =$E$63 -> 23081 | T64: =$E$63 -> 23081
C65: Deffered Tax Liabilities | D65: =E65/$E$25 -> 0.039551566 | E65: =Financials!$F$99 -> 3595 | F65: =$E$65 -> 3595 | G65: =G$25*$D65 -> 3888.352 | H65: =H$25*$D65 -> 4043.8861 | I65: =I$25*$D65 -> 4205.6415 | J65: =J$25*$D65 -> 4373.8672 | M65: Deffered Tax Liabilities | N65: =O65/$E$25 -> 0.039551566 | O65: =Financials!$F$99 -> 3595 | P65: =O65 -> 3595 | Q65: =Q$25*$D65 -> 3888.352 | R65: =R$25*$D65 -> 4043.8861 | S65: =S$25*$D65 -> 4205.6415 | T65: =T$25*$D65 -> 4373.8672
C66: Other Liabilities | D66: =E66/$E$25 -> 0.028021652 | E66: =Financials!$F$100 -> 2547 | F66: =$E$66 -> 2547 | G66: =$E$66 -> 2547 | H66: =$E$66 -> 2547 | I66: =$E$66 -> 2547 | J66: =$E$66 -> 2547 | M66: Other Liabilities | N66: =O66/$E$25 -> 0.028021652 | O66: =Financials!$F$100 -> 2547 | P66: =$E$66 -> 2547 | Q66: =$E$66 -> 2547 | R66: =$E$66 -> 2547 | S66: =$E$66 -> 2547 | T66: =$E$66 -> 2547
C67: Total Liabilities | D67: =E67/$E$25 -> 0.58669439 | E67: =SUM(E62:E66) -> 53327 | F67: =SUM(F62:F66) -> 68997.08 | G67: =SUM(G62:G66) -> 69552.595 | H67: =SUM(H62:H66) -> 69980.779 | I67: =SUM(I62:I66) -> 70426.09 | J67: =SUM(J62:J66) -> 70889.214 | M67: Total Liabilities | N67: =O67/$E$25 -> 0.58669439 | O67: =SUM(O62:O66) -> 53327 | P67: =SUM(P62:P66) -> 55460.08 | Q67: =SUM(Q62:Q66) -> 57678.483 | R67: =SUM(R62:R66) -> 59985.623 | S67: =SUM(S62:S66) -> 62385.047 | T67: =SUM(T62:T66) -> 64880.449
C68: Total Equity | D68: =E68/$E$25 -> 0.18420358 | E68: =Financials!$F$105+Financials!$F$106+Financials!$F$107+Financials!$F$108+Financials!$F$109+Financials!$F$110+Financials!$F$111+Financials!$F$113 -> 16743 | F68: =F$25*$D68 -> 17412.72 | G68: =G$25*$D68 -> 18109.229 | H68: =H$25*$D68 -> 18833.598 | I68: =I$25*$D68 -> 19586.942 | J68: =J$25*$D68 -> 20370.42 | M68: Total Equity | N68: =O68/$E$25 -> 0.18420358 | O68: =Financials!$F$105+Financials!$F$106+Financials!$F$107+Financials!$F$108+Financials!$F$109+Financials!$F$110+Financials!$F$111+Financials!$F$113 -> 16743 | P68: =F68+P41 -> 17412.72 | Q68: =G68+Q41 -> 18109.229 | R68: =H68+R41 -> 18833.598 | S68: =I68+S41 -> 19586.942 | T68: =J68+T41 -> 20370.42
C69: Total Liabilities & Equity | D69: =E69/$E$25 -> 0.77089797 | E69: =E67+E68 -> 70070 | F69: =F67+F68 -> 86409.8 | G69: =G67+G68 -> 87661.824 | H69: =H67+H68 -> 88814.377 | I69: =I67+I68 -> 90013.032 | J69: =J67+J68 -> 91259.633 | M69: Total Liabilities & Equity | N69: =O69/$E$25 -> 0.77089797 | O69: =O67+O68 -> 70070 | P69: =P67+P68 -> 72872.8 | Q69: =Q67+Q68 -> 75787.712 | R69: =R67+R68 -> 78819.22 | S69: =S67+S68 -> 81971.989 | T69: =T67+T68 -> 85250.869
C70: Net New Finance | E70: =E58-E69 -> 0 | F70: =F58-F69 -> -13537 | G70: =G58-G69 -> -11874.112 | H70: =H58-H69 -> -9995.1565 | I70: =I58-I69 -> -8041.0427 | J70: =J58-J69 -> -6008.7644 | M70: Net New Finance | O70: =O58-O69 -> 0 | P70: =P58-P69 -> 0 | Q70: =Q58-Q69 -> 0 | R70: =R58-R69 -> 0 | S70: =S58-S69 -> 0 | T70: =T58-T69 -> 0
C72: Balanced? | E72: =IF(E70=0,"Yes","No") -> Yes | F72: =IF(F70=0,"Yes","No") -> No | G72: =IF(G70=0,"Yes","No") -> No | H72: =IF(H70=0,"Yes","No") -> No | I72: =IF(I70=0,"Yes","No") -> No | J72: =IF(J70=0,"Yes","No") -> No | M72: Balanced? | O72: =IF(O70=0,"Yes","No") -> Yes | P72: =IF(P70=0,"Yes","No") -> Yes | Q72: =IF(Q70=0,"Yes","No") -> Yes | R72: =IF(R70=0,"Yes","No") -> Yes | S72: =IF(S70=0,"Yes","No") -> Yes | T72: =IF(T70=0,"Yes","No") -> Yes
B75: 2 a,b
B103: c | C103: Total equity shows a sharp jump in early years because the firm accumulated a large amount of retained earnings and then shows steady growth as profits continue to be reinvested every year. Cash has a spike in 2021 as profitability increases, and declines as excess cash is used to repay debt and fund growth. Total debt falls sharply as excess cash is used to repay borrowings, and gradually increases as UPS takes on new debt to support growth in the future.
B111: 3 | D111: 2020 | E111: 2021 | F111: 2022 | G111: 2023 | H111: 2024 | I111: 2025 | J111: 2026 | K111: 2027 | L111: 2028 | M111: 2029
B112: a | C112: Profitability Ratios:
C113: Operating Margin | D113: ='Workshop #2'!C272 -> 0.092808414 | E113: ='Workshop #2'!D272 -> 0.13484013 | F113: ='Workshop #2'!E272 -> 0.12963592 | G113: ='Workshop #2'!F272 -> 0.1032674 | H113: ='Workshop #2'!G272 -> 0.095550861 | I113: =P31/P25 -> 0.095550861 | J113: =Q31/Q25 -> 0.095550861 | K113: =R31/R25 -> 0.095550861 | L113: =S31/S25 -> 0.095550861 | M113: =T31/T25 -> 0.095550861
C114: Net Profit Margin | D114: ='Workshop #2'!C273 -> 0.015906291 | E114: ='Workshop #2'!D273 -> 0.13260771 | F114: ='Workshop #2'!E273 -> 0.11544075 | G114: ='Workshop #2'!F273 -> 0.073921428 | H114: ='Workshop #2'!G273 -> 0.06361256 | I114: =P37/P25 -> 0.059859132 | J114: =Q37/Q25 -> 0.067078966 | K114: =R37/R25 -> 0.066517282 | L114: =S37/S25 -> 0.065908652 | M114: =T37/T25 -> 0.065323432
C115: Return on Equity (ROE) | D115: ='Workshop #2'!C274 -> 2.0074738 | E115: ='Workshop #2'!D274 -> 0.90335693 | F115: ='Workshop #2'!E274 -> 0.58314397 | G115: ='Workshop #2'!F274 -> 0.38743214 | H115: ='Workshop #2'!G274 -> 0.34533835 | I115: =P37/P68 -> 0.32496183 | J115: =Q37/Q68 -> 0.36415669 | K115: =R37/R68 -> 0.36110744 | L115: =S37/S68 -> 0.35780332 | M115: =T37/T68 -> 0.35462629
C116: Financials Strength Ratios:
C117: Current Ratio | D117: ='Workshop #2'!C276 -> 1.0108359 | E117: ='Workshop #2'!D276 -> 1.2587964 | F117: ='Workshop #2'!E276 -> 1.3858654 | G117: ='Workshop #2'!F276 -> 1.3233663 | H117: ='Workshop #2'!G276 -> 1.3139685 | I117: =P50/P62 -> 1.2030374 | J117: =Q50/Q62 -> 1.2318134 | K117: =R50/R62 -> 1.2608114 | L117: =S50/S62 -> 1.2900114 | M117: =T50/T62 -> 1.3193929
C118: Book Debt-to-Equity Ratio | D118: ='Workshop #2'!C277 -> 0.28205804 | E118: ='Workshop #2'!D277 -> 0.012280238 | F118: ='Workshop #2'!E277 -> 0.0079728348 | G118: ='Workshop #2'!F277 -> 0.010056207 | H118: ='Workshop #2'!G277 -> 0.010586761 | I118: =(P63)/P68 -> 0.54810506 | J118: =(Q63)/Q68 -> 0.61884954 | K118: =(R63)/R68 -> 0.69481379 | L118: =(S63)/S68 -> 0.76785633 | M118: =(T63)/T68 -> 0.83808954
C119: Interest Coverage Ratio | D119: ='Workshop #2'!C279 -> 11.45614 | E119: ='Workshop #2'!D279 -> 19.190337 | F119: ='Workshop #2'!E279 -> 18.685879 | G119: ='Workshop #2'!F279 -> 12.091613 | H119: ='Workshop #2'!G279 -> 10.087108 | I119: =P37/P33 -> 4.5258683 | J119: =Q37/Q33 -> 11.16835 | K119: =R37/R33 -> 10.12771 | L119: =S37/S33 -> 9.1839807 | M119: =T37/T33 -> 8.4161237
C120: Payout Ratio | D120: ='Workshop #2'!C280 -> 2.620144 | E120: ='Workshop #2'!D280 -> 0.27790833 | F120: ='Workshop #2'!E280 -> 0.46068633 | G120: ='Workshop #2'!F280 -> 0.83076923 | H120: ='Workshop #2'!G280 -> 0.96412622 | I120: =P39/P37 -> 0.99231074 | J120: =Q39/Q37 -> 0.8855065 | K120: =R39/R37 -> 0.89298388 | L120: =S39/S37 -> 0.90123008 | M120: =T39/T37 -> 0.90930404
B122: b
B150: c | C150: Operating margin spikes duing a recovery period post-covid and stabilizes for projected constant future growth. The net profit margin follows the recovery trend. ROE drops because the early years are based on market value of equity while later years are based on book value. Debt-to-equity shows a sharp jump because the market equity is much higher than the book value on the balance sheet. Interest coverage drops as UPS repays debt and reduces interest expense. The drop in payout ratio is from high dividends in early years vs. the stable long term dividend projection.
D163: 2024 | E163: 2025 | F163: 2026 | G163: 2027 | H163: 2028 | I163: 2029
B164: 4 | C164: Needed info for FCF Calculations:
C165: Net Working Capital | D165: =O50-O62 -> 2869 | E165: =P50-P62 -> 3389.32 | F165: =Q50-Q62 -> 3930.4528 | G165: =R50-R62 -> 4493.2309 | H165: =S50-S62 -> 5078.5201 | I165: =T50-T62 -> 5687.221
C166: Change in Net Working Capital | E166: =E165-D165 -> 520.32 | F166: =F165-E165 -> 541.1328 | G166: =G165-F165 -> 562.77811 | H166: =H165-G165 -> 585.28924 | I166: =I165-H165 -> 608.70081
C167: Net PP&E | D167: =O53 -> 41328 | E167: =P53 -> 42981.12 | F167: =Q53 -> 44700.365 | G167: =R53 -> 46488.379 | H167: =S53 -> 48347.915 | I167: =T53 -> 50281.831
C168: Change in PP&E | E168: =E167-D167 -> 1653.12 | F168: =F167-E167 -> 1719.2448 | G168: =G167-F167 -> 1788.0146 | H168: =H167-G167 -> 1859.5352 | I168: =I167-H167 -> 1933.9166
C169: Depreciation | E169: =P52-O52 -> 1444.68 | F169: =Q52-P52 -> 1502.4672 | G169: =R52-Q52 -> 1562.5659 | H169: =S52-R52 -> 1625.0685 | I169: =T52-S52 -> 1690.0713
C170: Capital Expenditures | E170: =E169+E168 -> 3097.8 | F170: =F169+F168 -> 3221.712 | G170: =G169+G168 -> 3350.5805 | H170: =H169+H168 -> 3484.6037 | I170: =I169+I168 -> 3623.9878
C171: EBIT | E171: =O31 -> 8685 | F171: =P31 -> 9032.4 | G171: =Q31 -> 9393.696 | H171: =R31 -> 9769.4438 | I171: =S31 -> 10160.222
C172: FCF Calc:
C173: EBIT (1 - Tax Rate) | E173: =E171*(1-$G$17) -> 6675.987 | F173: =F171*(1-$G$17) -> 6943.0265 | G173: =G171*(1-$G$17) -> 7220.7476 | H173: =H171*(1-$G$17) -> 7509.5775 | I173: =I171*(1-$G$17) -> 7809.9606
C174: Plus Depreciation | E174: =E169 -> 1444.68 | F174: =F169 -> 1502.4672 | G174: =G169 -> 1562.5659 | H174: =H169 -> 1625.0685 | I174: =I169 -> 1690.0713
C175: Less Capital Expenditures | E175: =E170 -> 3097.8 | F175: =F170 -> 3221.712 | G175: =G170 -> 3350.5805 | H175: =H170 -> 3484.6037 | I175: =I170 -> 3623.9878
C176: Less Change in NWC | E176: =E166 -> 520.32 | F176: =F166 -> 541.1328 | G176: =G166 -> 562.77811 | H176: =H166 -> 585.28924 | I176: =I166 -> 608.70081
C177: Free Cash Flow in ($000,000's) | E177: =E173+E174-E175-E176 -> 4502.547 | F177: =F173+F174-F175-F176 -> 4682.6489 | G177: =G173+G174-G175-G176 -> 4869.9549 | H177: =H173+H174-H175-H176 -> 5064.7531 | I177: =I173+I174-I175-I176 -> 5267.3432

Sheet Workshop #6
B3: Estimating Cost of Capital
B5: Workshop 6
B6: Mathilde Sison, Averie Forshaw
B7: BUS 438
B8: Prof. Mahdi Rastad
A12: 1 | C12: Date Accessed: 1/31/26
B13: a(i) | C13: Year(s) to Maturity | D13: T-Bond Yield | E13: TIPS Yield
C14: =1/12 -> 0.083333333 | D14: 0.0372
C15: =3/12 -> 0.25 | D15: 0.0367
C16: =6/12 -> 0.5 | D16: 0.0361
C17: =1 -> 1 | D17: 0.0348
C18: 3 | D18: 0.036
C19: 5 | D19: 0.0379 | E19: =1.26% -> 0.0126
C20: 7 | D20: 0.0401 | E20: =1.59% -> 0.0159
C21: 10 | D21: 0.0426 | E21: =1.9% -> 0.019
C22: 20 | D22: 0.0482 | E22: =2.38% -> 0.0238
C23: 30 | D23: 0.0487 | E23: =2.6% -> 0.026
D27: T-Bond Yield | E27: TIPS Yield
B28: a(ii) | C28: Risk Free Rate Chosen | D28: ='Workshop #8'!D128 -> 0.0426 | E28: =E21 -> 0.019
B30: b(ii) | C30: Real Rate = Nominal Rate - Inflation
C31: Nominal Rate = Real Rate + Inflation
C32: TIPS Rate = Risk-Free Rate - Inflation
C33: Risk-Free Rate = TIPS Rate + Inflation
C34: MRP = Nom. Exp. Mkt. Return - Risk-Free Rate
C35: MRP = (Real Rate + Inflation) - (TIPS Rate + Inflation)
C36: MRP = Real Rate - TIPS Rate
C37: From Exhibit 11.6: Real Rate = | F37: 0.07
C38: TIPS Rate Being Used = | F38: =E28 -> 0.019
C39: Estimated MRP = | F39: =F37-F38 -> 0.051
B41: c(i)
C57: UPS vs. S&P 500 (60-Month)
C59: Regression Statistics
C60: Multiple R | D60: 0.60503922
C61: R Square | D61: 0.36607246
C62: Adjusted R Square | D62: 0.35514268
C63: Standard Error | D63: 0.064425478
C64: Observations | D64: 60
C66: ANOVA
D67: df | E67: SS | F67: MS | G67: F | H67: Significance F
C68: Regression | D68: 1 | E68: 0.1390179 | F68: 0.1390179 | G68: 33.493107 | H68: 3.0475922e-07
C69: Residual | D69: 58 | E69: 0.24073725 | F69: 0.0041506422
C70: Total | D70: 59 | E70: 0.37975515
D72: Coefficients | E72: Standard Error | F72: t Stat | G72: P-value | H72: Lower 95% | I72: Upper 95%
C73: Intercept | D73: 0.019907392 | E73: 0.0085121209 | F73: 2.3387112 | G73: 0.022818175 | H73: 0.0028685311 | I73: 0.036946254
C74: S&P 500 | D74: 1.1110203 | E74: 0.19197482 | F74: 5.7873229 | G74: 3.0475922e-07 | H74: 0.72674094 | I74: 1.4952997
B77: c(iia) | C77: R-Squared | D77: =D61 -> 0.36607246
C78: 95% Confidence Interval | E78: =H74 -> 0.72674094 | F78: =I74 -> 1.4952997
C79: I conclude that a good estimate for UPS's beta is | F79: =D74 -> 1.1110203
B81: c(iib) | C81: Adjusted Beta | D81: =(F79*2/3)+(1/3)*1 -> 1.0740135
B84: c(iic) | C84: FDX vs. S&P 500
C85: Regression Statistics
C86: Multiple R | D86: 0.63906887
C87: R Square | D87: 0.40840902
C88: Adjusted R Square | D88: 0.39820918
C89: Standard Error | D89: 0.070910541
C90: Observations | D90: 60
C92: ANOVA
D93: df | E93: SS | F93: MS | G93: F | H93: Significance F
C94: Regression | D94: 1 | E94: 0.2013369 | F94: 0.2013369 | G94: 40.040711 | H94: 3.9038773e-08
C95: Residual | D95: 58 | E95: 0.29164168 | F95: 0.0050283049
C96: Total | D96: 59 | E96: 0.49297858
D98: Coefficients | E98: Standard Error | F98: t Stat | G98: P-value | H98: Lower 95% | I98: Upper 95%
C99: Intercept | D99: -0.0058129977 | E99: 0.0094696797 | F99: -0.61385368 | G99: 0.54171227 | H99: -0.024768621 | I99: 0.013142626
C100: S&P500 | D100: 1.3443061 | E100: 0.21244537 | F100: 6.327773 | G100: 3.9038773e-08 | H100: 0.91905046 | I100: 1.7695617
C104: DHL vs. S&P 500
C105: Regression Statistics
C106: Multiple R | D106: 0.60496514
C107: R Square | D107: 0.36598282
C108: Adjusted R Square | D108: 0.35505149
C109: Standard Error | D109: 0.065318531
C110: Observations | D110: 60
C112: ANOVA
D113: df | E113: SS | F113: MS | G113: F | H113: Significance F
C114: Regression | D114: 1 | E114: 0.1428435 | F114: 0.1428435 | G114: 33.48017 | H114: 3.0604595e-07
C115: Residual | D115: 58 | E115: 0.24745761 | F115: 0.0042665105
C116: Total | D116: 59 | E116: 0.39030111
D118: Coefficients | E118: Standard Error | F118: t Stat | G118: P-value | H118: Lower 95% | I118: Upper 95%
C119: Intercept | D119: -0.0075738791 | E119: 0.0087229001 | F119: -0.86827534 | G119: 0.38882221 | H119: -0.025034661 | I119: 0.0098869026
C120: S&P500 | D120: 1.1323136 | E120: 0.19569191 | F120: 5.7862052 | G120: 3.0604595e-07 | H120: 0.74059364 | I120: 1.5240335
C123: EXPD vs. S&P 500
C124: Regression Statistics
C125: Multiple R | D125: 0.64424909
C126: R Square | D126: 0.41505688
C127: Adjusted R Square | D127: 0.40497166
C128: Standard Error | D128: 0.058677297
C129: Observations | D129: 60
C131: ANOVA
D132: df | E132: SS | F132: MS | G132: F | H132: Significance F
C133: Regression | D133: 1 | E133: 0.1416975 | F133: 0.1416975 | G133: 41.154941 | H133: 2.7920071e-08
C134: Residual | D134: 58 | E134: 0.19969546 | F134: 0.0034430252
C135: Total | D135: 59 | E135: 0.34139296
D137: Coefficients | E137: Standard Error | F137: t Stat | G137: P-value | H137: Lower 95% | I137: Upper 95%
C138: Intercept | D138: -0.00027869103 | E138: 0.0078360029 | F138: -0.035565458 | G138: 0.97175097 | H138: -0.015964155 | I138: 0.015406773
C139: S&P500 | D139: 1.1277623 | E139: 0.17579502 | F139: 6.4152117 | G139: 2.7920071e-08 | H139: 0.7758703 | I139: 1.4796542
C142: ODFL vs. S&P 500
C143: Regression Statistics
C144: Multiple R | D144: 0.17574391
C145: R Square | D145: 0.030885922
C146: Adjusted R Square | D146: 0.014177058
C147: Standard Error | D147: 0.09127609
...

Sheet Workshop #7
B2: Valuation and the Second Driver: ROIC
B4: Workshop 7
B5: Mathilde Sison, Averie Forshaw
B6: BUS 438
B7: Prof. Mahdi Rastad
B10: 1
B11: a | C11: UPS | F11: 2020 | G11: 2021 | H11: 2022 | I11: 2023 | J11: 2024
C12: EBIT | F12: =Financials!B14 -> 7836 | G12: =Financials!C14 -> 13107 | H12: =Financials!D14 -> 12968 | I12: =Financials!E14 -> 9371 | J12: =Financials!F14 -> 8685
C13: 1- Tax Rate | F13: =1-(Financials!B28/Financials!B27) -> 0.72830803 | G13: =1-(Financials!C28/Financials!C27) -> 0.77673998 | H13: =1-(Financials!D28/Financials!D27) -> 0.77895447 | I13: =1-(Financials!E28/Financials!E27) -> 0.78245655 | J13: =1-(Financials!F28/Financials!F27) -> 0.77694168
C14: NOPLAT | F14: =F12*F13 -> 5707.0217 | G14: =G12*G13 -> 10180.731 | H14: =H12*H13 -> 10101.482 | I14: =I12*I13 -> 7332.4003 | J14: =J12*J13 -> 6747.7385
C15: PP&E | F15: =Financials!B68 -> 35327 | G15: =Financials!C68 -> 37037 | H15: =Financials!D68 -> 38474 | I15: =Financials!E68 -> 41253 | J15: =Financials!F68 -> 41328
C16: Working Capital | F16: =Financials!B67-Financials!B94 -> 3200 | G16: =Financials!C67-Financials!C94 -> 7365 | H16: =Financials!D67-Financials!D94 -> 4077 | I16: =Financials!E67-Financials!E94 -> 1737 | J16: =Financials!F67-Financials!F94 -> 2869
C17: Less Cash | F17: =Financials!B55 -> 6316 | G17: =Financials!C55 -> 10593 | H17: =Financials!D55 -> 7595 | I17: =Financials!E55 -> 6072 | J17: =Financials!F55 -> 6318
C18: Invested Capital | F18: =F15+F16-F17 -> 32211 | G18: =G15+G16-G17 -> 33809 | H18: =H15+H16-H17 -> 34956 | I18: =I15+I16-I17 -> 36918 | J18: =J15+J16-J17 -> 37879
C19: ROIC | F19: =F14/F18 -> 0.17717617 | G19: =G14/G18 -> 0.30112488 | H19: =H14/H18 -> 0.28897704 | I19: =I14/I18 -> 0.19861315 | J19: =J14/J18 -> 0.1781393
C21: Average Historic ROIC | F21: =AVERAGE(F19:J19) -> 0.22880611
C22: Noirmalized UPS ROIC | F22: =AVERAGE(F19,I19,J19) -> 0.18464287
B24: b | C24: Company | D24: ROIC
C25: Deutsche Post AG (XTRA:DHL) | D25: ='Selective Comparable Firms'!BK5 -> 0.0955
C26: TFI International Inc. (TSX:TFII) | D26: ='Selective Comparable Firms'!BK6 -> 0.1145
C27: FedEx Corporation (NYSE:FDX) | D27: ='Selective Comparable Firms'!BK8 -> 0.099165988
C28: Industry Average ROIC | D28: =AVERAGE(D25:D27) -> 0.10305533
B30: c | C30: Forecasted long-term ROIC from Exhibits 4.6 and 4.8 | H30: 0.13
C31: Forecasted long-term ROIC from average of UPS and in dustry historic ROIC | H31: =AVERAGE(F22,D28) -> 0.1438491
C32: UPS's Estimated Long-Term ROIC | E32: =AVERAGE(H30,H31) -> 0.13692455
B35: 2
C36: DCF Method
C37: WACC (WS6) | E37: ='Workshop #6'!E239 -> 0.086843826
C38: Long-Term Growth Rate (g2)(WS4) | E38: ='Workshop #4'!G140 -> 0.025
D40: 2024 | E40: 2025 | F40: 2026 | G40: 2027 | H40: 2028 | I40: 2029
C41: FCF (in $000,000's) | D41: =Financials!$F$133+Financials!$F$135 -> 307 | E41: =D$41*(100%+'Workshop #4'!$G$139) -> 319.28 | F41: =E$41*(100%+'Workshop #4'!$G$139) -> 332.0512 | G41: =F$41*(100%+'Workshop #4'!$G$139) -> 345.33325 | H41: =G$41*(100%+'Workshop #4'!$G$139) -> 359.14658 | I41: =H$41*(100%+'Workshop #4'!$G$139) -> 373.51244
C42: Terminal Value | I42: =(I41*(100%+E38))/(E37-E38) -> 6190.5978
C43: PV (FCFs) | E43: =E41/((100%+$E$37)^1) -> 293.76806 | F43: =F41/((100%+$E$37)^2) -> 281.10642 | G43: =G41/((100%+$E$37)^3) -> 268.99051 | H43: =H41/((100%+$E$37)^4) -> 257.39681 | I43: =I41/((100%+$E$37)^5) -> 246.30281
C44: PV (terminal Value) | D44: =I42/((100%+E37)^5) -> 4082.2244
B46: b(i) | C46: Total PV of FCFs | D46: =SUM(E43:I43) -> 1347.5646
C47: PV (Terminal Value) | D47: =D44 -> 4082.2244
C48: Enterprise Value | D48: =D46+D44 -> 5429.789
B49: b(ii) | C49: EV w/ Mid-Year Correction | D49: =((100%+E37)^0.5)*D48 -> 5660.6529
B50: b(iii) | C50: Plus: Cash | D50: ='Workshop #5'!E45 -> 6318
B51: b(iv) | C51: Less: Total Debt | D51: ='Workshop #5'!E60+'Workshop #5'!E63 -> 25652
B52: b(v) | C52: Market Value of Equity | D52: =D49+D50-D51 -> -13673.347
C53: Shares Outstanding | D53: =Financials!F39 -> 855
B54: b(vi) | C54: Share Price | D54: =D52/D53 -> -15.992219
B57: 3
B58: a | C58: FTE Method (For Financial Company) | E58: F133+F135
C59: R(e ) (WS6) | D59: ='Workshop #6'!G227 -> 0.095773966
C60: Tax Rate (WS6) | D60: ='Workshop #6'!G226 -> 0.19113414
D62: 2024 | E62: 2025 | F62: 2026 | G62: 2027 | H62: 2028 | I62: 2029
C63: FCF (in $000,000's) | D63: =Financials!F133+Financials!F135 -> 307 | E63: =D$41*(100%+'Workshop #4'!$G$139) -> 319.28 | F63: =E$41*(100%+'Workshop #4'!$G$139) -> 332.0512 | G63: =F$41*(100%+'Workshop #4'!$G$139) -> 345.33325 | H63: =G$41*(100%+'Workshop #4'!$G$139) -> 359.14658 | I63: =H$41*(100%+'Workshop #4'!$G$139) -> 373.51244
C64: Interest Expense | D64: ='Workshop #5'!E33 -> 861 | E64: =($D$64/$D$51)*($D$51*(100%+'Workshop #4'!$G$139)^3) -> 968.5079 | F64: =($D$64/$D$51)*($D$51*(100%+'Workshop #4'!$G$139)^2) -> 931.2576 | G64: =($D$64/$D$51)*($D$51*(100%+'Workshop #4'!$G$139)^3) -> 968.5079 | H64: =($D$64/$D$51)*($D$51*(100%+'Workshop #4'!$G$139)^4) -> 1007.2482 | I64: =($D$64/$D$51)*($D$51*(100%+'Workshop #4'!$G$139)^5) -> 1047.5381
C65: Current Debt (WS5) | D65: ='Workshop #5'!E60 -> 2571 | E65: =($D$65/$D$67)*$E$67 -> 2673.84 | F65: =($D$65/$D$67)*$F$67 -> 2780.7936 | G65: =($D$65/$D$67)*$G$67 -> 2892.0253 | H65: =($D$65/$D$67)*$H$67 -> 3007.7064 | I65: =($D$65/$D$67)*$I$67 -> 3128.0146
C66: LT Debt & Leases (WS5) | D66: ='[1]Workshop #5'!$D$115 -> 23081 | E66: =$E$67-$E$65 -> 24004.24 | F66: =$F$67-$F$65 -> 24964.41 | G66: =$G$67-$G$65 -> 25962.986 | H66: =$H$67-$H$65 -> 27001.505 | I66: =$I$67-$I$65 -> 28081.566
C67: Total Debt | D67: =D65+D66 -> 25652 | E67: =D$67*(100%+'Workshop #4'!$G$139) -> 26678.08 | F67: =E$67*(100%+'Workshop #4'!$G$139) -> 27745.203 | G67: =F$67*(100%+'Workshop #4'!$G$139) -> 28855.011 | H67: =G$67*(100%+'Workshop #4'!$G$139) -> 30009.212 | I67: =H$67*(100%+'Workshop #4'!$G$139) -> 31209.58
C68: Net Borrowing | E68: =E67-D67 -> 1026.08 | F68: =F67-E67 -> 1067.1232 | G68: =G67-F67 -> 1109.8081 | H68: =H67-G67 -> 1154.2005 | I68: =I67-H67 -> 1200.3685
C69: FCFE (Free CF to Equity) | D69: =D63-(D64*(100%-$D$60))+D68 -> -389.43351 | E69: =E63-(E64*(100%-$D$60))+E68 -> 561.96702 | F69: =F63-(F64*(100%-$D$60))+F68 -> 645.91192 | G69: =G63-(G64*(100%-$D$60))+G68 -> 671.7484 | H69: =H63-(H64*(100%-$D$60))+H68 -> 698.61833 | I69: =I63-(I64*(100%-$D$60))+I68 -> 726.56307
C70: Discounted by R(e ) | E70: =E69/(100%+$D$59)^1 -> 512.8494 | F70: =F69/(100%+$D$59)^2 -> 537.93691 | G70: =G69/(100%+$D$59)^3 -> 510.55638 | H70: =H69/(100%+$D$59)^4 -> 484.56949 | I70: =I69/(100%+$D$59)^5 -> 459.90531
C71: PV (Total FCFs) | D71: =SUM(E70:I70) -> 2505.8175
C72: Terminal Value | I72: =(I69*(100%+E38))/(D59-E38) -> 10522.614
C73: PV (Terminal Value) | D73: =I72/(100%+D59)^5 -> 6660.6829
C74: Total Equity Value | D74: =D71+D73 -> 9166.5004
C75: Total Equity Value w/ MYA | D75: =((100%+D59)^0.5)*D74 -> 9595.4213
C76: Shares Outstanding | D76: =D53 -> 855
C77: Share Price | D77: =D75/D76 -> 11.222715
B80: b | C80: APV Method
C81: R(u ) (WS6) | D81: ='Workshop #6'!G228 -> 0.08832012
C82: Cost of Debt (WS6) | D82: ='Workshop #6'!G225 -> 0.048738912
C83: Tax Rate (WS6) | D83: =D60 -> 0.19113414
D85: 2024 | E85: 2025 | F85: 2026 | G85: 2027 | H85: 2028 | I85: 2029
B86: b(i) | C86: FCF (in $000,000's)(WS5) | D86: 6213 | E86: 6462 | F86: 6720 | G86: 6989 | H86: 7268 | I86: 7559
C87: Discounted by R(u ) | E87: =E86/(100%+$D$81) -> 5937.5912 | F87: =F86/(100%+$D$81)^2 -> 5673.564 | G87: =G86/(100%+$D$81)^3 -> 5421.8196 | H87: =H86/(100%+$D$81)^4 -> 5180.6981 | I87: =I86/(100%+$D$81)^5 -> 4950.8647
B88: b(ii) | C88: PV (Total FCFs) | D88: =SUM(E87:I87) -> 27164.538
C89: Terminal Value | I89: =(I86*(100%+E38))/(D81-E38) -> 122361.98
C90: PV (Terminal Value) | D90: =I89/(100%+D81)^5 -> 80142.556
C91: Total Unlevered Value | D91: =D88+D90 -> 107307.09
C92: Current Debt (WS5) | D92: 2571 | E92: 2674 | F92: 2781 | G92: 2892 | H92: 3008 | I92: 3128
C93: LT Debt & Leases (WS5) | D93: ='Workshop #5'!$O$63 -> 23081 | E93: =$E$67-$E$65 -> 24004.24 | F93: =$F$67-$F$65 -> 24964.41 | G93: =$G$67-$G$65 -> 25962.986 | H93: =$H$67-$H$65 -> 27001.505 | I93: =$I$67-$I$65 -> 28081.566
C94: Total Debt | D94: =SUM(D92:D93) -> 25652 | E94: =SUM(E92:E93) -> 26678.24 | F94: =SUM(F92:F93) -> 27745.41 | G94: =SUM(G92:G93) -> 28854.986 | H94: =SUM(H92:H93) -> 30009.505 | I94: =SUM(I92:I93) -> 31209.566
C95: Interest Expense | D95: ='Workshop #5'!$O$33 -> 861 | E95: =($D$64/$D$51)*($D$51*(100%+'Workshop #4'!$G$139)) -> 895.44 | F95: =($D$64/$D$51)*($D$51*(100%+'Workshop #4'!$G$139)^2) -> 931.2576 | G95: =($D$64/$D$51)*($D$51*(100%+'Workshop #4'!$G$139)^3) -> 968.5079 | H95: =($D$64/$D$51)*($D$51*(100%+'Workshop #4'!$G$139)^4) -> 1007.2482 | I95: =($D$64/$D$51)*($D$51*(100%+'Workshop #4'!$G$139)^5) -> 1047.5381
C96: Interest Tax Shield | E96: =E95*$D$83 -> 171.14915 | F96: =F95*$D$83 -> 177.99512 | G96: =G95*$D$83 -> 185.11492 | H96: =H95*$D$83 -> 192.51952 | I96: =I95*$D$83 -> 200.2203
C97: ITS Discounted by R(u ) | E97: =($D$95*(100%+'Workshop #4'!$G$139)^1*'Workshop #7'!$D$83)/(100%+'Workshop #7'!$D$81)^1 -> 157.25994 | F97: =($D$95*(100%+'Workshop #4'!$G$139)^2*'Workshop #7'!$D$83)/(100%+'Workshop #7'!$D$81)^2 -> 150.27778 | G97: =($D$95*(100%+'Workshop #4'!$G$139)^3*'Workshop #7'!$D$83)/(100%+'Workshop #7'!$D$81)^3 -> 143.60563 | H97: =($D$95*(100%+'Workshop #4'!$G$139)^4*'Workshop #7'!$D$83)/(100%+'Workshop #7'!$D$81)^4 -> 137.22971 | I97: =($D$95*(100%+'Workshop #4'!$G$139)^5*'Workshop #7'!$D$83)/(100%+'Workshop #7'!$D$81)^5 -> 131.13687
C98: Terminal Value of ITS | I98: =(I96*(100%+E38))/(D81-E38) -> 3241.0837
C99: PV (Terminal Val. Of ITS) | D99: =I98/((100%+D81)^5) -> 2122.7896
B100: b(iii) | C100: PV( ITS) | D100: =SUM(E97:I97)+D99 -> 2842.2996
C101: APV of UPS | D101: =D91+D100 -> 110149.39
C102: APV w/ Mid-Yr Adjustment | D102: =D101*(100%+D81)^0.5 -> 114910.69
C103: Plus: Cash | D103: =D50 -> 6318
C104: Less: Debt | D104: =D51 -> 25652
C105: Market Value of Equity | D105: =D102+D103-D104 -> 95576.691
C106: Shares Outstanding | D106: =D76 -> 855
C107: Share Price | D107: =D105/D106 -> 111.7856
B110: 4
B111: a | C111: FCF 2029 | D111: =I41 -> 373.51244
C112: WACC | D112: =E37 -> 0.086843826
C113: LT Growth Rate (g2) | D113: =E38 -> 0.025
C114: FCF 2030 | D114: =D111*(100%+D113) -> 382.85025
C115: Continuing Value | D115: =D114/(D112-D113) -> 6190.5978
B118: b | C118: EBIT in 2030 | D118: =J12*(100%+'Workshop #4'!G139)^5 -> 10566.63
C119: (1-Tax Rate) | D119: =100%-D83 -> 0.80886586
C120: NOPLAT in 2030 | D120: =D118*D119 -> 8546.9866
C121: Expected Growth Rate | D121: =E38 -> 0.025
...

Sheet Workshop #8
B3: Sensitivity Analysis and Comparison of Valuation Models
B5: Workshop 8
B6: Mathilde Sison, Averie Forshaw
B7: BUS 438
B8: Prof. Mahdi Rastad
B10: 1a | C10: i
B52: 1b | C52: I, ii | D52: 2020 | E52: 2021 | F52: 2022 | G52: 2023 | H52: 2024 | I52: 2025 | J52: 2026 | K52: 2027 | L52: 2028 | M52: 2029
C53: Profitability Ratios:
C54: Operating Margin | D54: ='Workshop #2'!C272 -> 0.092808414 | E54: ='Workshop #2'!D272 -> 0.13484013 | F54: ='Workshop #2'!E272 -> 0.12963592 | G54: ='Workshop #2'!F272 -> 0.1032674 | H54: ='Workshop #2'!G272 -> 0.095550861 | I54: ='Workshop #5'!P31/'Workshop #5'!P25 -> 0.095550861 | J54: ='Workshop #5'!Q31/'Workshop #5'!Q25 -> 0.095550861 | K54: ='Workshop #5'!R31/'Workshop #5'!R25 -> 0.095550861 | L54: ='Workshop #5'!S31/'Workshop #5'!S25 -> 0.095550861 | M54: ='Workshop #5'!T31/'Workshop #5'!T25 -> 0.095550861
C55: Net Profit Margin | D55: ='Workshop #2'!C273 -> 0.015906291 | E55: ='Workshop #2'!D273 -> 0.13260771 | F55: ='Workshop #2'!E273 -> 0.11544075 | G55: ='Workshop #2'!F273 -> 0.073921428 | H55: ='Workshop #2'!G273 -> 0.06361256 | I55: ='Workshop #5'!P37/'Workshop #5'!P26 -> 0.073688119 | J55: ='Workshop #5'!Q37/'Workshop #5'!Q26 -> 0.082575918 | K55: ='Workshop #5'!R37/'Workshop #5'!R26 -> 0.081884471 | L55: ='Workshop #5'!S37/'Workshop #5'!S26 -> 0.081135233 | M55: ='Workshop #5'!T37/'Workshop #5'!T26 -> 0.080414811
C56: Return on Equity (ROE | D56: ='Workshop #2'!C274 -> 2.0074738 | E56: ='Workshop #2'!D274 -> 0.90335693 | F56: ='Workshop #2'!E274 -> 0.58314397 | G56: ='Workshop #2'!F274 -> 0.38743214 | H56: ='Workshop #2'!G274 -> 0.34533835 | I56: ='Workshop #5'!P37/'Workshop #5'!O68 -> 0.33796031 | J56: ='Workshop #5'!Q37/'Workshop #5'!P68 -> 0.37872296 | K56: ='Workshop #5'!R37/'Workshop #5'!Q68 -> 0.37555173 | L56: ='Workshop #5'!S37/'Workshop #5'!R68 -> 0.37211546 | M56: ='Workshop #5'!T37/'Workshop #5'!S68 -> 0.36881134
C57: Financial Strength Ratios:
C58: Current Ratio | D58: ='Workshop #2'!C276 -> 1.0108359 | E58: ='Workshop #2'!D276 -> 1.2587964 | F58: ='Workshop #2'!E276 -> 1.3858654 | G58: ='Workshop #2'!F276 -> 1.3233663 | H58: ='Workshop #2'!G276 -> 1.3139685 | I58: ='Workshop #5'!P50/'Workshop #5'!P62 -> 1.2030374 | J58: ='Workshop #5'!Q50/'Workshop #5'!Q62 -> 1.2318134 | K58: ='Workshop #5'!R50/'Workshop #5'!R62 -> 1.2608114 | L58: ='Workshop #5'!S50/'Workshop #5'!S62 -> 1.2900114 | M58: ='Workshop #5'!T50/'Workshop #5'!T62 -> 1.3193929
C59: Book Debt-to-Equity Ratio | D59: ='Workshop #2'!C277 -> 0.28205804 | E59: ='Workshop #2'!D277 -> 0.012280238 | F59: ='Workshop #2'!E277 -> 0.0079728348 | G59: ='Workshop #2'!F277 -> 0.010056207 | H59: ='Workshop #2'!G277 -> 0.010586761 | I59: ='Workshop #5'!P63/('Workshop #5'!P68) -> 0.54810506 | J59: ='Workshop #5'!Q63/('Workshop #5'!Q68) -> 0.61884954 | K59: ='Workshop #5'!R63/('Workshop #5'!R68) -> 0.69481379 | L59: ='Workshop #5'!S63/('Workshop #5'!S68) -> 0.76785633 | M59: ='Workshop #5'!T63/('Workshop #5'!T68) -> 0.83808954
C60: Interest Coverage Ratio | D60: ='Workshop #2'!C279 -> 11.45614 | E60: ='Workshop #2'!D279 -> 19.190337 | F60: ='Workshop #2'!E279 -> 18.685879 | G60: ='Workshop #2'!F279 -> 12.091613 | H60: ='Workshop #2'!G279 -> 10.087108 | I60: ='Workshop #5'!P37/'Workshop #5'!P33 -> 4.5258683 | J60: ='Workshop #5'!Q37/'Workshop #5'!Q33 -> 11.16835 | K60: ='Workshop #5'!R37/'Workshop #5'!R33 -> 10.12771 | L60: ='Workshop #5'!S37/'Workshop #5'!S33 -> 9.1839807 | M60: ='Workshop #5'!T37/'Workshop #5'!T33 -> 8.4161237
C61: Payout Ratio | D61: ='Workshop #2'!C280 -> 2.620144 | E61: ='Workshop #2'!D280 -> 0.27790833 | F61: ='Workshop #2'!E280 -> 0.46068633 | G61: ='Workshop #2'!F280 -> 0.83076923 | H61: ='Workshop #2'!G280 -> 0.96412622 | I61: ='Workshop #5'!P39/'Workshop #5'!P37 -> 0.99231074 | J61: ='Workshop #5'!Q39/'Workshop #5'!Q37 -> 0.8855065 | K61: ='Workshop #5'!R39/'Workshop #5'!R37 -> 0.89298388 | L61: ='Workshop #5'!S39/'Workshop #5'!S37 -> 0.90123008 | M61: ='Workshop #5'!T39/'Workshop #5'!T37 -> 0.90930404
C92: iii
B94: 1c | D94: DCF | E94: APV | F94: Current Market Value
C95: Share Price | D95: ='Workshop #7'!D54 -> -15.992219 | E95: ='Workshop #7'!D107 -> 111.7856 | F95: ='Workshop #2'!D11 -> 108.03
C96: Market Cap | D96: ='Workshop #7'!D52 -> -13673.347 | E96: ='Workshop #7'!D105 -> 95576.691 | F96: =(F95)*Financials!F39 -> 92365.65
C97: Error Margin | D97: =(D96-F96)/F96 -> -1.148035 | E97: =(E96-F96)/F96 -> 0.034764454 | F97: 0
C99: Firm Value (Average of APV and DCF Value) | E99: =AVERAGE(D96:E96) -> 40951.672
C100: Corresponding Average Share Price | E100: =AVERAGE(D95:E95) -> 47.896693
C101: % Difference | E101: =(E99-F96)/F96 -> -0.55663526
B104: 2a | C104: Sensitivity Analysis:
B105: I,ii | C105: Driver | D105: % Change | E105: Value Original | F105: Value After | G105: Impact on Original Value
C106: Risk-Free Rate | D106: 1% increase | E106: =$E$99 -> 40951.672 | F106: 94130 | G106: =ABS(E106-F106) -> 53178.328
C107: Beta | D107: 1% increase | E107: =$E$99 -> 40951.672 | F107: 95013 | G107: =ABS(E107-F107) -> 54061.328
C108: Cost of Debt | D108: 1% increase | E108: =$E$99 -> 40951.672 | F108: 95276 | G108: =ABS(E108-F108) -> 54324.328
C109: Growth Rate (g2) | D109: 1% increase | E109: =$E$99 -> 40951.672 | F109: 95767 | G109: =ABS(E109-F109) -> 54815.328
B125: iii | C125: Growth rate has the biggest impact on UPS.
B127: 2b
B128: i | C128: Risk-free Rate | D128: ='Workshop #6'!D21 -> 0.0426
C129: Beta | D129: =AVERAGE('Workshop #6'!D81,'Workshop #6'!E189) -> 1.0426268
C130: Cost of Debt | D130: ='Workshop #6'!E198 -> 0.048738912
C131: Growth Rate (g2) | D131: 0.025
D134: Beta
C135: Firm Value | D135: =E99 -> 40951.672 | E135: =F135*0.99 -> 1.0015431 | F135: =G135*0.99 -> 1.0116597 | G135: =H135*0.99 -> 1.0218785 | H135: =I135*0.99 -> 1.0322005 | I135: =AVERAGE('Workshop #6'!E222:F222) -> 1.0426268 | J135: =I135*1.01 -> 1.0530531 | K135: =J135*1.01 -> 1.0635836 | L135: =K135*1.01 -> 1.0742194 | M135: =L135*1.01 -> 1.0849616 | N135: =M135*1.01 -> 1.0958112 | O135: =N135*1.01 -> 1.1067693 | P135: =O135*1.01 -> 1.117837
C136: Risk-Free Rate | D136: =D137*0.99 -> 0.040512176 | E136: 44426.174 | F136: 43975.64 | G136: 43527.109 | H136: 43080.592 | I136: 42636.097 | J136: 42198.026 | K136: 41761.954 | L136: 41327.888 | M136: 40895.837 | N136: 40465.807 | O136: 40037.805 | P136: 39611.839
D137: =D138*0.99 -> 0.04092139 | E137: 44068.306 | F137: 43622.904 | G137: 43179.448 | H137: 42737.945 | I137: 42298.406 | J137: 41865.184 | K137: 41433.904 | L137: 41004.575 | M137: 40577.203 | N137: 40151.798 | O137: 39728.366 | P137: 39306.914
D138: =D139*0.99 -> 0.041334737 | E138: 43710.965 | F138: 43270.66 | G138: 42832.241 | H138: 42395.718 | I138: 41961.102 | J138: 41532.697 | K138: 41106.178 | L138: 40681.554 | M138: 40258.833 | N138: 39838.023 | O138: 39419.133 | P138: 39002.168
D139: =D140*0.99 -> 0.04175226 | E139: 43354.169 | F139: 42918.923 | G139: 42485.506 | H139: 42053.929 | I139: 41624.201 | J139: 41200.58 | K139: 40778.791 | L139: 40358.842 | M139: 39940.742 | N139: 39524.499 | O139: 39110.122 | P139: 38697.618
D140: =D141*0.99 -> 0.042174 | E140: 42997.933 | F140: 42567.709 | G140: 42139.259 | H140: 41712.592 | I140: 41287.719 | J140: 40868.85 | K140: 40451.758 | L140: 40036.454 | M140: 39622.945 | N140: 39211.24 | O140: 38801.349 | P140: 38393.279
D141: 0.0426 | E141: 42642.274 | F141: 42217.037 | G141: 41793.517 | H141: 41371.725 | I141: 40951.672 | J141: 40537.522 | K141: 40125.097 | L141: 39714.406 | M141: 39305.458 | N141: 38898.263 | O141: 38492.829 | P141: 38089.165
D142: =D141*1.01 -> 0.043026 | E142: 42290.74 | F142: 41870.402 | G142: 41451.727 | H142: 41034.728 | I142: 40619.414 | J142: 40209.904 | K142: 39802.068 | L142: 39395.913 | M142: 38991.452 | N142: 38588.692 | O142: 38187.643 | P142: 37788.313
D143: =D142*1.01 -> 0.04345626 | E143: 41939.803 | F143: 41524.328 | G143: 41110.464 | H143: 40698.223 | I143: 40287.615 | J143: 39882.712 | K143: 39479.432 | L143: 39077.785 | M143: 38677.78 | N143: 38279.426 | O143: 37882.734 | P143: 37487.713
D144: =D143*1.01 -> 0.043890823 | E144: 41589.481 | F144: 41178.833 | G144: 40769.744 | H144: 40362.225 | I144: 39956.289 | J144: 39555.962 | K144: 39157.207 | L144: 38760.035 | M144: 38364.457 | N144: 37970.481 | O144: 37578.118 | P144: 37187.377
D145: =D144*1.01 -> 0.044329731 | E145: 41239.789 | F145: 40833.93 | G145: 40429.58 | H145: 40026.75 | I145: 39625.452 | J145: 39229.668 | K145: 38835.407 | L145: 38442.68 | M145: 38051.498 | N145: 37661.871 | O145: 37273.809 | P145: 36887.322
D146: =D145*1.01 -> 0.044773028 | E146: 40890.741 | F146: 40489.636 | G146: 40089.989 | H146: 39691.813 | I146: 39295.12 | J146: 38903.845 | K146: 38514.046 | L146: 38125.734 | M146: 37738.919 | N146: 37353.611 | O146: 36969.822 | P146: 36587.56
D147: =D146*1.01 -> 0.045220758 | E147: 40542.355 | F147: 40145.966 | G147: 39750.987 | H147: 39357.43 | I147: 38965.306 | J147: 38578.509 | K147: 38193.141 | L147: 37809.212 | M147: 37426.733 | N147: 37045.716 | O147: 36666.17 | P147: 36288.106
D151: Cost of Debt
C152: Firm Value | D152: =E99 -> 40951.672 | E152: =F152*(0.99) -> 0.046818405 | F152: =G152*(0.99) -> 0.047291318 | G152: =H152*(0.99) -> 0.047769008 | H152: =I152*(0.99) -> 0.048251523 | I152: =SUMPRODUCT('Workshop #6'!G194:G196,'Workshop #6'!H194:H196)/SUM('Workshop #6'!H194:H196) -> 0.048738912 | J152: =I152*(1.01) -> 0.049226301 | K152: =J152*(1.01) -> 0.049718564 | L152: =K152*(1.01) -> 0.05021575 | M152: =L152*(1.01) -> 0.050717907 | N152: =M152*(1.01) -> 0.051225086 | O152: =N152*(1.01) -> 0.051737337 | P152: =O152*(1.01) -> 0.052254711
C153: Risk-Free Rate | D153: =D136 -> 0.040512176 | E153: 42934.931 | F153: 42861.071 | G153: 42786.648 | H153: 42711.657 | I153: 42636.097 | J153: 42560.725 | K153: 42484.79 | L153: 42408.288 | M153: 42331.218 | N153: 42253.577 | O153: 42175.363 | P153: 42096.572
D154: =D137 -> 0.04092139 | E154: 42593.913 | F154: 42520.877 | G154: 42447.283 | H154: 42373.127 | I154: 42298.406 | J154: 42223.871 | K154: 42148.777 | L154: 42073.123 | M154: 41996.905 | N154: 41920.121 | O154: 41842.769 | P154: 41764.847
D155: =D138 -> 0.041334737 | E155: 42253.303 | F155: 42181.086 | G155: 42108.315 | H155: 42034.988 | I155: 41961.102 | J155: 41887.397 | K155: 41813.14 | L155: 41738.327 | M155: 41662.956 | N155: 41587.024 | O155: 41510.529 | P155: 41433.469
D156: =D139 -> 0.04175226 | E156: 41913.12 | F156: 41841.715 | G156: 41769.762 | H156: 41697.258 | I156: 41624.201 | J156: 41551.322 | K156: 41477.895 | L156: 41403.917 | M156: 41329.387 | N156: 41254.301 | O156: 41178.658 | P156: 41102.454
D157: =D140 -> 0.042174 | E157: 41573.379 | F157: 41502.781 | G157: 41431.64 | H157: 41359.954 | I157: 41287.719 | J157: 41215.659 | K157: 41143.057 | L157: 41069.91 | M157: 40996.215 | N157: 40921.97 | O157: 40847.172 | P157: 40771.818
D158: =D141 -> 0.0426 | E158: 41234.096 | F158: 41164.299 | G158: 41093.965 | H158: 41023.09 | I158: 40951.672 | J158: 40880.427 | K158: 40808.644 | L158: 40736.321 | M158: 40663.456 | N158: 40590.045 | O158: 40516.087 | P158: 40441.578
D159: =D142 -> 0.043026 | E159: 40898.656 | F159: 40829.647 | G159: 40760.106 | H159: 40690.029 | I159: 40619.414 | J159: 40548.969 | K159: 40477.992 | L159: 40406.48 | M159: 40334.429 | N159: 40261.839 | O159: 40188.707 | P159: 40115.029
D160: =D143 -> 0.04345626 | E160: 40563.697 | F160: 40495.47 | G160: 40426.716 | H160: 40357.432 | I160: 40287.615 | J160: 40217.965 | K160: 40147.787 | L160: 40077.079 | M160: 40005.839 | N160: 39934.064 | O160: 39861.752 | P160: 39788.899
D161: =D144 -> 0.043890823 | E161: 40229.234 | F161: 40161.784 | G161: 40093.812 | H161: 40025.314 | I161: 39956.289 | J161: 39887.428 | K161: 39818.044 | L161: 39748.136 | M161: 39677.7 | N161: 39606.734 | O161: 39535.236 | P161: 39463.203
D162: =D145 -> 0.044329731 | E162: 39895.282 | F162: 39828.604 | G162: 39761.408 | H162: 39693.691 | I162: 39625.452 | J162: 39557.374 | K162: 39488.779 | L162: 39419.664 | M162: 39350.027 | N162: 39279.865 | O162: 39209.175 | P162: 39137.955
D163: =D146 -> 0.044773028 | E163: 39561.858 | F163: 39495.945 | G163: 39429.519 | H163: 39362.578 | I163: 39295.12 | J163: 39227.82 | K163: 39160.007 | L163: 39091.68 | M163: 39022.835 | N163: 38953.471 | O163: 38883.584 | P163: 38813.173
D164: =D147 -> 0.045220758 | E164: 39228.976 | F164: 39163.822 | G164: 39098.161 | H164: 39031.99 | I164: 38965.306 | J164: 38898.779 | K164: 38831.744 | L164: 38764.198 | M164: 38696.141 | N164: 38627.568 | O164: 38558.478 | P164: 38488.869
D168: Growth Rate
C169: Firm Value | D169: =E99 -> 40951.672 | E169: =F169*(0.99) -> 0.0240149 | F169: =G169*(0.99) -> 0.024257475 | G169: =H169*(0.99) -> 0.0245025 | H169: =I169*(0.99) -> 0.02475 | I169: 0.025 | J169: =I169*1.01 -> 0.02525 | K169: =J169*1.01 -> 0.0255025 | L169: =K169*1.01 -> 0.025757525 | M169: =L169*1.01 -> 0.0260151 | N169: =M169*1.01 -> 0.026275251 | O169: =N169*1.01 -> 0.026538004 | P169: =O169*1.01 -> 0.026803384
C170: Risk-Free Rate | D170: =D153 -> 0.040512176 | E170: 41856.194 | F170: 42045.949 | G170: 42239.128 | H170: 42435.816 | I170: 42636.097 | J170: 42838.014 | K170: 43043.63 | L170: 43253.038 | M170: 43466.332 | N170: 43683.612 | O170: 43904.979 | P170: 44130.538
D171: =D154 -> 0.04092139 | E171: 41527.953 | F171: 41715.421 | G171: 41906.264 | H171: 42100.564 | I171: 42298.406 | J171: 42497.854 | K171: 42700.947 | L171: 42907.776 | M171: 43118.433 | N171: 43333.016 | O171: 43551.624 | P171: 43774.361
D172: =D155 -> 0.041334737 | E172: 41200.03 | F172: 41385.228 | G172: 41573.752 | H172: 41765.682 | I172: 41961.102 | J172: 42158.1 | K172: 42358.688 | L172: 42562.957 | M172: 42770.997 | N172: 42982.903 | O172: 43198.774 | P172: 43418.711
D173: =D156 -> 0.04175226 | E173: 40872.442 | F173: 41055.386 | G173: 41241.607 | H173: 41431.184 | I173: 41624.201 | J173: 41818.766 | K173: 42016.869 | L173: 42218.597 | M173: 42424.04 | N173: 42633.291 | O173: 42846.447 | P173: 43063.606
D174: =D157 -> 0.042174 | E174: 40545.204 | F174: 40725.91 | G174: 40909.846 | H174: 41097.088 | I174: 41287.719 | J174: 41479.87 | K174: 41675.507 | L174: 41874.714 | M174: 42077.58 | N174: 42284.196 | O174: 42494.657 | P174: 42709.061
D175: =D158 -> 0.0426 | E175: 40218.333 | F175: 40396.818 | G175: 40578.485 | H175: 40763.41 | I175: 40951.672 | J175: 41141.429 | K175: 41334.618 | L175: 41531.323 | M175: 41731.632 | N175: 41935.635 | O175: 42143.423 | P175: 42355.093
D176: =D159 -> 0.043026 | E176: 39895.091 | F176: 40071.393 | G176: 40250.831 | H176: 40433.479 | I176: 40619.414 | J176: 40806.818 | K176: 40997.602 | L176: 41191.85 | M176: 41389.648 | N176: 41591.083 | O176: 41796.246 | P176: 42005.232
D177: =D160 -> 0.04345626 | E177: 39572.24 | F177: 39746.375 | G177: 39923.6 | H177: 40103.988 | I177: 40287.615 | J177: 40472.683 | K177: 40661.082 | L177: 40852.892 | M177: 41048.198 | N177: 41247.086 | O177: 41449.646 | P177: 41655.969
D178: =D161 -> 0.043890823 | E178: 39249.793 | F178: 39421.778 | G178: 39596.807 | H178: 39774.953 | I178: 39956.289 | J178: 40139.04 | K178: 40325.072 | L178: 40514.464 | M178: 40707.298 | N178: 40903.66 | O178: 41103.637 | P178: 41307.319
D179: =D162 -> 0.044329731 | E179: 38927.768 | F179: 39097.619 | G179: 39270.469 | H179: 39446.389 | I179: 39625.452 | J179: 39805.904 | K179: 39989.588 | L179: 40176.58 | M179: 40366.963 | N179: 40560.819 | O179: 40758.235 | P179: 40959.298
D180: =D163 -> 0.044773028 | E180: 38606.177 | F180: 38773.911 | G180: 38944.599 | H180: 39118.311 | I180: 39295.12 | J180: 39473.291 | K180: 39654.645 | L180: 39839.258 | M180: 40027.209 | N180: 40218.58 | O180: 40413.455 | P180: 40611.922
D181: =D164 -> 0.045220758 | E181: 38285.038 | F181: 38450.671 | G181: 38619.214 | H181: 38790.735 | I181: 38965.306 | J181: 39141.216 | K181: 39320.259 | L181: 39502.512 | M181: 39688.051 | N181: 39876.957 | O181: 40069.314 | P181: 40265.206
D185: Cost of Debt
C186: Firm Value | D186: =E99 -> 40951.672 | E186: =F186*(0.99) -> 0.046818405 | F186: =G186*(0.99) -> 0.047291318 | G186: =H186*(0.99) -> 0.047769008 | H186: =I186*(0.99) -> 0.048251523 | I186: =SUMPRODUCT('Workshop #6'!G194:G196,'Workshop #6'!H194:H196)/SUM('Workshop #6'!H194:H196) -> 0.048738912 | J186: =I186*1.01 -> 0.049226301 | K186: =J186*1.01 -> 0.049718564 | L186: =K186*1.01 -> 0.05021575 | M186: =L186*1.01 -> 0.050717907 | N186: =M186*1.01 -> 0.051225086 | O186: =N186*1.01 -> 0.051737337 | P186: =O186*1.01 -> 0.052254711
C187: Beta | D187: =D188*0.99 -> 0.98902965 | E187: 43480.843 | F187: 43405.655 | G187: 43329.895 | H187: 43253.559 | I187: 43176.645 | J187: 43099.924 | K187: 43022.631 | L187: 42944.764 | M187: 42866.32 | N187: 42787.297 | O187: 42707.691 | P187: 42627.502
D188: =D189*0.99 -> 0.99901985 | E188: 43049.227 | F188: 42975.091 | G188: 42900.388 | H188: 42825.117 | I188: 42749.275 | J188: 42673.621 | K188: 42597.402 | L188: 42520.616 | M188: 42443.259 | N188: 42365.33 | O188: 42286.825 | P188: 42207.742
D189: =D190*0.99 -> 1.009111 | E189: 42619.362 | F189: 42546.265 | G189: 42472.609 | H189: 42398.391 | I189: 42323.608 | J189: 42249.01 | K189: 42173.854 | L189: 42098.136 | M189: 42021.855 | N189: 41945.008 | O189: 41867.592 | P189: 41789.604
D190: =D191*0.99 -> 1.019304 | E190: 42191.257 | F190: 42119.189 | G190: 42046.567 | H190: 41973.39 | I190: 41899.656 | J190: 41826.102 | K190: 41751.996 | L190: 41677.336 | M190: 41602.119 | N190: 41526.342 | O190: 41450.002 | P190: 41373.098
D191: =D192*0.99 -> 1.0296 | E191: 41764.925 | F191: 41693.873 | G191: 41622.274 | H191: 41550.127 | I191: 41477.429 | J191: 41404.908 | K191: 41331.842 | L191: 41258.227 | M191: 41184.062 | N191: 41109.343 | O191: 41034.069 | P191: 40958.237
D192: 1.04 | E192: 41340.374 | F192: 41270.327 | G192: 41199.741 | H192: 41128.612 | I192: 41056.939 | J192: 40985.439 | K192: 40913.4 | L192: 40840.82 | M192: 40767.695 | N192: 40694.023 | O192: 40619.802 | P192: 40545.03
D193: =D192*1.01 -> 1.0504 | E193: 40921.814 | F193: 40852.751 | G193: 40783.155 | H193: 40713.024 | I193: 40642.354 | J193: 40571.854 | K193: 40500.821 | L193: 40429.252 | M193: 40357.146 | N193: 40284.5 | O193: 40211.31 | P193: 40137.576
D194: =D193*1.01 -> 1.060904 | E194: 40505.02 | F194: 40436.931 | G194: 40368.314 | H194: 40299.168 | I194: 40229.49 | J194: 40159.979 | K194: 40089.941 | L194: 40019.374 | M194: 39948.275 | N194: 39876.642 | O194: 39804.473 | P194: 39731.764
D195: =D194*1.01 -> 1.071513 | E195: 40090.003 | F195: 40022.875 | G195: 39955.227 | H195: 39887.056 | I195: 39818.359 | J195: 39749.825 | K195: 39680.77 | L195: 39611.193 | M195: 39541.091 | N195: 39470.46 | O195: 39399.3 | P195: 39327.607
D196: =D195*1.01 -> 1.0822282 | E196: 39676.77 | F196: 39610.594 | G196: 39543.903 | H196: 39476.695 | I196: 39408.968 | J196: 39341.401 | K196: 39273.319 | L196: 39204.721 | M196: 39135.603 | N196: 39065.964 | O196: 38995.801 | P196: 38925.112
D197: =D196*1.01 -> 1.0930505 | E197: 39265.331 | F197: 39200.095 | G197: 39134.351 | H197: 39068.096 | I197: 39001.328 | J197: 38934.716 | K197: 38867.596 | L197: 38799.965 | M197: 38731.822 | N197: 38663.163 | O197: 38593.987 | P197: 38524.29
D198: =D197*1.01 -> 1.103981 | E198: 38855.695 | F198: 38791.388 | G198: 38726.579 | H198: 38661.266 | I198: 38595.446 | J198: 38529.779 | K198: 38463.61 | L198: 38396.936 | M198: 38329.756 | N198: 38262.066 | O198: 38193.865 | P198: 38125.15
C203: Growth Rate
C204: Firm Value | D204: =E99 -> 40951.672 | E204: =F204*(0.99) -> 0.0240149 | F204: =G204*(0.99) -> 0.024257475 | G204: =H204*(0.99) -> 0.0245025 | H204: =I204*(0.99) -> 0.02475 | I204: 0.025 | J204: =I204*1.01 -> 0.02525 | K204: =J204*1.01 -> 0.0255025 | L204: =K204*1.01 -> 0.025757525 | M204: =L204*1.01 -> 0.0260151 | N204: =M204*1.01 -> 0.026275251 | O204: =N204*1.01 -> 0.026538004 | P204: =O204*1.01 -> 0.026803384
C205: Beta | D205: =D206*0.99 -> 0.98902965 | E205: 42381.496 | F205: 42574.939 | G205: 42771.888 | H205: 42972.427 | I205: 43176.645 | J205: 43382.545 | K205: 43592.233 | L205: 43805.804 | M205: 44023.356 | N205: 44244.989 | O205: 44470.81 | P205: 44700.925
D206: =D207*0.99 -> 0.99901985 | E206: 41966.191 | F206: 42156.716 | G206: 42350.681 | H206: 42548.172 | I206: 42749.275 | J206: 42952.022 | K206: 43158.487 | L206: 43368.763 | M206: 43582.946 | N206: 43801.133 | O206: 44023.428 | P206: 44249.937
D207: =D208*0.99 -> 1.009111 | E207: 41552.451 | F207: 41740.09 | G207: 41931.107 | H207: 42125.584 | I207: 42323.608 | J207: 42523.239 | K207: 42726.52 | L207: 42933.541 | M207: 43144.394 | N207: 43359.178 | O207: 43577.991 | P207: 43800.938
D208: =D209*0.99 -> 1.019304 | E208: 41140.287 | F208: 41325.072 | G208: 41513.175 | H208: 41704.675 | I208: 41899.656 | J208: 42096.209 | K208: 42296.343 | L208: 42500.147 | M208: 42707.712 | N208: 42919.133 | O208: 43134.507 | P208: 43353.936
D209: =D210*0.99 -> 1.0296 | E209: 40729.71 | F209: 40911.676 | G209: 41096.898 | H209: 41285.456 | I209: 41477.429 | J209: 41670.94 | K209: 41867.965 | L209: 42068.592 | M209: 42272.908 | N209: 42481.008 | O209: 42692.986 | P209: 42908.941
D210: 1.04 | E210: 40320.732 | F210: 40499.911 | G210: 40682.287 | H210: 40867.936 | I210: 41056.939 | J210: 41247.444 | K210: 41441.398 | L210: 41638.886 | M210: 41839.994 | N210: 42044.813 | O210: 42253.437 | P210: 42465.961
...

Sheet WS8 Work
B3: Income Statement
B4: Report Date | C4: 2020 | D4: 2021 | E4: 2022 | F4: 2023 | G4: =2024 -> 2024 | H4: 2025 | I4: 2026 | J4: 2027 | K4: 2028 | L4: 2029
B5: Sales | C5: =Financials!B4 -> 84432 | D5: =Financials!C4 -> 97204 | E5: =Financials!D4 -> 100034 | F5: =Financials!E4 -> 90745 | G5: =Financials!F4 -> 90894 | H5: ='Workshop #5'!P25 -> 94529.76 | I5: ='Workshop #5'!Q25 -> 98310.95 | J5: ='Workshop #5'!R25 -> 102243.39 | K5: ='Workshop #5'!S25 -> 106333.12 | L5: ='Workshop #5'!T25 -> 110586.45
B6: COGS | C6: =Financials!B5 -> 62649 | D6: =Financials!C5 -> 79772 | E6: =Financials!D5 -> 79954 | F6: =Financials!E5 -> 73039 | G6: =Financials!F5 -> 73836 | H6: ='Workshop #5'!P26 -> 76789.44 | I6: ='Workshop #5'!Q26 -> 79861.018 | J6: ='Workshop #5'!R26 -> 83055.458 | K6: ='Workshop #5'!S26 -> 86377.677 | L6: ='Workshop #5'!T26 -> 89832.784
B7: Gross Income | C7: =C5-C6 -> 21783 | D7: =D5-D6 -> 17432 | E7: =E5-E6 -> 20080 | F7: =F5-F6 -> 17706 | G7: =G5-G6 -> 17058 | H7: ='Workshop #5'!P27 -> 17740.32 | I7: ='Workshop #5'!Q27 -> 18449.933 | J7: ='Workshop #5'!R27 -> 19187.93 | K7: ='Workshop #5'!S27 -> 19955.447 | L7: ='Workshop #5'!T27 -> 20753.665
B8: Depreciation & Amortizaton | C8: =Financials!B8+Financials!B9 -> 2698 | D8: =Financials!C8+Financials!C9 -> 2953 | E8: =Financials!D8+Financials!D9 -> 3188 | F8: =Financials!E8+Financials!E9 -> 3366 | G8: =Financials!F8+Financials!F9 -> 3609 | H8: ='Workshop #5'!P28 -> 3753.36 | I8: ='Workshop #5'!Q28 -> 3903.4944 | J8: ='Workshop #5'!R28 -> 4059.6342 | K8: ='Workshop #5'!S28 -> 4222.0195 | L8: ='Workshop #5'!T28 -> 4390.9003
B9: SG&A | C9: =Financials!$F$11 -> 8684 | D9: =Financials!$F$11 -> 8684 | E9: =Financials!$F$11 -> 8684 | F9: =Financials!$F$11 -> 8684 | G9: =Financials!$F$11 -> 8684 | H9: ='Workshop #5'!P29 -> 9031.36 | I9: ='Workshop #5'!Q29 -> 9392.6144 | J9: ='Workshop #5'!R29 -> 9768.319 | K9: ='Workshop #5'!S29 -> 10159.052 | L9: ='Workshop #5'!T29 -> 10565.414
B10: Other Operating Expense | C10: =-Financials!B13 -> 0 | D10: =-Financials!C13 -> 0 | E10: =-Financials!D13 -> 0 | F10: =-Financials!E13 -> 0 | G10: =-Financials!F13 -> 311 | H10: ='Workshop #5'!P30 -> 323.44 | I10: ='Workshop #5'!Q30 -> 336.3776 | J10: ='Workshop #5'!R30 -> 349.8327 | K10: ='Workshop #5'!S30 -> 363.82601 | L10: ='Workshop #5'!T30 -> 378.37905
B11: Operating Income (EBIT) | C11: =C7-C9+C10 -> 13099 | D11: =D7-D9+D10 -> 8748 | E11: =E7-E9+E10 -> 11396 | F11: =F7-F9+F10 -> 9022 | G11: =G7-G9+G10 -> 8685 | H11: ='Workshop #5'!P31 -> 9032.4 | I11: ='Workshop #5'!Q31 -> 9393.696 | J11: ='Workshop #5'!R31 -> 9769.4438 | K11: ='Workshop #5'!S31 -> 10160.222 | L11: ='Workshop #5'!T31 -> 10566.63
B12: Other Income (Expense) | C12: =Financials!B17 -> -4978 | D12: =Financials!C17 -> 4590 | E12: =Financials!D17 -> 2729 | F12: =Financials!E17 -> 423 | G12: =Financials!F17 -> 17 | H12: ='Workshop #5'!P32 -> 17.68 | I12: ='Workshop #5'!Q32 -> 18.3872 | J12: ='Workshop #5'!R32 -> 19.122688 | K12: ='Workshop #5'!S32 -> 19.887596 | L12: ='Workshop #5'!T32 -> 20.683099
B13: Interest Expense | C13: =Financials!B18 -> 684 | D13: =Financials!C18 -> 683 | E13: =Financials!D18 -> 694 | F13: =Financials!E18 -> 775 | G13: =Financials!F18 -> 861 | H13: ='Workshop #5'!P33 -> 1250.2506 | I13: ='Workshop #5'!Q33 -> 590.47192 | J13: ='Workshop #5'!R33 -> 671.51927 | K13: ='Workshop #5'!S33 -> 763.09752 | L13: ='Workshop #5'!T33 -> 858.3389
B14: Unusual Expense | C14: =Financials!B21 -> 330 | D14: =Financials!C21 -> 419 | E14: =Financials!D21 -> 178 | F14: =Financials!E21 -> 446 | G14: =Financials!F21 -> 399 | H14: ='Workshop #5'!P34 -> 414.96 | I14: ='Workshop #5'!Q34 -> 431.5584 | J14: ='Workshop #5'!R34 -> 448.82074 | K14: ='Workshop #5'!S34 -> 466.77357 | L14: ='Workshop #5'!T34 -> 485.44451
B15: Earnings Before Tax | C15: =C11+C12-C13-C14 -> 7107 | D15: =D11+D12-D13-D14 -> 12236 | E15: =E11+E12-E13-E14 -> 13253 | F15: =F11+F12-F13-F14 -> 8224 | G15: =G11+G12-G13-G14 -> 7442 | H15: ='Workshop #5'!P35 -> 7384.8694 | I15: ='Workshop #5'!Q35 -> 8390.0529 | J15: ='Workshop #5'!R35 -> 8668.2265 | K15: ='Workshop #5'!S35 -> 8950.2381 | L15: ='Workshop #5'!T35 -> 9243.5302
B16: Income Tax | C16: =Financials!B28 -> 501 | D16: =Financials!C28 -> 3705 | E16: =Financials!D28 -> 3277 | F16: =Financials!E28 -> 1865 | G16: =Financials!F28 -> 1660 | H16: ='Workshop #5'!P36 -> 1726.4 | I16: ='Workshop #5'!Q36 -> 1795.456 | J16: ='Workshop #5'!R36 -> 1867.2742 | K16: ='Workshop #5'!S36 -> 1941.9652 | L16: ='Workshop #5'!T36 -> 2019.6438
B17: Net Income | C17: =C15-C16 -> 6606 | D17: =D15-D16 -> 8531 | E17: =E15-E16 -> 9976 | F17: =F15-F16 -> 6359 | G17: =G15-G16 -> 5782 | H17: ='Workshop #5'!P37 -> 5658.4694 | I17: ='Workshop #5'!Q37 -> 6594.5969 | J17: ='Workshop #5'!R37 -> 6800.9523 | K17: ='Workshop #5'!S37 -> 7008.2729 | L17: ='Workshop #5'!T37 -> 7223.8863
B20: Balance Sheet
B21: Report Date | C21: 2020 | D21: 2021 | E21: 2022 | F21: 2023 | G21: =2024 -> 2024 | H21: 2025 | I21: 2026 | J21: 2027 | K21: 2028 | L21: 2029
B22: Cash & ST Investments | C22: =Financials!B55 -> 6316 | D22: =Financials!C55 -> 10593 | E22: =Financials!D55 -> 7595 | F22: =Financials!E55 -> 6072 | G22: =Financials!F55 -> 6318 | H22: ='Workshop #5'!P45 -> 6570.72 | I22: ='Workshop #5'!Q45 -> 6833.5488 | J22: ='Workshop #5'!R45 -> 7106.8908 | K22: ='Workshop #5'!S45 -> 7391.1664 | L22: ='Workshop #5'!T45 -> 7686.813
B23: Receivables ST | C23: =Financials!B60 -> 11167 | D23: =Financials!C60 -> 12973 | E23: =Financials!D60 -> 13037 | F23: =Financials!E60 -> 11579 | G23: =Financials!F60 -> 11314 | H23: ='Workshop #5'!P46 -> 11766.56 | I23: ='Workshop #5'!Q46 -> 12237.222 | J23: ='Workshop #5'!R46 -> 12726.711 | K23: ='Workshop #5'!S46 -> 13235.78 | L23: ='Workshop #5'!T46 -> 13765.211
B24: Bad Debt | C24: =-Financials!B61 -> 138 | D24: =-Financials!C61 -> 128 | E24: =-Financials!D61 -> 146 | F24: =-Financials!E61 -> 126 | G24: =-Financials!F61 -> 136 | H24: ='Workshop #5'!P47 -> 141.44 | I24: ='Workshop #5'!Q47 -> 147.0976 | J24: ='Workshop #5'!R47 -> 152.9815 | K24: ='Workshop #5'!S47 -> 159.10076 | L24: ='Workshop #5'!T47 -> 165.46479
B25: Inventories | C25: =Financials!B63 -> 620 | D25: =Financials!C63 -> 717 | E25: =Financials!D63 -> 889 | F25: =Financials!E63 -> 935 | G25: =Financials!F63 -> 826 | H25: ='Workshop #5'!P48 -> 859.04 | I25: ='Workshop #5'!Q48 -> 893.4016 | J25: ='Workshop #5'!R48 -> 929.13766 | K25: ='Workshop #5'!S48 -> 966.30317 | L25: ='Workshop #5'!T48 -> 1004.9553
B26: Other Current Assets | C26: =Financials!B65 -> 2251 | D26: =Financials!C65 -> 779 | E26: =Financials!D65 -> 842 | F26: =Financials!E65 -> 953 | G26: =Financials!F65 -> 988 | H26: ='Workshop #5'!P49 -> 1027.52 | I26: ='Workshop #5'!Q49 -> 1068.6208 | J26: ='Workshop #5'!R49 -> 1111.3656 | K26: ='Workshop #5'!S49 -> 1155.8203 | L26: ='Workshop #5'!T49 -> 1202.0531
B27: Total Current Assets | C27: =C22+C23-C24+C25+C26 -> 20216 | D27: =D22+D23-D24+D25+D26 -> 24934 | E27: =E22+E23-E24+E25+E26 -> 22217 | F27: =F22+F23-F24+F25+F26 -> 19413 | G27: =G22+G23-G24+G25+G26 -> 19310 | H27: ='Workshop #5'!P50 -> 20082.4 | I27: ='Workshop #5'!Q50 -> 20885.696 | J27: ='Workshop #5'!R50 -> 21721.124 | K27: ='Workshop #5'!S50 -> 22589.969 | L27: ='Workshop #5'!T50 -> 23493.568
B28: Gross PP&E | C28: =Financials!B69 -> 65164 | D28: =Financials!C69 -> 68371 | E28: =Financials!D69 -> 71185 | F28: =Financials!E69 -> 75823 | G28: =Financials!F69 -> 77445 | H28: ='Workshop #5'!P51 -> 80542.8 | I28: ='Workshop #5'!Q51 -> 83764.512 | J28: ='Workshop #5'!R51 -> 87115.092 | K28: ='Workshop #5'!S51 -> 90599.696 | L28: ='Workshop #5'!T51 -> 94223.684
B29: Accumulated Depr | C29: =Financials!B77 -> 29837 | D29: =Financials!C77 -> 31334 | E29: =Financials!D77 -> 32711 | F29: =Financials!E77 -> 34570 | G29: =Financials!F77 -> 36117 | H29: ='Workshop #5'!P52 -> 37561.68 | I29: ='Workshop #5'!Q52 -> 39064.147 | J29: ='Workshop #5'!R52 -> 40626.713 | K29: ='Workshop #5'!S52 -> 42251.782 | L29: ='Workshop #5'!T52 -> 43941.853
B30: Net PP&E | C30: =C28-C29 -> 35327 | D30: =D28-D29 -> 37037 | E30: =E28-E29 -> 38474 | F30: =F28-F29 -> 41253 | G30: =G28-G29 -> 41328 | H30: ='Workshop #5'!P53 -> 42981.12 | I30: ='Workshop #5'!Q53 -> 44700.365 | J30: ='Workshop #5'!R53 -> 46488.379 | K30: ='Workshop #5'!S53 -> 48347.915 | L30: ='Workshop #5'!T53 -> 50281.831
B31: Intangible Assets | C31: =Financials!B81 -> 5641 | D31: =Financials!C81 -> 6178 | E31: =Financials!D81 -> 7019 | F31: =Financials!E81 -> 8177 | G31: =Financials!F81 -> 7364 | H31: ='Workshop #5'!P54 -> 7658.56 | I31: ='Workshop #5'!Q54 -> 7964.9024 | J31: ='Workshop #5'!R54 -> 8283.4985 | K31: ='Workshop #5'!S54 -> 8614.8384 | L31: ='Workshop #5'!T54 -> 8959.432
B32: Other Assets | C32: =Financials!B85 -> 672 | D32: =Financials!C85 -> 1054 | E32: =Financials!D85 -> 2720 | F32: =Financials!E85 -> 1464 | G32: =Financials!F85 -> 1457 | H32: ='Workshop #5'!P55 -> 1515.28 | I32: ='Workshop #5'!Q55 -> 1575.8912 | J32: ='Workshop #5'!R55 -> 1638.9268 | K32: ='Workshop #5'!S55 -> 1704.4839 | L32: ='Workshop #5'!T55 -> 1772.6633
B33: Long-Term Investments | C33: =Financials!B78 -> 25 | D33: =Financials!C78 -> 26 | E33: =Financials!D78 -> 555 | F33: =Financials!E78 -> 424 | G33: =Financials!F78 -> 499 | H33: ='Workshop #5'!P56 -> 518.96 | I33: ='Workshop #5'!Q56 -> 539.7184 | J33: ='Workshop #5'!R56 -> 561.30714 | K33: ='Workshop #5'!S56 -> 583.75942 | L33: ='Workshop #5'!T56 -> 607.1098
B34: Deferred Tax Assets | C34: =Financials!B84 -> 527 | D34: =Financials!C84 -> 176 | E34: =Financials!D84 -> 139 | F34: =Financials!E84 -> 126 | G34: =Financials!F84 -> 112 | H34: ='Workshop #5'!P57 -> 116.48 | I34: ='Workshop #5'!Q57 -> 121.1392 | J34: ='Workshop #5'!R57 -> 125.98477 | K34: ='Workshop #5'!S57 -> 131.02416 | L34: ='Workshop #5'!T57 -> 136.26513
B35: Total Assets | C35: =SUM(C27,C30:C34) -> 62408 | D35: =SUM(D27,D30:D34) -> 69405 | E35: =SUM(E27,E30:E34) -> 71124 | F35: =SUM(F27,F30:F34) -> 70857 | G35: =SUM(G27,G30:G34) -> 70070 | H35: ='Workshop #5'!P58 -> 72872.8 | I35: ='Workshop #5'!Q58 -> 75787.712 | J35: ='Workshop #5'!R58 -> 78819.22 | K35: ='Workshop #5'!S58 -> 81971.989 | L35: ='Workshop #5'!T58 -> 85250.869
B36: Accounts Payable | C36: =Financials!B90 -> 6455 | D36: =Financials!C90 -> 7523 | E36: =Financials!D90 -> 7512 | F36: =Financials!E90 -> 6340 | G36: =Financials!F90 -> 6302 | H36: ='Workshop #5'!P59 -> 6554.08 | I36: ='Workshop #5'!Q59 -> 6816.2432 | J36: ='Workshop #5'!R59 -> 7088.8929 | K36: ='Workshop #5'!S59 -> 7372.4486 | L36: ='Workshop #5'!T59 -> 7667.3466
B37: ST Debt | C37: =Financials!B89 -> 3183 | D37: =Financials!C89 -> 2711 | E37: =Financials!D89 -> 2962 | F37: =Financials!E89 -> 4057 | G37: =Financials!F89 -> 2571 | H37: ='Workshop #5'!P60 -> 2571 | I37: ='Workshop #5'!Q60 -> 2571 | J37: ='Workshop #5'!R60 -> 2571 | K37: ='Workshop #5'!S60 -> 2571 | L37: ='Workshop #5'!T60 -> 2571
B38: Other Current Liabilities | C38: =Financials!B91 -> 7378 | D38: =Financials!C91 -> 7335 | E38: =Financials!D91 -> 7666 | F38: =Financials!E91 -> 7279 | G38: =Financials!F91 -> 7568 | H38: ='Workshop #5'!P61 -> 7568 | I38: ='Workshop #5'!Q61 -> 7568 | J38: ='Workshop #5'!R61 -> 7568 | K38: ='Workshop #5'!S61 -> 7568 | L38: ='Workshop #5'!T61 -> 7568
B39: Total Current Liabilities | C39: =SUM(C36:C38) -> 17016 | D39: =SUM(D36:D38) -> 17569 | E39: =SUM(E36:E38) -> 18140 | F39: =SUM(F36:F38) -> 17676 | G39: =SUM(G36:G38) -> 16441 | H39: ='Workshop #5'!P62 -> 16693.08 | I39: ='Workshop #5'!Q62 -> 16955.243 | J39: ='Workshop #5'!R62 -> 17227.893 | K39: ='Workshop #5'!S62 -> 17511.449 | L39: ='Workshop #5'!T62 -> 17806.347
B40: LT Debt | C40: =Financials!B95 -> 24571 | D40: =Financials!C95 -> 22817 | E40: =Financials!D95 -> 20559 | F40: =Financials!E95 -> 22672 | G40: =Financials!F95 -> 23081 | H40: ='Workshop #5'!P63 -> 9544 | I40: ='Workshop #5'!Q63 -> 11206.888 | J40: ='Workshop #5'!R63 -> 13085.844 | K40: ='Workshop #5'!S63 -> 15039.957 | L40: ='Workshop #5'!T63 -> 17072.236
B41: Provisions for Risk & Charges | C41: =Financials!B98 -> 16654 | D41: =Financials!C98 -> 8877 | E41: =Financials!D98 -> 5628 | F41: =Financials!E98 -> 6972 | G41: =Financials!F98 -> 7663 | H41: ='Workshop #5'!P64 -> 23081 | I41: ='Workshop #5'!Q64 -> 23081 | J41: ='Workshop #5'!R64 -> 23081 | K41: ='Workshop #5'!S64 -> 23081 | L41: ='Workshop #5'!T64 -> 23081
B42: Deffered Tax Liabilities | C42: =Financials!B99 -> 488 | D42: =Financials!C99 -> 3125 | E42: =Financials!D99 -> 4302 | F42: =Financials!E99 -> 3772 | G42: =Financials!F99 -> 3595 | H42: ='Workshop #5'!P65 -> 3595 | I42: ='Workshop #5'!Q65 -> 3888.352 | J42: ='Workshop #5'!R65 -> 4043.8861 | K42: ='Workshop #5'!S65 -> 4205.6415 | L42: ='Workshop #5'!T65 -> 4373.8672
B43: Other Liabilities | C43: =Financials!B100 -> 3010 | D43: =Financials!C100 -> 2748 | E43: =Financials!D100 -> 2692 | F43: =Financials!E100 -> 2451 | G43: =Financials!F100 -> 2547 | H43: ='Workshop #5'!P66 -> 2547 | I43: ='Workshop #5'!Q66 -> 2547 | J43: ='Workshop #5'!R66 -> 2547 | K43: ='Workshop #5'!S66 -> 2547 | L43: ='Workshop #5'!T66 -> 2547
B44: Total Liabilities | C44: =SUM(C39:C43) -> 61739 | D44: =SUM(D39:D43) -> 55136 | E44: =SUM(E39:E43) -> 51321 | F44: =SUM(F39:F43) -> 53543 | G44: =SUM(G39:G43) -> 53327 | H44: ='Workshop #5'!P67 -> 55460.08 | I44: ='Workshop #5'!Q67 -> 57678.483 | J44: ='Workshop #5'!R67 -> 59985.623 | K44: ='Workshop #5'!S67 -> 62385.047 | L44: ='Workshop #5'!T67 -> 64880.449

Sheet WS6 Work
B4: UPS 10-Year Historical Prices | F4: S&P500 10-Year Historical Prices | J4: 60 Month Rolling Beta
B6: Date | C6: Price | F6: Date | G6: Price | H6: Return | J6: Date | K6: Beta
B7: 46052 | C7: 106.22 | D7: UPS | F7: 46052 | G7: 6939.03 | H7: S&P500 | J7: 46052 | K7: =SLOPE(D7:D67,H7:H67) -> 1.1110203
B8: 46022 | C8: 99.19 | D8: =(C8-C7)/C7 -> -0.066183393 | F8: 46022 | G8: 6845.5047 | H8: =(G8-G7)/G7 -> -0.013478151 | J8: 46022 | K8: =SLOPE(D8:D68,H8:H68) -> 1.1207493
B9: 45989 | C9: 95.79 | D9: =(C9-C8)/C8 -> -0.034277649 | F9: 45989 | G9: 6849.0874 | H9: =(G9-G8)/G8 -> 0.00052336042 | J9: 45989 | K9: =SLOPE(D9:D69,H9:H69) -> 1.1100819
B10: 45961 | C10: 96.42 | D10: =(C10-C9)/C9 -> 0.0065768869 | F10: 45961 | G10: 6840.1987 | H10: =(G10-G9)/G9 -> -0.0012977833 | J10: 45961 | K10: =SLOPE(D10:D70,H10:H70) -> 1.1129741
B11: 45930 | C11: 83.53 | D11: =(C11-C10)/C10 -> -0.13368596 | F11: 45930 | G11: 6688.459 | H11: =(G11-G10)/G10 -> -0.022183523 | J11: 45930 | K11: =SLOPE(D11:D71,H11:H71) -> 1.1158557
B12: 45898 | C12: 87.44 | D12: =(C12-C11)/C11 -> 0.04680953 | F12: 45898 | G12: 6460.2627 | H12: =(G12-G11)/G11 -> -0.034117929 | J12: 45898 | K12: =SLOPE(D12:D72,H12:H72) -> 1.0671493
B13: 45869 | C13: 86.16 | D13: =(C13-C12)/C12 -> -0.014638609 | F13: 45869 | G13: 6339.3946 | H13: =(G13-G12)/G12 -> -0.018709471 | J13: 45869 | K13: =SLOPE(D13:D73,H13:H73) -> 1.1138382
B14: 45838 | C14: 100.94 | D14: =(C14-C13)/C13 -> 0.17154132 | F14: 45838 | G14: 6204.954 | H14: =(G14-G13)/G13 -> -0.021207169 | J14: 45838 | K14: =SLOPE(D14:D74,H14:H74) -> 1.1725401
B15: 45807 | C15: 97.54 | D15: =(C15-C14)/C14 -> -0.033683376 | F15: 45807 | G15: 5911.6867 | H15: =(G15-G14)/G14 -> -0.047263401 | J15: 45807 | K15: =SLOPE(D15:D75,H15:H75) -> 1.1930128
B16: 45777 | C16: 95.3 | D16: =(C16-C15)/C15 -> -0.022964937 | F16: 45777 | G16: 5569.0647 | H16: =(G16-G15)/G15 -> -0.057956733 | J16: 45777 | K16: =SLOPE(D16:D76,H16:H76) -> 1.1987407
B17: 45747 | C17: 109.99 | D17: =(C17-C16)/C16 -> 0.15414481 | F17: 45747 | G17: 5611.8526 | H17: =(G17-G16)/G16 -> 0.0076831451 | J17: 45747 | K17: =SLOPE(D17:D77,H17:H77) -> 1.1307935
B18: 45716 | C18: 119.03 | D18: =(C18-C17)/C17 -> 0.08218929 | F18: 45716 | G18: 5954.5048 | H18: =(G18-G17)/G17 -> 0.061058664 | J18: 45716 | K18: =SLOPE(D18:D78,H18:H78) -> 0.91853452
B19: 45688 | C19: 114.23 | D19: =(C19-C18)/C18 -> -0.040325968 | F19: 45688 | G19: 6040.5259 | H19: =(G19-G18)/G18 -> 0.014446391 | J19: 45688 | K19: =SLOPE(D19:D79,H19:H79) -> 0.94216847
... B67: 44225 | C67: 155 | D67: =(C67-C66)/C66 -> -0.017930685 | F67: 44225 | G67: 3714.2427 | H67: =(G67-G66)/G66 -> -0.025427251 | J67: 44225 | K67: =SLOPE(D67:D127,H67:H127) -> 1.0079415
B68: 44196 | C68: 168.4 | D68: =(C68-C67)/C67 -> 0.086451613 | F68: 44196 | G68: 3756.0715 | H68: =(G68-G67)/G67 -> 0.011261725 | J68: 44196 | K68: =SLOPE(D68:D127,H68:H127) -> 1.0083852
B69: 44165 | C69: 171.07 | D69: =(C69-C68)/C68 -> 0.015855107 | F69: 44165 | G69: 3621.6334 | H69: =(G69-G68)/G68 -> -0.035792194 | J69: 44165 | K69: =SLOPE(D69:D128,H69:H128) -> 0.99493508
B70: 44134 | C70: 157.11 | D70: =(C70-C69)/C69 -> -0.081604022 | F70: 44134 | G70: 3269.9591 | H70: =(G70-G69)/G69 -> -0.097103793 | J70: 44134 | K70: =SLOPE(D70:D129,H70:H129) -> 1.0061771
B71: 44104 | C71: 166.63 | D71: =(C71-C70)/C70 -> 0.060594488 | F71: 44104 | G71: 3362.999 | H71: =(G71-G70)/G70 -> 0.028452925 | J71: 44104 | K71: =SLOPE(D71:D130,H71:H130) -> 1.0178796
B72: 44074 | C72: 163.62 | D72: =(C72-C71)/C71 -> -0.018063974 | F72: 44074 | G72: 3500.3085 | H72: =(G72-G71)/G71 -> 0.04082949 | J72: 44074 | K72: =SLOPE(D72:D131,H72:H131) -> 1.007214
B73: 44043 | C73: 142.76 | D73: =(C73-C72)/C72 -> -0.12749053 | F73: 44043 | G73: 3271.1249 | H73: =(G73-G72)/G72 -> -0.065475268 | J73: 44043 | K73: =SLOPE(D73:D132,H73:H132) -> 1.0378556
B74: 44012 | C74: 111.18 | D74: =(C74-C73)/C73 -> -0.22121042 | F74: 44012 | G74: 3100.2851 | H74: =(G74-G73)/G73 -> -0.052226606 | J74: 44012 | K74: =SLOPE(D74:D133,H74:H133) -> 0.95149402
B75: 43980 | C75: 99.71 | D75: =(C75-C74)/C74 -> -0.10316604 | F75: 43980 | G75: 3044.3052 | H75: =(G75-G74)/G74 -> -0.018056395 | J75: 43980 | K75: =SLOPE(D75:D134,H75:H134) -> 0.80860655
B76: 43951 | C76: 94.66 | D76: =(C76-C75)/C75 -> -0.050646876 | F76: 43951 | G76: 2912.4305 | H76: =(G76-G75)/G75 -> -0.043318466 | J76: 43951 | K76: =SLOPE(D76:D135,H76:H135) -> 0.80373047
B77: 43921 | C77: 93.42 | D77: =(C77-C76)/C76 -> -0.013099514 | F77: 43921 | G77: 2584.5908 | H77: =(G77-G76)/G76 -> -0.11256569 | J77: 43921 | K77: =SLOPE(D77:D136,H77:H136) -> 0.74931892
B78: 43889 | C78: 90.49 | D78: =(C78-C77)/C77 -> -0.031363734 | F78: 43889 | G78: 2954.2237 | H78: =(G78-G77)/G77 -> 0.1430141 | J78: 43889 | K78: =SLOPE(D78:D137,H78:H137) -> 0.78872552
B79: 43861 | C79: 103.52 | D79: =(C79-C78)/C78 -> 0.14399381 | F79: 43861 | G79: 3225.5163 | H79: =(G79-G78)/G78 -> 0.091832123 | J79: 43861 | K79: =SLOPE(D79:D138,H79:H138) -> 0.97455802
... B127: 42398 | C127: 93.2 | D127: =(C127-C126)/C126 -> -0.034697048 | F127: 42398 | G127: 1940.2397 | H127: =(G127-G126)/G126 -> 0.004147176 | J127: 42398 | K127: =SLOPE(D127:D186,H127:H186) -> 0.3197099
B130: S&P 500 5-Year Historical Prices | F130: FDX 5-Year Historical Prices | J130: DHL 5-Year Historical Prices | N130: EXPD 5-Year Historical Prices | R130: ODFL 5-Year Historical Prices | V130: TFII 5-Year Historical Prices
B131: Date | C131: Price | D131: Return | F131: Date | G131: Price | H131: Return | J131: Date | K131: Price | L131: Return | N131: Date | O131: Price | P131: Return | R131: Date | S131: Price | T131: Return | V131: Date | W131: Price | X131: Return
B132: 44225 | C132: 3714.2427 | D132: S&P500 | F132: 44225 | G132: 235.34 | H132: FDX | J132: 44225 | K132: 49.580067 | L132: DHL | N132: 44225 | O132: 89.52 | P132: EXPD | R132: 44253 | S132: 107.385 | T132: ODFL | V132: 44225 | W132: 66.491844 | X132: TFII
B133: 44253 | C133: 3811.1497 | D133: =(C133-C132)/C132 -> 0.026090664 | F133: 44253 | G133: 254.5 | H133: =(G133-G132)/G132 -> 0.081414124 | J133: 44253 | K133: 49.838627 | L133: =(K133-K132)/K132 -> 0.005214999 | N133: 44253 | O133: 91.84 | P133: =(O133-O132)/O132 -> 0.025915996 | R133: 44286 | S133: 120.205 | T133: =(S133-S132)/S132 -> 0.11938353 | V133: 44253 | W133: 70.213264 | X133: =(W133-W132)/W132 -> 0.055968067
B134: 44286 | C134: 3972.8922 | D134: =(C134-C133)/C133 -> 0.042439282 | F134: 44286 | G134: 284.04 | H134: =(G134-G133)/G133 -> 0.11607073 | J134: 44286 | K134: 54.910015 | L134: =(K134-K133)/K133 -> 0.10175617 | N134: 44286 | O134: 107.69 | P134: =(O134-O133)/O133 -> 0.17258275 | R134: 44316 | S134: 128.905 | T134: =(S134-S133)/S133 -> 0.072376357 | V134: 44286 | W134: 74.94927 | X134: =(W134-W133)/W133 -> 0.067451728
B135: 44316 | C135: 4181.1749 | D135: =(C135-C134)/C134 -> 0.05242596 | F135: 44316 | G135: 290.31 | H135: =(G135-G134)/G134 -> 0.022074356 | J135: 44316 | K135: 58.93203 | L135: =(K135-K134)/K134 -> 0.073247385 | N135: 44316 | O135: 109.86 | P135: =(O135-O134)/O134 -> 0.020150432 | R135: 44344 | S135: 132.725 | T135: =(S135-S134)/S134 -> 0.029634227 | V135: 44316 | W135: 87.54674 | X135: =(W135-W134)/W134 -> 0.16807996
B136: 44344 | C136: 4204.1105 | D136: =(C136-C135)/C135 -> 0.0054854558 | F136: 44344 | G136: 314.81 | H136: =(G136-G135)/G135 -> 0.084392546 | J136: 44347 | K136: 68.22388 | L136: =(K136-K135)/K135 -> 0.15767062 | N136: 44344 | O136: 125.69 | P136: =(O136-O135)/O135 -> 0.14409248 | R136: 44377 | S136: 126.9 | T136: =(S136-S135)/S135 -> -0.043887738 | V136: 44347 | W136: 96.06821 | X136: =(W136-W135)/W135 -> 0.097336234
B137: 44377 | C137: 4297.4966 | D137: =(C137-C136)/C136 -> 0.022213043 | F137: 44377 | G137: 298.33 | H137: =(G137-G136)/G136 -> -0.052349036 | J137: 44377 | K137: 68.023224 | L137: =(K137-K136)/K136 -> -0.0029411403 | N137: 44377 | O137: 126.6 | P137: =(O137-O136)/O136 -> 0.007240035 | R137: 44407 | S137: 134.575 | T137: =(S137-S136)/S136 -> 0.060480693 | V137: 44377 | W137: 91.391426 | X137: =(W137-W136)/W136 -> -0.04868191
B138: 44407 | C138: 4395.264 | D138: =(C138-C137)/C137 -> 0.022749835 | F138: 44407 | G138: 279.95 | H138: =(G138-G137)/G137 -> -0.061609627 | J138: 44407 | K138: 67.72104 | L138: =(K138-K137)/K137 -> -0.0044423652 | N138: 44407 | O138: 128.25 | P138: =(O138-O137)/O137 -> 0.013033175 | R138: 44439 | S138: 144.36 | T138: =(S138-S137)/S137 -> 0.072710385 | V138: 44407 | W138: 111.87568 | X138: =(W138-W137)/W137 -> 0.22413759
B139: 44439 | C139: 4522.6801 | D139: =(C139-C138)/C138 -> 0.028989419 | F139: 44439 | G139: 265.69 | H139: =(G139-G138)/G138 -> -0.050937667 | J139: 44439 | K139: 70.33121 | L139: =(K139-K138)/K138 -> 0.03854297 | N139: 44439 | O139: 124.64 | P139: =(O139-O138)/O138 -> -0.028148148 | R139: 44469 | S139: 142.99 | T139: =(S139-S138)/S138 -> -0.0094901635 | V139: 44439 | W139: 112.80814 | X139: =(W139-W138)/W138 -> 0.0083347873
B140: 44469 | C140: 4307.5388 | D140: =(C140-C139)/C139 -> -0.047569442 | F140: 44469 | G140: 219.29 | H140: =(G140-G139)/G139 -> -0.17463962 | J140: 44469 | K140: 63.139595 | L140: =(K140-K139)/K139 -> -0.10225354 | N140: 44469 | O140: 119.13 | P140: =(O140-O139)/O139 -> -0.044207317 | R140: 44498 | S140: 170.675 | T140: =(S140-S139)/S139 -> 0.19361494 | V140: 44469 | W140: 102.28519 | X140: =(W140-W139)/W139 -> -0.093281797
B141: 44498 | C141: 4605.3766 | D141: =(C141-C140)/C140 -> 0.069143405 | F141: 44498 | G141: 235.53 | H141: =(G141-G140)/G140 -> 0.074057185 | J141: 44498 | K141: 61.93602 | L141: =(K141-K140)/K140 -> -0.019062127 | N141: 44498 | O141: 123.26 | P141: =(O141-O140)/O140 -> 0.03466801 | R141: 44530 | S141: 177.585 | T141: =(S141-S140)/S140 -> 0.040486304 | V141: 44498 | W141: 110.70953 | X141: =(W141-W140)/W140 -> 0.082361207
B142: 44530 | C142: 4567.0015 | D142: =(C142-C141)/C141 -> -0.0083326853 | F142: 44530 | G142: 230.37 | H142: =(G142-G141)/G141 -> -0.021908037 | J142: 44530 | K142: 58.72255 | L142: =(K142-K141)/K141 -> -0.051883702 | N142: 44530 | O142: 121.62 | P142: =(O142-O141)/O141 -> -0.013305209 | R142: 44561 | S142: 179.19 | T142: =(S142-S141)/S141 -> 0.0090379255 | V142: 44530 | W142: 98.87746 | X142: =(W142-W141)/W141 -> -0.10687487
B143: 44561 | C143: 4766.183 | D143: =(C143-C142)/C142 -> 0.043613184 | F143: 44561 | G143: 258.64 | H143: =(G143-G142)/G142 -> 0.12271563 | J143: 44560 | K143: 64.065475 | L143: =(K143-K142)/K142 -> 0.090985916 | N143: 44561 | O143: 134.29 | P143: =(O143-O142)/O142 -> 0.10417694 | R143: 44592 | S143: 150.965 | T143: =(S143-S142)/S142 -> -0.15751437 | V143: 44561 | W143: 112.31445 | X143: =(W143-W142)/W142 -> 0.13589538
B144: 44592 | C144: 4515.5476 | D144: =(C144-C143)/C143 -> -0.052586188 | F144: 44592 | G144: 245.86 | H144: =(G144-G143)/G143 -> -0.049412311 | J144: 44592 | K144: 59.40179 | L144: =(K144-K143)/K143 -> -0.072795605 | N144: 44592 | O144: 114.48 | P144: =(O144-O143)/O143 -> -0.14751657 | R144: 44620 | S144: 157.015 | T144: =(S144-S143)/S143 -> 0.040075514 | V144: 44592 | W144: 96.20223 | X144: =(W144-W143)/W143 -> -0.14345634
... B192: 46052 | C192: 6939.0295 | D192: =(C192-C191)/C191 -> 0.013662223 | F192: 46052 | G192: 322.25 | H192: =(G192-G191)/G191 -> 0.11559233 | J192: 46052 | K192: 56.294235 | L192: =(K192-K191)/K191 -> 0.024510083 | N192: 46052 | O192: 160.54 | P192: =(O192-O191)/O191 -> 0.077377357 | R192: 46052 | S192: 173.2 | T192: =(S192-S191)/S191 -> 0 | V192: 46052 | W192: 107.44601 | X192: =(W192-W191)/W191 -> 0.038144874

Sheet Comparable Firms
A2: All Comparables
A3: Company Name | B3: Exchange:Ticker | C3: Industry Group | D3: Primary Sector | E3: SIC Code | F3: Country | G3: Broad Group | H3: Sub Group | I3: Bottom up Beta for sector | J3: Bottom up levered beta | K3: ERP for Country | L3: Cost of equity in US$ | M3: Default Spread based on bond rating (if available) | N3: Total Default Spread for cost of debt (Company + Country) | O3: Pre-tax cost of debt in US $ | P3: After-tax cost of debt in US $ | Q3: Cost of capital in US$ | R3: ROE - Cost of Equity | S3: ROIC - Cost of Capital | T3: Market Cap (in US $) | U3: PV of lease debt | V3: Total Debt without Oper Leases | W3: Total Debt incl leases (in US $) | X3: Firm Value (in US $) | Y3: Cash | Z3: Enterprise Value (in US $) | AA3: Cash/ Firm Value | AB3: Liquidity Ratio (Annual trading volume/Shrs outs) | AC3: Book Debt to capital ratio | AD3: Market Debt to capital ratio | AE3: Book Debt to Equity Ratio | AF3: Market Debt to Equity ratio | AG3: Stock price (End of most recent year)in US$ | AH3: Price Change for Sub-group | AI3: Jensen's Alpha | AJ3: Beta | AK3: Correlation with market | AL3: Standard deviation in stock price | AM3: HiL0 Risk Measure (Hi- lo)/ (Hi+Lo) | AN3: Interest coverage ratio | AO3: Current PE | AP3: Trailing PE | AQ3: PE- Start of 2024 | AR3: Forward PE | AS3: PEG | AT3: PBV | AU3: PBV - Start of 2024 | AV3: PS | AW3: EV/EBIT | AX3: EV/EBITDA | AY3: EV/Invested Capital | AZ3: EV/Sales | BA3: Payout ratio | BB3: Dividend Yield | BC3: Price Change in 2023 | BD3: Historical growth in Net Income - Last 3 years | BE3: Historical growth in Net Income - Last 5 years | BF3: Historical growth in Revenues - Last 3 years | BG3: Historical growth in Revenues - Last 5 years | BH3: Expected growth rate in EPS- Next 5 years | BI3: Expected growth in revenues - Next 2 years | BJ3: Return on Equity | BK3: Return on Capital (ROC or ROIC) | BL3: Sales/Capital | BM3: Net Profit Margin | BN3: Pre-tax Operating Margin | BO3: Gross Margin | BP3: Marginal Tax Rate | BQ3: Effective Tax Rate | BR3: % held by institutions | BS3: Net Income | BT3: Trailing Net Income | BU3: Operating Income | BV3: Trailing Operating Income (adj for leases) | BW3: Trailing Gross Profit | BX3: Revenues | BY3: Trailing Revenues | BZ3: EBITDA | CA3: Trailing EBITDA (adj for leases) | CB3: Trailing After-tax Operating Income | CC3: Net Debt repaid (Debt repaid - issued) | CD3: Change in non-cash Working capital | CE3: Non-cash Working Capital | CF3: Non-cash Working Capital as % of Revenues | CG3: Net Cap Ex | CH3: Reinvestment Rate | CI3: FCFF | CJ3: FCFE | CK3: FCFE without debt | CL3: Book Value of Equity - 4 qtrs ago | CM3: Invested Capital - 4 qtre ago | CN3: Current Book Value of Equity | CO3: Current Invested Capital | CP3: Dividends | CQ3: Modified 2-year beta | CR3: Modified 5-year beta | CS3: Beta adjustment factor | CT3: Coeff of variation - Op Income | CU3: Coeff of variation - Net Income | CV3: Average 10-year EBIT | CW3: Average 10-yr Net Income | CX3: Dividends + Buybacks | CY3: Only +ve Taxable Income | CZ3: Only +ve Taxes | DA3: Only +'ve Net Income | DB3: Onlt +'ve Net Income Mkt cap | DC3: Only +"ve EBITDA | DD3: Only +ve EBITDA EV | DE3: Only +ve div FCFE | DF3: Capitalized R&D | DG3: Operating Income adjusted for leases & R&D | DH3: Invested Capital Adjusted for R&D | DI3: EBITDAR&D | DJ3: ROE (adj for R&D) | DK3: ROIC (adj for R&D) | DL3: EV/EBITDAR&D | DM3: Depreciation & Amortization (Modified) | DN3: Invested Capital - 10 years ago | DO3: Normalized Operating Income | DP3: Normalized ROIC | DQ3: Change in Debt | DR3: Debt Repaid | DS3: Debt Issued | DT3: Change in Lease Commitments | DU3: Equity Issuances | DV3: EBIT | DW3: Interest expense | DX3: Interest Income | DY3: Accounts Payable | DZ3: Company Age | EA3: % Price Change: 2023 Q1 | EB3: % Price Change: 2023 Q2 | EC3: % Price Change: 2023 Q3 | ED3: % Pirce change: 2023 Q4 | EE3: % Price Change: 2023 | EF3: % Change in Revenue in LTM | EG3: Operating Margin in LTM 2022 | EH3: Operating Margin one year before | EI3: Change in Debt | EJ3: EBIT [LTM] ($USDmm, Historical rate) | EK3: EBIT [LTM - 1] ($USDmm, Historical rate) | EL3: Market Capitalization [My Setting] [12/31/2024] ($USDmm, Historical rate) | EM3: Market Capitalization [My Setting] [03/31/2025] ($USDmm, Historical rate) | EN3: Market Capitalization [My Setting] [06/30/2025] ($USDmm, Historical rate) | EO3: Market Capitalization [My Setting] [09/30/2025] ($USDmm, Historical rate) | EP3: Revenues (with employee count) | EQ3: Market Cap (with employee count) | ER3: Money Maker indicator | ES3: Revenue Growth (last 5 yeers) | ET3: Expected revenue Growth (next 5 years) | EU3: Current Revenues (when revenues in 2018 available) | EV3: Current Revenue (when revenus in 2028 available) | EW3: Market Cap (Dec 30, 2014) | EX3: Market Cap (Dec 30, 2019) | EY3: Market Cap (Dec 30, 2020) | EZ3: Market Cap (Dec 30, 2021) | FA3: Market Cap (Dec 30, 2022) | FB3: Market Cap (Dec 30, 2023) | FC3: Short term Debt | FD3: Bonds as % of Debt | FE3: Floating Rate Debt | FF3: Fixd Rate Debt
A4: United Parcel Service, Inc. (NYSE:UPS) | B4: NYSE:UPS | C4: Transportation | D4: Industrials | E4: 4210 | F4: United States | G4: United States | H4: United States | I4: 0.7474 | J4: 0.9406 | K4: 0.0446 | L4: 0.0815 | M4: 0.0078 | N4: 0.0101 | O4: 0.0496 | P4: 0.0372 | Q4: 0.0701 | R4: 0.2449 | S4: 0.1232 | T4: 84151.4 | U4: 4217.15 | V4: 24782 | W4: 28999.15 | X4: 113150.55 | Y4: 6764 | Z4: 106386.55 | AA4: 0.0598 | AB4: 1.99 | AC4: 0.6466 | AD4: 0.2563 | AE4: 1.8298 | AF4: 0.3446 | AG4: 99.19 | AH4: 31.61 | AI4: -0.1445 | AJ4: 0.78 | AK4: 0.3899 | AL4: 0.2345 | AM4: 0.25 | AN4: 8.18 | AO4: 14.55 | AP4: 15.29 | AQ4: 14.23 | AR4: 14.44 | AS4: 2.39 | AT4: 5.31 | AU4: 4.91 | AV4: 0.92 | AW4: 13.37 | AX4: 8.55 | AY4: 3.2 | AZ4: 1.17 | BA4: 0.9806 | BB4: 0.0641 | BC4: 0.0228 | BD4: -0.211 | BE4: 0.0372 | BF4: -0.0398 | BG4: 0.0219 | BH4: 0.0608 | BI4: -0.0176 | BJ4: 0.3264 | BK4: 0.1933 | BL4: 2.73 | BM4: 0.0615 | BN4: 0.0889 | BO4: 0.2169 | BP4: 0.25 | BQ4: 0.2048 | BR4: 0.5761 | BS4: 5782 | BT4: 5502 | BU4: 7953 | BV4: 7956.57 | BW4: 19410 | BX4: 91070 | BY4: 89483 | BZ4: 11620 | CA4: 12448 | CB4: 6327.08 | CC4: -2465 | CD4: 817 | CE4: 5020 | CF4: 0.0561 | CG4: 858 | CH4: 0.2647 | CI4: 4652.08 | CJ4: 6292 | CK4: 3827 | CL4: 16857 | CM4: 32738.15 | CN4: 15848 | CO4: 33273.15 | CP4: -5395 | CQ4: 0.76 | CR4: 1.09 | CS4: 1.12 | CT4: 0.28 | CU4: 0.62 | CV4: 8983.6 | CW4: 6099 | CX4: -6395 | CY4: 6919 | CZ4: 1417 | DA4: 5502 | DB4: 84151.4 | DC4: 12448 | DD4: 106386.55 | DE4: 6292 | DF4: 0 | DG4: 7956.57 | DH4: 33273.15 | DI4: 11620 | DJ4: 0.3264 | DK4: 0.1933 | DL4: 9.16 | DM4: 3693 | DN4: 8505 | DO4: 8983.6 | DP4: 0.4301 | DQ4: $ 2,969.00 | DR4: 1,688.0 | DS4: 4,153.0 | DT4: #REF! | DU4: $ 181.00 | DV4: $ 7,953.00 | DW4: $ 972.00 | DX4: $ 697.00 | DY4: $ 5,784.00 | DZ4: 113 | EA4: -0.1337 | EB4: -0.0831 | EC4: -0.1717 | ED4: 0.1886 | EE4: -0.218 | EF4: -0.0092 | EG4: 0.0866 | EH4: 0.089 | EI4: $ 2,969.00 | EJ4: 7953 | EK4: 7825 | EL4: $ 107,609.90 | EM4: $ 93,220.00 | EN4: $ 85,475.80 | EO4: $ 70,797.50 | EP4: $ - | EQ4: $ - | ER4: 1 | ES4: 0.0112 | ET4: 0.0151 | EU4: 89483 | EV4: $ 89,483.00 | EW4: 100041.2 | EX4: 185909.5 | EY4: 150357.4 | EZ4: 133948.3 | FA4: 107609.9 | FB4: 82278.4 | FC4: 0 | FD4: 0.812 | FE4: 2246 | FF4: 21975
A5: Deutsche Post AG (XTRA:DHL) | B5: XTRA:DHL | C5: Transportation | D5: Industrials | E5: 4210 | F5: Germany | G5: Developed Europe | H5: EU & Environs | I5: 0.7474 | J5: 1.0099 | K5: 0.0423 | L5: 0.0822 | M5: NA | N5: 0.0055 | O5: 0.045 | P5: 0.0315 | Q5: 0.0653 | R5: 0.085 | S5: 0.0302 | T5: 61526.6 | U5: 0 | V5: 30835.4 | W5: 30835.4 | X5: 92362 | Y5: 4165.2 | Z5: 88196.8 | AA5: 0.0451 | AB5: 0.49 | AC5: 0.5462 | AD5: 0.3339 | AE5: 1.2034 | AF5: 0.5012 | AG5: 54.97 | AH5: 50.04 | AI5: -0.1489 | AJ5: 2.1 | AK5: 0.6033 | AL5: 0.2307 | AM5: 0.21 | AN5: 5.12 | AO5: 17.84 | AP5: 14.82 | AQ5: 12.88 | AR5: 14.47 | AS5: 1.88 | AT5: 2.4 | AU5: 1.77 | AV5: 0.7 | AW5: 13.58 | AX5: 9.49 | AY5: 1.69 | AZ5: 1 | BA5: 0.5999 | BB5: 0.0405 | BC5: 0.3847 | BD5: -0.137 | BE5: 0.069 | BF5: -0.0378 | BG5: 0.0533 | BH5: 0.0951 | BI5: 0.0074 | BJ5: 0.1672 | BK5: 0.0955 | BL5: 2.06 | BM5: 0.0421 | BN5: 0.0659 | BO5: 0.1716 | BP5: 0.2993 | BQ5: 0.2952 | BR5: 0.3541 | BS5: 3449.6 | BT5: 4152.3 | BU5: 6496.5 | BV5: 6496.5 | BW5: 16926 | BX5: 87764.8 | BY5: 98619 | BZ5: 7838.3 | CA5: 9298.4 | CB5: 4578.8 | CC5: 583.1 | CD5: 768.5 | CE5: -287.4 | CF5: -0.0029 | CG5: -2012.2 | CH5: -0.2716 | CI5: 5822.5 | CJ5: 4812.9 | CK5: 5396 | CL5: 24829.4 | CM5: 47936.7 | CN5: 25623.6 | CO5: 52293.8 | CP5: -2490.9 | CQ5: 1.16 | CR5: 1.15 | CS5: 0.55 | CT5: 0.46 | CU5: 0.39 | CV5: 5088.52 | CW5: 3579.49 | CX5: -4446.8 | CY5: 6212.6 | CZ5: 1833.9 | DA5: 4152.3 | DB5: 61526.6 | DC5: 9298.4 | DD5: 88196.8 | DE5: 4812.9 | DF5: 310.32 | DG5: 6508 | DH5: 52604.12 | DI5: 7946.2 | DJ5: 0.1656 | DK5: 0.0951 | DL5: 11.1 | DM5: 5697.5 | DN5: 801.3 | DO5: 5088.52 | DP5: 0.1917 | DQ5: $ 4,727.90 | DR5: 5,161.3 | DS5: 4,578.2 | DT5: #REF! | DU5: $ - | DV5: $ 6,496.50 | DW5: $ 1,268.30 | DX5: $ 255.80 | DY5: $ 8,868.90 | DZ5: 25 | EA5: 0.209 | EB5: 0.0653 | EC5: -0.0425 | ED5: 0.23 | EE5: 0.5167 | EF5: -0.0064 | EG5: 0.0637 | EH5: 0.066 | EI5: $ 4,727.90 | EJ5: 6496.5 | EK5: 6323 | EL5: $ 40,566.20 | EM5: $ 49,044.50 | EN5: $ 52,245.40 | EO5: $ 50,022.90 | EP5: $ 98,619.00 | EQ5: $ 61,526.60 | ER5: 1 | ES5: 0.0374 | ET5: 0.0207 | EU5: 98619 | EV5: $ 98,619.00 | EW5: 39376.3 | EX5: 78398 | EY5: 45307.3 | EZ5: 58616.6 | FA5: 40566.2 | FB5: 44432.8 | FC5: 0 | FD5: 0.309 | FE5: 0 | FF5: 11296.5
A6: Old Dominion Freight Line, Inc. (NasdaqGS:ODFL) | B6: NasdaqGS:ODFL | C6: Trucking | D6: Industrials | E6: 4210 | F6: United States | G6: United States | H6: United States | I6: 0.6693 | J6: 0.6722 | K6: 0.0446 | L6: 0.0695 | M6: NA | N6: 0.0112 | O6: 0.0507 | P6: 0.038 | Q6: 0.0693 | R6: 0.1837 | S6: 0.1783 | T6: 32786.6 | U6: 105.06 | V6: 85 | W6: 190.06 | X6: 32976.66 | Y6: 46.6 | Z6: 32930.06 | AA6: 0.0014 | AB6: 2.34 | AC6: 0.0427 | AD6: 0.0058 | AE6: 0.0446 | AF6: 0.0058 | AG6: 156.8 | AH6: 31.61 | AI6: 0.0427 | AJ6: 1.01 | AK6: 0.4528 | AL6: 0.2783 | AM6: 0.25 | AN6: 37589.19 | AO6: 27.64 | AP6: 31.01 | AQ6: 27.28 | AR6: 32.07 | AS6: 2.49 | AT6: 7.69 | AU6: 7.62 | AV6: 5.64 | AW6: 23.69 | AX6: 18.58 | AY6: 7.47 | AZ6: 5.66 | BA6: 0.22 | BB6: 0.0071 | BC6: 0.0133 | BD6: -0.0741 | BE6: 0.11 | BF6: -0.0337 | BG6: 0.0713 | BH6: 0.111 | BI6: -0.0138 | BJ6: 0.2532 | BK6: 0.2476 | BL6: 1.31 | BM6: 0.1897 | BN6: 0.2494 | BO6: 0.393 | BP6: 0.25 | BQ6: 0.2401 | BR6: 0.7798 | BS6: 1186.1 | BT6: 1057.4 | BU6: 1390.8 | BV6: 1390.29 | BW6: 2190.7 | BX6: 5814.8 | BY6: 5574.9 | BZ6: 1888.6 | CA6: 1772.1 | CB6: 1056.53 | CC6: -25 | CD6: -53.1 | CE6: 437.1 | CF6: 0.0784 | CG6: 179.4 | CH6: 0.1195 | CI6: 930.23 | CJ6: 956.1 | CK6: 931.1 | CL6: 4175.7 | CM6: 4266.56 | CN6: 4263.2 | CO6: 4406.66 | CP6: -232.6 | CQ6: 1.05 | CR6: 1.27 | CS6: 1.12 | CT6: 0.48 | CU6: 0.51 | CV6: 1051.75 | CW6: 734.37 | CX6: -1020.5 | CY6: 1391.3 | CZ6: 334 | DA6: 1057.4 | DB6: 32786.6 | DC6: 1772.1 | DD6: 32930.06 | DE6: 956.1 | DF6: 0 | DG6: 1390.29 | DH6: 4406.66 | DI6: 1888.6 | DJ6: 0.2532 | DK6: 0.2476 | DL6: 17.44 | DM6: 360.8 | DN6: 1595.5 | DO6: 1051.75 | DP6: 0.3505 | DQ6: $ 25.00 | DR6: 20.0 | DS6: 45.0 | DT6: #REF! | DU6: $ - | DV6: $ 1,390.80 | DW6: $ 0.04 | DX6: $ 4.81 | DY6: $ 81.90 | DZ6: 86 | EA6: -0.0663 | EB6: -0.0247 | EC6: -0.1373 | ED6: 0.1081 | EE6: -0.1294 | EF6: -0.0113 | EG6: 0.2539 | EH6: 0.249 | EI6: $ 25.00 | EJ6: 1390.8 | EK6: 1431.8 | EL6: $ 37,661.00 | EM6: $ 35,165.60 | EN6: $ 34,298.10 | EO6: $ 29,587.50 | EP6: $ - | EQ6: $ - | ER6: 1 | ES6: 0.0678 | ET6: 0.0371 | EU6: 5574.9 | EV6: $ 5,574.90 | EW6: 7072.5 | EX6: 40975 | EY6: 31352.5 | EZ6: 44227 | FA6: 37661 | FB6: 32355.7 | FC6: 0 | FD6: 0.356 | FE6: 45 | FF6: 40
A7: Grab Holdings Limited (NasdaqGS:GRAB) | B7: NasdaqGS:GRAB | C7: Transportation | D7: Industrials | E7: 4210 | F7: Singapore | G7: Emerging Markets | H7: Small Asia | I7: 0.7474 | J7: 0.8124 | K7: 0.0423 | L7: 0.0739 | M7: 0.023 | N7: 0.023 | O7: 0.0625 | P7: 0.0518 | Q7: 0.0718 | R7: -0.0547 | S7: -0.0684 | T7: 20394.1 | U7: 0 | V7: 2137 | W7: 2137 | X7: 22531.1 | Y7: 3280 | Z7: 19251.1 | AA7: 0.1456 | AB7: 2.5 | AC7: 0.247 | AD7: 0.0948 | AE7: 0.3281 | AF7: 0.1048 | AG7: 4.99 | AH7: 69.06 | AI7: -0.4885 | AJ7: 2.85 | AK7: 0.5206 | AL7: 0.3112 | AM7: 0.33 | AN7: 0.9 | AO7: NA | AP7: 167.16 | AQ7: NA | AR7: 61.6 | AS7: NA | AT7: 3.13 | AU7: 2.6 | AV7: 7.29 | AW7: 740.43 | AX7: 100.79 | AY7: 3.58 | AZ7: 6.88 | BA7: 0 | BB7: 0 | BC7: 0.2372 | BD7: NA | BE7: NA | BF7: 0.453 | BG7: NA | BH7: NA | BI7: 0.216 | BJ7: 0.0192 | BK7: 0.0034 | BL7: 0.85 | BM7: 0.0378 | BN7: 0.0081 | BO7: 0.4136 | BP7: 0.17 | BQ7: 0.5 | BR7: 0.4895 | BS7: -105 | BT7: 122 | BU7: 26 | BV7: 26 | BW7: 1335 | BX7: 2797 | BY7: 3228 | BZ7: -9 | CA7: 191 | CB7: 13 | CC7: -1405 | CD7: 4 | CE7: -2218 | CF7: -0.6871 | CG7: 193 | CH7: 15.1538 | CI7: -184 | CJ7: 1330 | CK7: -75 | CL7: 6359 | CM7: 3802 | CN7: 6514 | CO7: 5371 | CP7: 0 | CQ7: 1.35 | CR7: 0.89 | CS7: 0.42 | CT7: NA | CU7: NA | CV7: NA | CW7: NA | CX7: -311 | CY7: 116 | CZ7: 58 | DA7: 122 | DB7: 20394.1 | DC7: 191 | DD7: 19251.1 | DE7: 1330 | DF7: 1266.8 | DG7: 37.8 | DH7: 6637.8 | DI7: 421 | DJ7: 0.0175 | DK7: 0.0037 | DL7: 45.73 | DM7: 165 | DN7: NA | DO7: NA | DP7: NA | DQ7: $ 1,809.00 | DR7: 275.0 | DS7: 1,680.0 | DT7: #REF! | DU7: $ 27.00 | DV7: $ 26.00 | DW7: $ 29.00 | DX7: $ 206.00 | DY7: $ 1,170.00 | DZ7: 8 | EA7: -0.0299 | EB7: 0.125 | EC7: 0.1831 | ED7: -0.169 | EE7: 0.073 | EF7: 0.0508 | EG7: -0.013 | EH7: 0.008 | EI7: $ 1,809.00 | EJ7: 26 | EK7: -40 | EL7: $ 19,007.40 | EM7: $ 18,438.40 | EN7: $ 20,742.70 | EO7: $ 24,540.90 | EP7: $ - | EQ7: $ - | ER7: 1 | ES7: 0.4708 | ET7: 0.1433 | EU7: 3228 | EV7: $ 3,228.00 | EW7: 0 | EX7: 26748.8 | EY7: 12401.3 | EZ7: 13183.4 | FA7: 19007.4 | FB7: 16484.7 | FC7: 0 | FD7: 0 | FE7: 0 | FF7: 0
A8: TFI International Inc. (TSX:TFII) | B8: TSX:TFII | C8: Trucking | D8: Industrials | E8: 4210 | F8: Canada | G8: Australia, NZ and Canada | H8: Canada | I8: 0.6693 | J8: 0.8432 | K8: 0.0423 | L8: 0.0752 | M8: NA | N8: 0.0089 | O8: 0.0484 | P8: 0.0357 | Q8: 0.0649 | R8: 0.0437 | S8: 0.0496 | T8: 8514.3 | U8: 0 | V8: 2994.2 | W8: 2994.2 | X8: 11508.5 | Y8: 31.6 | Z8: 11476.9 | AA8: 0.0027 | AB8: 0.84 | AC8: 0.5316 | AD8: 0.2602 | AE8: 1.1348 | AF8: 0.3517 | AG8: 103.47 | AH8: 16.54 | AI8: 0.1199 | AJ8: 1.52 | AK8: 0.3521 | AL8: 0.3885 | AM8: 0.33 | AN8: 3.89 | AO8: 20.15 | AP8: 26.04 | AQ8: 16.17 | AR8: 22.16 | AS8: 2.48 | AT8: 3.23 | AU8: 2.56 | AV8: 1.01 | AW8: 19.7 | AX8: 11.36 | AY8: 3.17 | AZ8: 1.37 | BA8: 0.4511 | BB8: 0.0173 | BC8: 0.246 | BD8: -0.262 | BE8: 0.0583 | BF8: -0.0365 | BG8: 0.171 | BH8: 0.0814 | BI8: -0.018 | BJ8: 0.1188 | BK8: 0.1145 | BL8: 2.1 | BM8: 0.0406 | BN8: 0.0724 | BO8: 0.2017 | BP8: 0.2614 | BQ8: 0.2453 | BR8: 0.7035 | BS8: 422.5 | BT8: 327 | BU8: 582.5 | BV8: 582.5 | BW8: 1623 | BX8: 8396.8 | BY8: 8047.6 | BZ8: 1118.6 | CA8: 1010.7 | CB8: 439.6 | CC8: 329.6 | CD8: -92.04 | CE8: 239 | CF8: 0.0297 | CG8: -303.1 | CH8: -0.8989 | CI8: 834.74 | CJ8: 392.54 | CK8: 722.14 | CL8: 2751.9 | CM8: 3839.4 | CN8: 2638.6 | CO8: 3615.7 | CP8: -147.5 | CQ8: 1.14 | CR8: 1.32 | CS8: 0.79 | CT8: 0.6 | CU8: 0.67 | CV8: 456.95 | CW8: 391.77 | CX8: -415.5 | CY8: 433.3 | CZ8: 106.3 | DA8: 327 | DB8: 8514.3 | DC8: 1010.7 | DD8: 11476.9 | DE8: 392.54 | DF8: 0 | DG8: 582.5 | DH8: 3615.7 | DI8: 1118.6 | DJ8: 0.1188 | DK8: 0.1145 | DL8: 10.26 | DM8: 615.3 | DN8: 1365.1 | DO8: 456.95 | DP8: 0.1835 | DQ8: -175.2 | DR8: 808.0 | DS8: 478.4 | DT8: #REF! | DU8: $ 6.79 | DV8: $ 582.50 | DW8: $ 149.70 | DX8: $ 1.82 | DY8: $ 678.30 | DZ8: 63 | EA8: -0.4284 | EB8: 0.1524 | EC8: -0.03 | ED8: 0.1663 | EE8: -0.2548 | EF8: -0.0261 | EG8: 0.0763 | EH8: 0.072 | EI8: -175.2 | EJ8: 582.5 | EK8: 630.1 | EL8: $ 11,425.70 | EM8: $ 6,530.90 | EN8: $ 7,526.20 | EO8: $ 7,300.30 | EP8: $ 8,047.60 | EQ8: $ 8,514.30 | ER8: 1 | ES8: 0.1631 | ET8: 0.0319 | EU8: 8047.6 | EV8: $ 8,047.60 | EW8: 2371.1 | EX8: 10244.7 | EY8: 8735.2 | EZ8: 11566.7 | FA8: 11425.7 | FB8: 6833.2 | FC8: 0 | FD8: 0.554 | FE8: 275.1 | FF8: 1851.3
A9: Knight-Swift Transportation Holdings Inc. (NYSE:KNX) | B9: NYSE:KNX | C9: Trucking | D9: Industrials | E9: 4210 | F9: United States | G9: United States | H9: United States | I9: 0.6693 | J9: 0.864 | K9: 0.0446 | L9: 0.078 | M9: NA | N9: 0.0112 | O9: 0.0507 | P9: 0.038 | Q9: 0.0668 | R9: -0.0579 | S9: -0.0273 | T9: 8487.1 | U9: 391.36 | V9: 2899.8 | W9: 3291.16 | X9: 11778.26 | Y9: 192.7 | Z9: 11585.56 | AA9: 0.0164 | AB9: 4.68 | AC9: 0.3161 | AD9: 0.2794 | AE9: 0.4622 | AF9: 0.3878 | AG9: 52.28 | AH9: 31.61 | AI9: -0.0112 | AJ9: 1.01 | AK9: 0.5225 | AL9: 0.2526 | AM9: 0.25 | AN9: 1.56 | AO9: 72.17 | AP9: 59.68 | AQ9: 54.94 | AR9: 29.54 | AS9: 1.36 | AT9: 1.19 | AU9: 0.91 | AV9: 1.15 | AW9: 36.12 | AX9: 9.76 | AY9: 1.85 | AZ9: 1.56 | BA9: 0.8024 | BB9: 0.0134 | BC9: 0.3137 | BD9: -0.455 | BE9: -0.158 | BF9: -0.0011 | BG9: 0.102 | BH9: 0.529 | BI9: 0.0344 | BJ9: 0.0201 | BK9: 0.0395 | BL9: 1.2 | BM9: 0.019 | BN9: 0.0429 | BO9: 0.2434 | BP9: 0.25 | BQ9: 0.2304 | BR9: 0.9782 | BS9: 117.6 | BT9: 142.2 | BU9: 259.9 | BV9: 320.73 | BW9: 1819.7 | BX9: 7410.1 | BY9: 7477.6 | BZ9: 1027.1 | CA9: 1187.3 | CB9: 246.82 | CC9: 145.5 | CD9: 45.9 | CE9: 822.5 | CF9: 0.11 | CG9: 91.7 | CH9: 0.5575 | CI9: 109.22 | CJ9: -140.9 | CK9: 4.6 | CL9: 7058.7 | CM9: 6247.36 | CN9: 7121.1 | CO9: 6257.46 | CP9: -114.1 | CQ9: 1.1 | CR9: 1.17 | CS9: 1.12 | CT9: 0.68 | CU9: 0.66 | CV9: 443.98 | CW9: 396.13 | CX9: -114.1 | CY9: 184 | CZ9: 42.4 | DA9: 142.2 | DB9: 8487.1 | DC9: 1187.3 | DD9: 11585.56 | DE9: -140.9 | DF9: 0 | DG9: 320.73 | DH9: 6257.46 | DI9: 1027.1 | DJ9: 0.0201 | DK9: 0.0395 | DL9: 11.28 | DM9: 788.3 | DN9: 749.5 | DO9: 443.98 | DP9: 0.1267 | DQ9: -149.7 | DR9: 2,148.5 | DS9: 2,003.0 | DT9: #REF! | DU9: $ 5.57 | DV9: $ 259.90 | DW9: $ 167.10 | DX9: $ 12.50 | DY9: $ 251.60 | DZ9: 31 | EA9: -0.1796 | EB9: 0.0175 | EC9: -0.1053 | ED9: 0.3235 | EE9: -0.0116 | EF9: 0.0068 | EG9: 0.0352 | EH9: 0.043 | EI9: -149.7 | EJ9: 259.9 | EK9: 261.3 | EL9: $ 8,586.80 | EM9: $ 7,044.30 | EN9: $ 7,167.50 | EO9: $ 6,412.60 | EP9: $ - | EQ9: $ - | ER9: 1 | ES9: 0.0985 | ET9: 0.0352 | EU9: 7477.6 | EV9: $ 7,477.60 | EW9: 2645 | EX9: 10081.9 | EY9: 8422.1 | EZ9: 9302.9 | FA9: 8586.8 | FB9: 6460.6 | FC9: 0 | FD9: 0.0637 | FE9: 2159.5 | FF9: 0
A10: InPost S.A. (ENXTAM:INPST) | B10: ENXTAM:INPST | C10: Transportation | D10: Industrials | E10: 4210 | F10: Luxembourg | G10: Developed Europe | H10: EU & Environs | I10: 0.7474 | J10: 1.0014 | K10: 0.0423 | L10: 0.0819 | M10: NA | N10: 0.0089 | O10: 0.0484 | P10: 0.0363 | Q10: 0.0677 | R10: 0.3518 | S10: 0.1213 | T10: 6140.3 | U10: 0 | V10: 2779.5 | W10: 2779.5 | X10: 8919.8 | Y10: 388.5 | Z10: 8531.3 | AA10: 0.0436 | AB10: 0.39 | AC10: 0.7652 | AD10: 0.3116 | AE10: 3.2589 | AF10: 0.4527 | AG10: 12.29 | AH10: 50.04 | AI10: NA | AJ10: 1.71 | AK10: 0.3834 | AL10: 0.2695 | AM10: 0.32 | AN10: 2.94 | AO10: 20.35 | AP10: 24.97 | AQ10: 24.04 | AR10: 15.02 | AS10: 1.6 | AT10: 7.2 | AU10: 12.21 | AV10: 2.32 | AW10: 16.46 | AX10: 11.04 | AY10: 3.18 | AZ10: 3.23 | BA10: 0 | BB10: 0 | BC10: -0.1535 | BD10: 0.14 | BE10: 0.306 | BF10: 0.273 | BG10: 0.458 | BH10: 0.127 | BI10: 0.267 | BJ10: 0.4337 | BK10: 0.189 | BL10: 1.99 | BM10: 0.0658 | BN10: 0.1387 | BO10: 0.704 | BP10: 0.2494 | BQ10: 0.316 | BR10: 0.2504 | BS10: 301.8 | BT10: 245.9 | BU10: 518.3 | BV10: 518.3 | BW10: 2630.8 | BX10: 2642.1 | BY10: 3736.8 | BZ10: 581.5 | CA10: 772.7 | CB10: 354.5 | CC10: -26.2 | CD10: 43.25 | CE10: 91.72 | CF10: 0.0245 | CG10: 27.9 | CH10: 0.2007 | CI10: 283.35 | CJ10: 200.95 | CK10: 174.75 | CL10: 567 | CM10: 1876.1 | CN10: 852.9 | CO10: 2680.4 | CP10: 0 | CQ10: 0.86 | CR10: 1.1 | CS10: 0.55 | CT10: 1.16 | CU10: 0.9 | CV10: 142.32 | CW10: 39.68 | CX10: -51.7 | CY10: 354.4 | CZ10: 112 | DA10: 245.9 | DB10: 6140.3 | DC10: 772.7 | DD10: 8531.3 | DE10: 200.95 | DF10: 0.36 | DG10: 517.59 | DH10: 2680.76 | DI10: 581.5 | DJ10: 0.4322 | DK10: 0.1887 | DL10: 14.67 | DM10: 409.8 | DN10: 247.2 | DO10: 142.32 | DP10: 0.0972 | DQ10: $ 913.40 | DR10: 2,060.9 | DS10: 2,087.1 | DT10: #REF! | DU10: $ - | DV10: $ 518.30 | DW10: $ 176.30 | DX10: $ 4.12 | DY10: $ 590.60 | DZ10: 21 | EA10: -0.1502 | EB10: 0.1348 | EC10: -0.2569 | ED10: 0.0026 | EE10: -0.2814 | EF10: 0.0923 | EG10: 0.1531 | EH10: 0.139 | EI10: $ 913.40 | EJ10: 518.3 | EK10: 523.6 | EL10: $ 8,545.40 | EM10: $ 7,262.00 | EN10: $ 8,241.20 | EO10: $ 6,124.20 | EP10: $ - | EQ10: $ - | ER10: 1 | ES10: 0.409 | ET10: 0.0985 | EU10: 3736.8 | EV10: $ 3,736.80 | EW10: 0 | EX10: 5920.5 | EY10: 4206.7 | EZ10: 6911.7 | FA10: 8545.4 | FB10: 7253.9 | FC10: 0 | FD10: 0.337 | FE10: 0 | FF10: 0
A11: Schneider National, Inc. (NYSE:SNDR) | B11: NYSE:SNDR | C11: Trucking | D11: Industrials | E11: 4210 | F11: United States | G11: United States | H11: United States | I11: 0.6693 | J11: 0.7346 | K11: 0.0446 | L11: 0.0723 | M11: NA | N11: 0.0078 | O11: 0.0473 | P11: 0.0355 | Q11: 0.068 | R11: -0.0338 | S11: -0.0148 | T11: 4650.7 | U11: 82.37 | V11: 522.2 | W11: 604.57 | X11: 5255.27 | Y11: 194.1 | Z11: 5061.17 | AA11: 0.0369 | AB11: 1.26 | AC11: 0.1668 | AD11: 0.115 | AE11: 0.2001 | AF11: 0.13 | AG11: 26.53 | AH11: 31.61 | AI11: 0.0106 | AJ11: 0.71 | AK11: 0.3347 | AL11: 0.232 | AM11: 0.22 | AN11: 5.78 | AO11: 39.75 | AP11: 40.76 | AQ11: 33.45 | AR11: 28.37 | AS11: 1.09 | AT11: 1.54 | AU11: 1.31 | AV11: 0.88 | AW11: 25.86 | AX11: 8.1 | AY11: 1.64 | AZ11: 0.96 | BA11: 0.5872 | BB11: 0.0144 | BC11: 0.1884 | BD11: -0.381 | BE11: -0.0976 | BF11: -0.0534 | BG11: 0.0479 | BH11: 0.364 | BI11: 0.065 | BJ11: 0.0385 | BK11: 0.0532 | BL11: 2 | BM11: 0.0203 | BN11: 0.0349 | BO11: 0.1693 | BP11: 0.25 | BQ11: 0.2383 | BR11: 0.3227 | BS11: 117 | BT11: 114.1 | BU11: 177 | BV11: 195.73 | BW11: 950.4 | BX11: 5290.5 | BY11: 5613.8 | BZ11: 548.4 | CA11: 625 | CB11: 149.08 | CC11: -258.4 | CD11: 15.5 | CE11: 361.9 | CF11: 0.0645 | CG11: 484.8 | CH11: 3.3559 | CI11: -351.22 | CJ11: -127.8 | CK11: -386.2 | CL11: 2967.2 | CM11: 2802.57 | CN11: 3021 | CO11: 3092.57 | CP11: -67 | CQ11: 0.65 | CR11: 1.1 | CS11: 1.12 | CT11: 0.41 | CU11: 0.48 | CV11: 352.7 | CW11: 268.56 | CX11: -75.3 | CY11: 149.8 | CZ11: 35.7 | DA11: 114.1 | DB11: 4650.7 | DC11: 625 | DD11: 5061.17 | DE11: -127.8 | DF11: 0 | DG11: 195.73 | DH11: 3092.57 | DI11: 548.4 | DJ11: 0.0385 | DK11: 0.0532 | DL11: 9.23 | DM11: 445.3 | DN11: 1263.8 | DO11: 352.7 | DP11: 0.1619 | DQ11: $ 258.50 | DR11: 191.6 | DS11: 450.0 | DT11: #REF! | DU11: $ - | DV11: $ 177.00 | DW11: $ 30.60 | DX11: $ 6.00 | DY11: $ 228.30 | DZ11: 85 | EA11: -0.2183 | EB11: 0.0552 | EC11: -0.1235 | ED11: 0.254 | EE11: -0.0933 | EF11: 0.025 | EG11: 0.0337 | EH11: 0.035 | EI11: $ 258.50 | EJ11: 177 | EK11: 184.8 | EL11: $ 5,129.40 | EM11: $ 4,009.90 | EN11: $ 4,231.10 | EO11: $ 3,708.60 | EP11: $ - | EQ11: $ - | ER11: 1 | ES11: 0.0428 | ET11: NA | EU11: 5613.8 | EV11: NA | EW11: 0 | EX11: 4773.6 | EY11: 4165.5 | EZ11: 4490.6 | FA11: 5129.4 | FB11: 3913.4 | FC11: 0 | FD11: 0.237 | FE11: 467.5 | FF11: 0
A12: Yamato Holdings Co., Ltd. (TSE:9064) | B12: TSE:9064 | C12: Transportation | D12: Industrials | E12: 4210 | F12: Japan | G12: Japan | H12: Japan | I12: 0.7474 | J12: 1.0289 | K12: 0.0514 | L12: 0.0924 | M12: NA | N12: 0.0115 | O12: 0.051 | P12: 0.0358 | Q12: 0.0727 | R12: -0.0171 | S12: -0.0472 | T12: 4461.7 | U12: 1163.14 | V12: 1228.8 | W12: 2391.94 | X12: 6853.64 | Y12: 1105.3 | Z12: 5748.34 | AA12: 0.1613 | AB12: 1.07 | AC12: 0.3834 | AD12: 0.349 | AE12: 0.6219 | AF12: 0.5361 | AG12: 14.14 | AH12: 24.3 | AI12: -0.0781 | AJ12: 0.99 | AK12: 0.255 | AL12: 0.2245 | AM12: 0.19 | AN12: 12.27 | AO12: 17.61 | AP12: 14.93 | AQ12: 35.52 | AR12: 21.23 | AS12: 1.43 | AT12: 1.16 | AU12: 1.16 | AV12: 0.38 | AW12: 32.93 | AX12: 7.56 | AY12: 1.14 | AZ12: 0.49 | BA12: 0.3484 | BB12: 0.0233 | BC12: 0.009 | BD12: -0.0506 | BE12: 0.0204 | BF12: 0.0032 | BG12: 0.0226 | BH12: 0.123 | BI12: 0.0481 | BJ12: 0.0753 | BK12: 0.0254 | BL12: 2.63 | BM12: 0.0242 | BN12: 0.0141 | BO12: 0.0463 | BP12: 0.2974 | BQ12: 0.3141 | BR12: 0.542 | BS12: 253.3 | BT12: 298.8 | BU12: 171.8 | BV12: 174.57 | BW12: 572.4 | BX12: 11771.1 | BY12: 12359.4 | BZ12: 422.4 | CA12: 760.4 | CB12: 119.73 | CC12: -367.1 | CD12: 76.64 | CE12: 358.7 | CF12: 0.029 | CG12: 605.8 | CH12: 5.6997 | CI12: -562.71 | CJ12: -16.54 | CK12: -383.64 | CL12: 3969.3 | CM12: 4705.54 | CN12: 3846.4 | CO12: 5031.04 | CP12: -104.1 | CQ12: 0.48 | CR12: 0.31 | CS12: 0.43 | CT12: 0.55 | CU12: 0.52 | CV12: 463.57 | CW12: 307.09 | CX12: -442.1 | CY12: 439.3 | CZ12: 138 | DA12: 298.8 | DB12: 4461.7 | DC12: 760.4 | DD12: 5748.34 | DE12: -16.54 | DF12: 35.1 | DG12: 185.23 | DH12: 5066.14 | DI12: 441.5 | DJ12: 0.0773 | DK12: 0.0268 | DL12: 13.02 | DM12: 20.1 | DN12: 3826.8 | DO12: 463.57 | DP12: 0.1047 | DQ12: $ 508.20 | DR12: 14.4 | DS12: 381.5 | DT12: #REF! | DU12: $ - | DV12: $ 171.80 | DW12: $ 14.00 | DX12: $ 29.60 | DY12: $ 1,074.10 | DZ12: 101 | EA12: 0.1226 | EB12: -0.0183 | EC12: 0.1951 | ED12: -0.1187 | EE12: 0.1608 | EF12: -0.0063 | EG12: 0.0122 | EH12: 0.014 | EI12: $ 508.20 | EJ12: 171.8 | EK12: 151.3 | EL12: $ 3,843.60 | EM12: $ 4,314.90 | EN12: $ 4,236.10 | EO12: $ 5,062.70 | EP12: $ - | EQ12: $ - | ER12: 1 | ES12: -0.0522 | ET12: 0.0055 | EU12: 12359.4 | EV12: $ 12,359.40 | EW12: 8111.7 | EX12: 8710 | EY12: 5733.2 | EZ12: 6491.9 | FA12: 3843.6 | FB12: 4421.7 | FC12: 105.7 | FD12: 0.115 | FE12: 0 | FF12: 135.8
A13: Shenzhen Yan Tian Port Holdings Co.,Ltd. (SZSE:000088) | B13: SZSE:000088 | C13: Transportation | D13: Industrials | E13: 4210 | F13: China | G13: Emerging Markets | H13: China | I13: 0.7474 | J13: 0.8224 | K13: 0.0514 | L13: 0.0818 | M13: NA | N13: 0.0115 | O13: 0.051 | P13: 0.0383 | Q13: 0.0766 | R13: 0.0216 | S13: -0.0717 | T13: 3308 | U13: 0 | V13: 442.3 | W13: 442.3 | X13: 3750.3 | Y13: 431.1 | Z13: 3319.2 | AA13: 0.115 | AB13: 1.11 | AC13: 0.1379 | AD13: 0.1179 | AE13: 0.1599 | AF13: 0.1337 | AG13: 0.64 | AH13: 69.06 | AI13: -0.1526 | AJ13: 0.77 | AK13: 0.2191 | AL13: 0.1654 | AM13: 0.11 | AN13: 0.83 | AO13: 17.89 | AP13: 16.63 | AQ13: 18.3 | AR13: NA | AS13: NA | AT13: 1.2 | AU13: 1.27 | AV13: 30.43 | AW13: 325.41 | AX13: 78.28 | AY13: 1.2 | AZ13: 30.54 | BA13: 0.5455 | BB13: 0.0328 | BC13: -0.0224 | BD13: 0.425 | BE13: 0.283 | BF13: 0.0065 | BG13: 0.0897 | BH13: NA | BI13: NA | BJ13: 0.1034 | BK13: 0.0049 | BL13: 0.06 | BM13: 1.7775 | BN13: 0.0912 | BO13: 0.2815 | BP13: 0.25 | BQ13: 0.0464 | BR13: 0.1325 | BS13: 184.9 | BT13: 198.9 | BU13: 10.2 | BV13: 10.2 | BW13: 31.5 | BX13: 108.7 | BY13: 111.9 | BZ13: 34.6 | CA13: 42.4 | CB13: 9.73 | CC13: 228.5 | CD13: -0.75 | CE13: 357.95 | CF13: 3.1988 | CG13: 103.6 | CH13: 10.5743 | CI13: -93.13 | CJ13: -132.45 | CK13: 96.05 | CL13: 1923.5 | CM13: 1980.1 | CN13: 2765.9 | CO13: 2777.1 | CP13: -108.5 | CQ13: 0.3 | CR13: 0.36 | CS13: 0.42 | CT13: 0.52 | CU13: 0.38 | CV13: 11.55 | CW13: 72.67 | CX13: -108.5 | CY13: 214 | CZ13: 9.93 | DA13: 198.9 | DB13: 3308 | DC13: 42.4 | DD13: 3319.2 | DE13: -132.45 | DF13: 2.54 | DG13: 10.46 | DH13: 2779.64 | DI13: 35.48 | DJ13: 0.1034 | DK13: 0.005 | DL13: 93.56 | DM13: 32.2 | DN13: 856.14 | DO13: 11.55 | DP13: 0.0064 | DQ13: -238.6 | DR13: 280.6 | DS13: 52.1 | DT13: #REF! | DU13: $ 558.00 | DV13: $ 10.20 | DW13: $ 12.30 | DX13: $ 184.30 | DY13: $ 88.20 | DZ13: 23 | EA13: -0.0189 | EB13: -0.034 | EC13: -0.016 | ED13: 0.0224 | EE13: -0.0464 | EF13: 0.0342 | EG13: 0.05 | EH13: 0.091 | EI13: -238.6 | EJ13: 10.2 | EK13: 5.41 | EL13: $ 3,469.10 | EM13: $ 3,403.50 | EN13: $ 3,287.90 | EO13: $ 3,235.40 | EP13: $ - | EQ13: $ - | ER13: 1 | ES13: 0.0657 | ET13: NA | EU13: 111.9 | EV13: NA | EW13: 1994.4 | EX13: 1856.7 | EY13: 1653.3 | EZ13: 1547.9 | FA13: 3469.1 | FB13: 3383.7 | FC13: 0 | FD13: 0.06 | FE13: 358.8 | FF13: 0
A14: STO Express Co.,Ltd (SZSE:002468) | B14: SZSE:002468 | C14: Transportation | D14: Industrials | E14: 4210 | F14: China | G14: Emerging Markets | H14: China | I14: 0.7474 | J14: 1.0246 | K14: 0.0514 | L14: 0.0922 | M14: NA | N14: 0.0149 | O14: 0.0544 | P14: 0.0408 | Q14: 0.0752 | R14: 0.0275 | S14: 0.0114 | T14: 2899.6 | U14: 0 | V14: 1433.7 | W14: 1433.7 | X14: 4333.3 | Y14: 314.8 | Z14: 4018.5 | AA14: 0.0726 | AB14: 4.17 | AC14: 0.498 | AD14: 0.3309 | AE14: 0.9918 | AF14: 0.4944 | AG14: 1.92 | AH14: 69.06 | AI14: 0.0015 | AJ14: 0.52 | AK14: 0.0949 | AL14: 0.3656 | AM14: 0.35 | AN14: 6.23 | AO14: 20.35 | AP14: 18.05 | AQ14: 16.26 | AR14: 13.06 | AS14: NA | AT14: 2.01 | AU14: 1.72 | AV14: 0.45 | AW14: 16.79 | AX14: 9.36 | AY14: 1.65 | AZ14: 0.62 | BA14: 0.1638 | BB14: 0.0091 | BC14: 0.2515 | BD14: NA | BE14: 0.3 | BF14: 0.172 | BG14: 0.187 | BH14: NA | BI14: 0.143 | BJ14: 0.1197 | BK14: 0.0866 | BL14: 3.37 | BM14: 0.0219 | BN14: 0.0326 | BO14: 0.0588 | BP14: 0.25 | BQ14: 0.2112 | BR14: 0.0361 | BS14: 142.5 | BT14: 160.6 | BU14: 239.3 | BV14: 239.3 | BW14: 431.7 | BX14: 6462.4 | BY14: 7339.2 | BZ14: 384.5 | CA14: 429.2 | CB14: 188.75 | CC14: -91.6 | CD14: -51.05 | CE14: -27.1 | CF14: -0.0037 | CG14: 437.6 | CH14: 2.0479 | CI14: -197.79 | CJ14: -134.35 | CK14: -225.95 | CL14: 1341.8 | CM14: 2179.7 | CN14: 1445.5 | CO14: 2440 | CP14: -26.3 | CQ14: 0.29 | CR14: 0.07 | CS14: 0.42 | CT14: 0.71 | CU14: 0.96 | CV14: 162.63 | CW14: 108.95 | CX14: -30.53 | CY14: 203.1 | CZ14: 42.9 | DA14: 160.6 | DB14: 2899.6 | DC14: 429.2 | DD14: 4018.5 | DE14: -134.35 | DF14: 76.32 | DG14: 239.06 | DH14: 2516.32 | DI14: 410.2 | DJ14: 0.1131 | DK14: 0.0836 | DL14: 9.8 | DM14: 189.9 | DN14: 205.37 | DO14: 162.63 | DP14: 0.123 | DQ14: $ 234.00 | DR14: 716.8 | DS14: 808.4 | DT14: #REF! | DU14: $ - | DV14: $ 239.30 | DW14: $ 38.40 | DX14: $ 10.40 | DY14: $ 561.70 | DZ14: 27 | EA14: 0.1726 | EB14: -0.0831 | EC14: 0.685 | ED14: -0.2369 | EE14: 0.3825 | EF14: 0.0385 | EG14: 0.0306 | EH14: 0.033 | EI14: $ 234.00 | EJ14: 239.3 | EK14: 216.1 | EL14: $ 2,097.40 | EM14: $ 2,459.50 | EN14: $ 2,255.10 | EO14: $ 3,799.80 | EP14: $ - | EQ14: $ - | ER14: 1 | ES14: 0.1731 | ET14: 0.0458 | EU14: 7339.2 | EV14: $ 7,339.20 | EW14: 6662.6 | EX14: 2172.5 | EY14: 2263.4 | EZ14: 1660.2 | FA14: 2097.4 | FB14: 2316.9 | FC14: 672.7 | FD14: 0 | FE14: 0 | FF14: 0
A15: Yunda Holding Group Co., Ltd. (SZSE:002120) | B15: SZSE:002120 | C15: Transportation | D15: Industrials | E15: 4210 | F15: China | G15: Emerging Markets | H15: China | I15: 0.7474 | J15: 1.0189 | K15: 0.0514 | L15: 0.0919 | M15: NA | N15: 0.0149 | O15: 0.0544 | P15: 0.0408 | Q15: 0.0752 | R15: -0.0314 | S15: -0.0202 | T15: 2786.6 | U15: 0 | V15: 1349.4 | W15: 1349.4 | X15: 4136 | Y15: 623 | Z15: 3513 | AA15: 0.1506 | AB15: 3.15 | AC15: 0.316 | AD15: 0.3263 | AE15: 0.4619 | AF15: 0.4842 | AG15: 0.96 | AH15: 69.06 | AI15: -0.2781 | AJ15: 1.11 | AK15: 0.2214 | AL15: 0.2716 | AM15: 0.18 | AN15: 5.71 | AO15: 10.63 | AP15: 16.05 | AQ15: 10.32 | AR15: 10.59 | AS15: 2.59 | AT15: 0.95 | AU15: 0.96 | AV15: 0.42 | AW15: 13.04 | AX15: 7.45 | AY15: 0.96 | AZ15: 0.53 | BA15: 0.674 | BB15: 0.042 | BC15: 0.0298 | BD15: -0.0462 | BE15: -0.0631 | BF15: 0.0146 | BG15: 0.0874 | BH15: 0.0411 | BI15: 0.0841 | BJ15: 0.0605 | BK15: 0.055 | BL15: 1.86 | BM15: 0.0245 | BN15: 0.038 | BO15: 0.0719 | BP15: 0.25 | BQ15: 0.2209 | BR15: 0.582 | BS15: 262.2 | BT15: 173.6 | BU15: 269.5 | BV15: 269.5 | BW15: 510.1 | BX15: 6650.6 | BY15: 7097.3 | BZ15: 608.6 | CA15: 471.8 | CB15: 209.97 | CC15: 400.4 | CD15: -82.46 | CE15: 108.8 | CF15: 0.0153 | CG15: 435.1 | CH15: 1.6795 | CI15: -142.67 | CJ15: -579.44 | CK15: -179.04 | CL15: 2869.8 | CM15: 3820.1 | CN15: 2921.5 | CO15: 3647.9 | CP15: -117 | CQ15: 0.5 | CR15: 0.39 | CS15: 0.42 | CT15: 0.3 | CU15: 0.4 | CV15: 309.81 | CW15: 239.71 | CX15: -122.59 | CY15: 225.9 | CZ15: 49.9 | DA15: 173.6 | DB15: 2786.6 | DC15: 471.8 | DD15: 3513 | DE15: -579.44 | DF15: 108.48 | DG15: 270.76 | DH15: 3756.38 | DI15: 645.3 | DJ15: 0.0587 | DK15: 0.0537 | DL15: 5.44 | DM15: 202.3 | DN15: 89.13 | DO15: 309.81 | DP15: 0.1658 | DQ15: -375.3 | DR15: 1,017.8 | DS15: 617.4 | DT15: #REF! | DU15: $ - | DV15: $ 269.50 | DW15: $ 47.20 | DX15: $ 24.10 | DY15: $ 392.10 | DZ15: 24 | EA15: -0.079 | EB15: -0.015 | EC15: 0.1144 | ED15: -0.0754 | EE15: -0.0653 | EF15: 0.0144 | EG15: 0.0416 | EH15: 0.038 | EI15: -375.3 | EJ15: 269.5 | EK15: 291.2 | EL15: $ 2,981.20 | EM15: $ 2,745.70 | EN15: $ 2,704.60 | EO15: $ 3,014.00 | EP15: $ - | EQ15: $ - | ER15: 1 | ES15: 0.067 | ET15: 0.0235 | EU15: 7097.3 | EV15: $ 7,097.30 | EW15: 7357.8 | EX15: 9338.8 | EY15: 6050.9 | EZ15: 3050.1 | FA15: 2981.2 | FB15: 2706 | FC15: 317.4 | FD15: 0.709 | FE15: 0 | FF15: 0
A16: Deewin Tianxia Co., Ltd (SEHK:2418) | B16: SEHK:2418 | C16: Trucking | D16: Industrials | E16: 4210 | F16: China | G16: Emerging Markets | H16: China | I16: 0.6693 | J16: 0.7929 | K16: 0.0514 | L16: 0.0803 | M16: NA | N16: 0.0945 | O16: 0.134 | P16: 0.1005 | Q16: 0.0843 | R16: -0.0404 | S16: -0.0647 | T16: 2648.5 | U16: 0 | V16: 652.3 | W16: 652.3 | X16: 3300.8 | Y16: 90.9 | Z16: 3209.9 | AA16: 0.0275 | AB16: 0.15 | AC16: 0.5802 | AD16: 0.1976 | AE16: 1.382 | AF16: 0.2463 | AG16: 1.21 | AH16: 69.06 | AI16: NA | AJ16: 0.87 | AK16: 0.0447 | AL16: 1.0143 | AM16: 0.8 | AN16: 5.98 | AO16: 126.12 | AP16: 145.52 | AQ16: 23.83 | AR16: NA | AS16: NA | AT16: 5.61 | AU16: 1.09 | AV16: 7.36 | AW16: 126.87 | AX16: 111.07 | AY16: 3.11 | AZ16: 8.92 | BA16: 0.6813 | BB16: 0.0047 | BC16: 4.2917 | BD16: -0.2 | BE16: NA | BF16: -0.0275 | BG16: NA | BH16: NA | BI16: NA | BJ16: 0.0399 | BK16: 0.0196 | BL16: 0.34 | BM16: 0.0528 | BN16: 0.0734 | BO16: 0.1558 | BP16: 0.25 | BQ16: 0.216 | BR16: 0.1362 | BS16: 21 | BT16: 18.2 | BU16: 25.3 | BV16: 25.3 | BW16: 53.7 | BX16: 360 | BY16: 344.7 | BZ16: 31.3 | CA16: 28.9 | CB16: 19.83 | CC16: 68.9 | CD16: -172.44 | CE16: 21.3 | CF16: 0.0618 | CG16: 5.02 | CH16: -8.4409 | CI16: 187.25 | CJ16: 116.72 | CK16: 185.62 | CL16: 456.5 | CM16: 1013.7 | CN16: 472 | CO16: 1033.4 | CP16: -12.4 | CQ16: 0.38 | CR16: 0.34 | CS16: 0.42 | CT16: NA | CU16: NA | CV16: NA | CW16: NA | CX16: -12.4 | CY16: 23.7 | CZ16: 5.12 | DA16: 18.2 | DB16: 2648.5 | DC16: 28.9 | DD16: 3209.9 | DE16: 116.72 | DF16: 14.91 | DG16: 25.53 | DH16: 1048.31 | DI16: 36.46 | DJ16: 0.0391 | DK16: 0.0195 | DL16: 88.04 | DM16: 3.6 | DN16: NA | DO16: NA | DP16: NA | DQ16: -103 | DR16: 235.8 | DS16: 166.9 | DT16: #REF! | DU16: $ 1.12 | DV16: $ 25.30 | DW16: $ 4.23 | DX16: $ 1.75 | DY16: $ 96.70 | DZ16: 15 | EA16: 0.4657 | EB16: 0.0233 | EC16: 0.3363 | ED16: 2.734 | EE16: 6.4838 | EF16: -0.0185 | EG16: 0.0749 | EH16: 0.073 | EI16: -103 | EJ16: 25.3 | EK16: 26.3 | EL16: $ 353.90 | EM16: $ 518.70 | EN16: $ 530.80 | EO16: $ 709.30 | EP16: $ 344.70 | EQ16: $ 2,648.50 | ER16: 1 | ES16: -0.0715 | ET16: NA | EU16: 344.7 | EV16: NA | EW16: 0 | EX16: 0 | EY16: 275.3 | EZ16: 562.6 | FA16: 353.9 | FB16: 500.5 | FC16: 392.8 | FD16: 0.211 | FE16: 0 | FF16: 717.2
A17: NIKKON Holdings Co.,Ltd. (TSE:9072) | B17: TSE:9072 | C17: Trucking | D17: Industrials | E17: 4210 | F17: Japan | G17: Japan | H17: Japan | I17: 0.6693 | J17: 0.8283 | K17: 0.0514 | L17: 0.0821 | M17: NA | N17: 0.0115 | O17: 0.051 | P17: 0.0358 | Q17: 0.0704 | R17: -0.0137 | S17: -0.0211 | T17: 2577.5 | U17: 0 | V17: 871.4 | W17: 871.4 | X17: 3448.9 | Y17: 247.5 | Z17: 3201.4 | AA17: 0.0718 | AB17: 0.8 | AC17: 0.3434 | AD17: 0.2527 | AE17: 0.523 | AF17: 0.3381 | AG17: 21.79 | AH17: 24.3 | AI17: 0.243 | AJ17: 0.59 | AK17: 0.1643 | AL17: 0.1921 | AM17: 0.3 | AN17: 38.17 | AO17: 23.33 | AP17: 22.16 | AQ17: 23.14 | AR17: 21.92 | AS17: NA | AT17: 1.55 | AU17: 1.62 | AV17: 1.56 | AW17: 21.02 | AX17: 12.19 | AY17: 1.45 | AZ17: 1.93 | BA17: 0.3852 | BB17: 0.0174 | BC17: 0.0481 | BD17: 0.0422 | BE17: 0.0629 | BF17: 0.0777 | BG17: 0.0715 | BH17: NA | BI17: 0.0688 | BJ17: 0.0683 | BK17: 0.0492 | BL17: 0.84 | BM17: 0.0663 | BN17: 0.0869 | BO17: 0.1554 | BP17: 0.2974 | BQ17: 0.3247 | BR17: 0.1865 | BS17: 110.5 | BT17: 116.3 | BU17: 152.3 | BV17: 152.3 | BW17: 272.4 | BX17: 1655.4 | BY17: 1753.1 | BZ17: 254.3 | CA17: 262.7 | CB17: 102.86 | CC17: -225.4 | CD17: 7.75 | CE17: 117.92 | CF17: 0.0673 | CG17: 284.38 | CH17: 2.8402 | CI17: -189.27 | CJ17: 49.57 | CK17: -175.83 | CL17: 1701.9 | CM17: 2088.6 | CN17: 1666.3 | CO17: 2215.2 | CP17: -44.8 | CQ17: 0.26 | CR17: 0.23 | CS17: 0.43 | CT17: 0.11 | CU17: 0.11 | CV17: 162.87 | CW17: 126.41 | CX17: -104.8 | CY17: 172.8 | CZ17: 56.1 | DA17: 116.3 | DB17: 2577.5 | DC17: 262.7 | DD17: 3201.4 | DE17: 49.57 | DF17: 0 | DG17: 152.3 | DH17: 2215.2 | DI17: 254.3 | DJ17: 0.0683 | DK17: 0.0492 | DL17: 12.59 | DM17: 9.72 | DN17: 1493.3 | DO17: 162.87 | DP17: 0.0878 | DQ17: $ 155.60 | DR17: 341.6 | DS17: 567.0 | DT17: #REF! | DU17: $ - | DV17: $ 152.30 | DW17: $ 3.99 | DX17: $ 9.74 | DY17: $ 111.00 | DZ17: 70 | EA17: 0.3861 | EB17: 0.2372 | EC17: 0.0366 | ED17: -0.0752 | EE17: 0.6439 | EF17: -0.011 | EG17: 0.0904 | EH17: 0.087 | EI17: $ 155.60 | EJ17: 152.3 | EK17: 160.2 | EL17: $ 1,567.90 | EM17: $ 2,173.20 | EN17: $ 2,688.70 | EO17: $ 2,787.00 | EP17: $ - | EQ17: $ - | ER17: 1 | ES17: -0.0026 | ET17: 0.0152 | EU17: 1753.1 | EV17: $ 1,753.10 | EW17: 1413.6 | EX17: 1232.5 | EY17: 1144.6 | EZ17: 1386.6 | FA17: 1567.9 | FB17: 2459.3 | FC17: 21.2 | FD17: 0.586 | FE17: 0 | FF17: 337.9
A18: Österreichische Post AG (WBAG:POST) | B18: WBAG:POST | C18: Transportation | D18: Industrials | E18: 4210 | F18: Austria | G18: Developed Europe | H18: EU & Environs | I18: 0.7474 | J18: 0.9532 | K18: 0.0459 | L18: 0.0833 | M18: NA | N18: 0.0078 | O18: 0.0473 | P18: 0.0364 | Q18: 0.0709 | R18: 0.125 | S18: 0.0257 | T18: 2466.7 | U18: 0 | V18: 882.1 | W18: 882.1 | X18: 3348.8 | Y18: 68.5 | Z18: 3280.3 | AA18: 0.0205 | AB18: 0.14 | AC18: 0.5092 | AD18: 0.2634 | AE18: 1.0376 | AF18: 0.3576 | AG18: 36.58 | AH18: 50.04 | AI18: -0.0394 | AJ18: 0.66 | AK18: 0.2702 | AL18: 0.1213 | AM18: 0.08 | AN18: 5.8 | AO18: 17.27 | AP18: 15.85 | AQ18: 16.63 | AR18: 15.31 | AS18: NA | AT18: 2.9 | AU18: 3.01 | AV18: 0.76 | AW18: 16.84 | AX18: 9.21 | AY18: 2.06 | AZ18: 1.01 | BA18: 0.9312 | BB18: 0.0587 | BC18: 0.0384 | BD18: 0.0048 | BE18: 0.0269 | BF18: 0.0742 | BG18: 0.0834 | BH18: NA | BI18: 0.0154 | BJ18: 0.2082 | BK18: 0.0967 | BL18: 2.42 | BM18: 0.0427 | BN18: 0.0534 | BO18: 0.2031 | BP18: 0.23 | BQ18: 0.2527 | BR18: 0.1017 | BS18: 142.8 | BT18: 155.6 | BU18: 194.8 | BV18: 194.8 | BW18: 740.3 | BX18: 3242.7 | BY18: 3645.3 | BZ18: 322.6 | CA18: 356.1 | CB18: 145.58 | CC18: 111.5 | CD18: -51.82 | CE18: -323.8 | CF18: -0.0888 | CG18: -82.9 | CH18: -0.9254 | CI18: 280.3 | CJ18: 178.82 | CK18: 290.32 | CL18: 747.3 | CM18: 1506 | CN18: 850.1 | CO18: 1593.1 | CP18: -144.9 | CQ18: 0.27 | CR18: 0.54 | CS18: 0.55 | CT18: 0.15 | CU18: 0.22 | CV18: 206.56 | CW18: 151.63 | CX18: -144.9 | CY18: 215.3 | CZ18: 54.4 | DA18: 155.6 | DB18: 2466.7 | DC18: 356.1 | DD18: 3280.3 | DE18: 178.82 | DF18: 0 | DG18: 194.8 | DH18: 1593.1 | DI18: 322.6 | DJ18: 0.2082 | DK18: 0.0967 | DL18: 10.17 | DM18: 246 | DN18: 416.5 | DO18: 206.56 | DP18: 0.2056 | DQ18: -14.8 | DR18: 143.3 | DS18: 31.8 | DT18: #REF! | DU18: $ - | DV18: $ 194.80 | DW18: $ 33.60 | DX18: $ 19.40 | DY18: $ 609.10 | DZ18: 21 | EA18: 0.1328 | EB18: 0.0518 | EC18: -0.0224 | ED18: 0.0514 | EE18: 0.2247 | EF18: -0.0036 | EG18: 0.0521 | EH18: 0.053 | EI18: -14.8 | EJ18: 194.8 | EK18: 190.6 | EL18: $ 2,014.20 | EM18: $ 2,281.70 | EN18: $ 2,399.80 | EO18: $ 2,346.10 | EP18: $ 3,645.30 | EQ18: $ 2,466.70 | ER18: 1 | ES18: 0.0624 | ET18: NA | EU18: 3645.3 | EV18: NA | EW18: 2274 | EX18: 2891.2 | EY18: 2122.5 | EZ18: 2441.7 | FA18: 2014.2 | FB18: 2375.4 | FC18: 0 | FD18: 0 | FE18: 0 | FF18: 0
A19: Seino Holdings Co., Ltd. (TSE:9076) | B19: TSE:9076 | C19: Trucking | D19: Industrials | E19: 4210 | F19: Japan | G19: Japan | H19: Japan | I19: 0.6693 | J19: 0.8623 | K19: 0.0514 | L19: 0.0838 | M19: NA | N19: 0.0171 | O19: 0.0566 | P19: 0.0398 | Q19: 0.071 | R19: -0.0302 | S19: -0.0136 | T19: 2243.3 | U19: 156.25 | V19: 764.4 | W19: 920.65 | X19: 3163.95 | Y19: 482.4 | Z19: 2681.55 | AA19: 0.1525 | AB19: 0.81 | AC19: 0.2402 | AD19: 0.291 | AE19: 0.3161 | AF19: 0.4104 | AG19: 15.08 | AH19: 24.3 | AI19: 0.0984 | AJ19: 0.06 | AK19: 0.0632 | AL19: NA | AM19: 0.07 | AN19: 33.23 | AO19: 17.44 | AP19: 14.08 | AQ19: 23.8 | AR19: 14.78 | AS19: NA | AT19: 0.77 | AU19: 0.82 | AV19: 0.46 | AW19: 10.67 | AX19: 5.67 | AY19: 0.81 | AZ19: 0.54 | BA19: 0.6792 | BB19: 0.0482 | BC19: -0.0499 | BD19: 0.0842 | BE19: 0.165 | BF19: 0.0912 | BG19: 0.0633 | BH19: NA | BI19: 0.0615 | BJ19: 0.0537 | BK19: 0.0574 | BL19: 1.92 | BM19: 0.0293 | BN19: 0.0462 | BO19: 0.1186 | BP19: 0.2974 | BQ19: 0.3539 | BR19: 0.5277 | BS19: 128.6 | BT19: 159.3 | BU19: 235.9 | BV19: 251.25 | BW19: 644.4 | BX19: 4924.1 | BY19: 5435.1 | BZ19: 375.1 | CA19: 472.7 | CB19: 162.33 | CC19: -197.8 | CD19: -17.13 | CE19: 508.1 | CF19: 0.0935 | CG19: 492.9 | CH19: 2.931 | CI19: -313.44 | CJ19: -118.67 | CK19: -316.47 | CL19: 2969.1 | CM19: 2827.15 | CN19: 2912.1 | CO19: 3298.55 | CP19: -108.2 | CQ19: -0.07 | CR19: 0.22 | CS19: 0.43 | CT19: 0.16 | CU19: 0.3 | CV19: 230.73 | CW19: 166.51 | CX19: -383.5 | CY19: 268.7 | CZ19: 95.1 | DA19: 159.3 | DB19: 2243.3 | DC19: 472.7 | DD19: 2681.55 | DE19: -118.67 | DF19: 0 | DG19: 251.25 | DH19: 3298.55 | DI19: 375.1 | DJ19: 0.0537 | DK19: 0.0574 | DL19: 7.15 | DM19: 33.4 | DN19: 2502.66 | DO19: 230.73 | DP19: 0.0795 | DQ19: $ 178.70 | DR19: 23.7 | DS19: 221.5 | DT19: #REF! | DU19: $ 4.37 | DV19: $ 235.90 | DW19: $ 7.10 | DX19: $ 8.72 | DY19: $ 359.40 | DZ19: 90 | EA19: -0.0972 | EB19: -0.0025 | EC19: -0.0401 | ED19: 0.0212 | EE19: -0.1173 | EF19: 0.0153 | EG19: 0.0421 | EH19: 0.046 | EI19: $ 178.70 | EJ19: 235.9 | EK19: 225.6 | EL19: $ 2,541.30 | EM19: $ 2,294.20 | EN19: $ 2,288.50 | EO19: $ 2,196.80 | EP19: $ - | EQ19: $ - | ER19: 1 | ES19: -0.0107 | ET19: 0.0012 | EU19: 5435.1 | EV19: $ 5,435.10 | EW19: 2192.8 | EX19: 1846.9 | EY19: 1611.3 | EZ19: 2741.7 | FA19: 2541.3 | FB19: 2361 | FC19: 551.3 | FD19: 0.217 | FE19: 0 | FF19: 0
A20: Kodiak AI, Inc. (NasdaqGM:KDK) | B20: NasdaqGM:KDK | C20: Auto Parts | D20: Consumer Discretionary | E20: 4210 | F20: United States | G20: United States | H20: United States | I20: 1.3505 | J20: 1.3728 | K20: 0.0446 | L20: 0.1007 | M20: NA | N20: 0.0134 | O20: 0.0529 | P20: 0.0397 | Q20: 0.0994 | R20: NA | S20: -1.0994 | T20: 1910.5 | U20: 8.3 | V20: 33.7 | W20: 42 | X20: 1952.5 | Y20: 146.2 | Z20: 1806.3 | AA20: 0.0749 | AB20: 1.01 | AC20: 0.9194 | AD20: 0.0215 | AE20: 11.4126 | AF20: 0.022 | AG20: 10.92 | AH20: 31.61 | AI20: NA | AJ20: -0.09 | AK20: 0.0447 | AL20: NA | AM20: 0.36 | AN20: NA | AO20: NA | AP20: NA | AQ20: NA | AR20: NA | AS20: NA | AT20: 519.16 | AU20: NA | AV20: 128.22 | AW20: NA | AX20: NA | AY20: NA | AZ20: 121.23 | BA20: NA | BB20: 0 | BC20: 1.734 | BD20: NA | BE20: NA | BF20: NA | BG20: NA | BH20: NA | BI20: NA | BJ20: NA | BK20: -1 | BL20: 1.99 | BM20: -31.8909 | BN20: -4.9957 | BO20: 1 | BP20: 0.25 | BQ20: 0 | BR20: 0.1829 | BS20: -69.5 | BT20: -526.2 | BU20: -83.4 | BV20: -82.43 | BW20: 16.5 | BX20: 14.9 | BY20: 16.5 | BZ20: -57.1 | CA20: -77.67 | CB20: -82.43 | CC20: -31.6 | CD20: 1.4 | CE20: -5.52 | CF20: -0.3348 | CG20: 14.3 | CH20: NA | CI20: -98.13 | CJ20: -510.3 | CK20: -541.9 | CL20: 0 | CM20: 8.3 | CN20: 3.68 | CO20: 0 | CP20: 0 | CQ20: -0.14 | CR20: -0.04 | CS20: 1.12 | CT20: NA | CU20: NA | CV20: NA | CW20: NA | CX20: 0 | CY20: NA | CZ20: NA | DA20: NA | DB20: NA | DC20: NA | DD20: NA | DE20: NA | DF20: 139.2 | DG20: -67.33 | DH20: 139.2 | DI20: -7.2 | DJ20: NA | DK20: -0.4565 | DL20: NA | DM20: 3.1 | DN20: NA | DO20: NA | DP20: NA | DQ20: $ 39.60 | DR20: 12.3 | DS20: 43.9 | DT20: #REF! | DU20: $ 26.10 | DV20: -83.4 | DW20: $ 7.11 | DX20: $ 0.30 | DY20: $ 3.28 | DZ20: 2 | EA20: 0.0154 | EB20: 0.0057 | EC20: 0.7074 | ED20: 0.5965 | EE20: 1.7838 | EF20: 0.0248 | EG20: -4.4472 | EH20: -4.996 | EI20: $ 39.69 | EJ20: -83.4 | EK20: -71.6 | EL20: $ 686.30 | EM20: $ 696.90 | EN20: $ 700.90 | EO20: $ 1,196.70 | EP20: $ - | EQ20: $ - | ER20: 0 | ES20: NA | ET20: 0.7284 | EU20: NA | EV20: $ 16.50 | EW20: 0 | EX20: 0 | EY20: 0 | EZ20: 652.5 | FA20: 686.3 | FB20: 698.8 | FC20: 0 | FD20: 0 | FE20: 0 | FF20: 0
A21: ANE (Cayman) Inc. (SEHK:9956) | B21: SEHK:9956 | C21: Trucking | D21: Industrials | E21: 4210 | F21: Hong Kong | G21: Emerging Markets | H21: China | I21: 0.6693 | J21: 0.8467 | K21: 0.0501 | L21: 0.0819 | M21: NA | N21: 0.0162 | O21: 0.0557 | P21: 0.0465 | Q21: 0.0734 | R21: 0.1873 | S21: 0.0746 | T21: 1683 | U21: 0 | V21: 534.3 | W21: 534.3 | X21: 2217.3 | Y21: 304.1 | Z21: 1913.2 | AA21: 0.1371 | AB21: 0.78 | AC21: 0.5001 | AD21: 0.241 | AE21: 1.0006 | AF21: 0.3175 | AG21: 1.52 | AH21: 69.06 | AI21: NA | AJ21: 0.85 | AK21: 0.0316 | AL21: NA | AM21: 0.29 | AN21: 21.23 | AO21: 16.39 | AP21: 15.47 | AQ21: 11.57 | AR21: 12.56 | AS21: NA | AT21: 3.15 | AU21: 2.36 | AV21: 1.06 | AW21: 13.06 | AX21: 9.54 | AY21: 2.56 | AZ21: 1.21 | BA21: 0.2169 | BB21: 0.014 | BC21: 0.4169 | BD21: 0.182 | BE21: NA | BF21: 0.0875 | BG21: NA | BH21: NA | BI21: 0.0911 | BJ21: 0.2692 | BK21: 0.148 | BL21: 2.27 | BM21: 0.0654 | BN21: 0.0881 | BO21: 0.1547 | BP21: 0.165 | BQ21: 0.2615 | BR21: 0.0507 | BS21: 102.7 | BT21: 108.8 | BU21: 146.5 | BV21: 146.5 | BW21: 257.3 | BX21: 1585.9 | BY21: 1662.8 | BZ21: 194.9 | CA21: 200.6 | CB21: 108.19 | CC21: 94.36 | CD21: 1.38 | CE21: -146.48 | CF21: -0.0881 | CG21: 18.35 | CH21: 0.1824 | CI21: 88.46 | CJ21: -5.29 | CK21: 89.07 | CL21: 404.1 | CM21: 731.2 | CN21: 534 | CO21: 748.3 | CP21: -23.6 | CQ21: -0.11 | CR21: 1.31 | CS21: 0.42 | CT21: NA | CU21: NA | CV21: NA | CW21: NA | CX21: -37.4 | CY21: 148 | CZ21: 38.7 | DA21: 108.8 | DB21: 1683 | DC21: 200.6 | DD21: 1913.2 | DE21: -5.29 | DF21: 0 | DG21: 146.5 | DH21: 748.3 | DI21: 194.9 | DJ21: 0.2692 | DK21: 0.148 | DL21: 9.82 | DM21: 4.65 | DN21: NA | DO21: NA | DP21: NA | DQ21: -16.6 | DR21: 94.5 | DS21: 0.1 | DT21: #REF! | DU21: $ 0.90 | DV21: $ 146.50 | DW21: $ 6.90 | DX21: $ 1.42 | DY21: $ 43.60 | DZ21: 10 | EA21: 0.064 | EB21: 0.4422 | EC21: -0.0438 | ED21: 0.0904 | EE21: 0.6 | EF21: 4.7636 | EG21: 0.7071 | EH21: 0.088 | EI21: -3.7 | EJ21: 146.5 | EK21: 204 | EL21: $ 1,051.90 | EM21: $ 1,119.20 | EN21: $ 1,614.10 | EO21: $ 1,543.40 | EP21: $ 1,662.80 | EQ21: $ 1,683.00 | ER21: 1 | ES21: 0.592 | ET21: NA | EU21: 1662.8 | EV21: NA | EW21: 720.8 | EX21: 610.3 | EY21: 742.8 | EZ21: 930.6 | FA21: 1051.9 | FB21: 1187.8 | FC21: 0 | FD21: 0 | FE21: 0 | FF21: 91.5
A22: Blue Dart Express Limited (BSE:526612) | B22: BSE:526612 | C22: Transportation | D22: Industrials | E22: 4210 | F22: India | G22: Emerging Markets | H22: India | I22: 0.7474 | J22: 0.7911 | K22: 0.0708 | L22: 0.0955 | M22: NA | N22: 0.0276 | O22: 0.0671 | P22: 0.047 | Q22: 0.0918 | R22: 0.0809 | S22: 0.0274 | T22: 1458 | U22: 0 | V22: 121.6 | W22: 121.6 | X22: 1579.6 | Y22: 15.7 | Z22: 1563.9 | AA22: 0.0099 | AB22: 0.05 | AC22: 0.3984 | AD22: 0.077 | AE22: 0.6623 | AF22: 0.0834 | AG22: 63.17 | AH22: 69.06 | AI22: -0.0411 | AJ22: 0.99 | AK22: 0.2627 | AL22: 0.2604 | AM22: 0.16 | AN22: 5.14 | AO22: 49.42 | AP22: 48.6 | AQ22: 54.03 | AR22: 37.6 | AS22: 3.95 | AT22: 7.94 | AU22: 10.42 | AV22: 2.18 | AW22: 33.42 | AX22: 21.57 | AY22: 5.4 | AZ22: 2.33 | BA22: 0.2227 | BB22: 0.0046 | BC22: -0.1594 | BD22: -0.174 | BE22: NA | BF22: 0.0553 | BG22: 0.156 | BH22: 0.125 | BI22: 0.11 | BJ22: 0.1764 | BK22: 0.1192 | BL22: 2.33 | BM22: 0.045 | BN22: 0.0702 | BO22: 0.2251 | BP22: 0.3 | BQ22: 0.2725 | BR22: 0.16 | BS22: 29.5 | BT22: 30 | BU22: 46.8 | BV22: 46.8 | BW22: 150.1 | BX22: 669.9 | BY22: 666.9 | BZ22: 72.2 | CA22: 72.5 | CB22: 34.05 | CC22: 33.5 | CD22: 18.02 | CE22: 14.13 | CF22: 0.0212 | CG22: -26.2 | CH22: -0.2402 | CI22: 42.22 | CJ22: 4.68 | CK22: 38.18 | CL22: 170.1 | CM22: 285.7 | CN22: 183.6 | CO22: 289.5 | CP22: -6.68 | CQ22: 0.57 | CR22: 0.11 | CS22: 0.42 | CT22: NA | CU22: NA | CV22: NA | CW22: NA | CX22: -6.68 | CY22: 41.1 | CZ22: 11.2 | DA22: 30 | DB22: 1458 | DC22: 72.5 | DD22: 1563.9 | DE22: 4.68 | DF22: 0 | DG22: 46.8 | DH22: 289.5 | DI22: 72.2 | DJ22: 0.1764 | DK22: 0.1192 | DL22: 21.66 | DM22: 56 | DN22: 75.6 | DO22: NA | DP22: NA | DQ22: -9.3 | DR22: 33.5 | DS22: 0 | DT22: #REF! | DU22: $ - | DV22: $ 46.80 | DW22: $ 9.11 | DX22: $ 0.85 | DY22: $ 79.10 | DZ22: 37 | EA22: -0.1175 | EB22: 0.0368 | EC22: -0.1399 | ED22: -0.0417 | EE22: -0.2458 | EF22: -0.0178 | EG22: 0.0673 | EH22: 0.07 | EI22: -9.3 | EJ22: 46.8 | EK22: 45.7 | EL22: $ 1,933.10 | EM22: $ 1,706.00 | EN22: $ 1,768.80 | EO22: $ 1,521.40 | EP22: $ - | EQ22: $ - | ER22: 1 | ES22: 0.0982 | ET22: 0.0469 | EU22: 666.9 | EV22: $ 666.90 | EW22: 1508.6 | EX22: 2008.6 | EY22: 2216.5 | EZ22: 2094.8 | FA22: 1933.1 | FB22: 1734.5 | FC22: 0 | FD22: 0.0005 | FE22: 0 | FF22: 0
A23: Hangzhou SF Intra-city Industrial Co., Ltd. (SEHK:9699) | B23: SEHK:9699 | C23: Transportation | D23: Industrials | E23: 4210 | F23: China | G23: Emerging Markets | H23: China | I23: 0.7474 | J23: 0.7481 | K23: 0.0514 | L23: 0.078 | M23: NA | N23: 0.0149 | O23: 0.0544 | P23: 0.0408 | Q23: 0.0779 | R23: -0.0057 | S23: 0.0273 | T23: 1292.1 | U23: 0 | V23: 1.65 | W23: 1.65 | X23: 1293.75 | Y23: 158.5 | Z23: 1135.25 | AA23: 0.1225 | AB23: 0.99 | AC23: 0.0038 | AD23: 0.0013 | AE23: 0.0038 | AF23: 0.0013 | AG23: 1.41 | AH23: 69.06 | AI23: NA | AJ23: 1.8 | AK23: 0.1049 | AL23: 0.3833 | AM23: 0.44 | AN23: 226.73 | AO23: 71.39 | AP23: 44.71 | AQ23: 52.87 | AR23: 21.36 | AS23: NA | AT23: 2.97 | AU23: 2.36 | AV23: 0.6 | AW23: 49.57 | AX23: 47.7 | AY23: 4.09 | AZ23: 0.53 | BA23: 0 | BB23: 0 | BC23: 0.3502 | BD23: NA | BE23: NA | BF23: 0.289 | BG23: NA | BH23: NA | BI23: 0.338 | BJ23: 0.0723 | BK23: 0.1052 | BL23: 13.13 | BM23: 0.0108 | BN23: 0.0086 | BO23: 0.0669 | BP23: 0.25 | BQ23: 0.0671 | BR23: 0.0388 | BS23: 18.1 | BT23: 28.9 | BU23: 22.9 | BV23: 22.9 | BW23: 178.5 | BX23: 2157.3 | BY23: 2666.7 | BZ23: 14 | CA23: 23.8 | CB23: 21.36 | CC23: 2.13 | CD23: -9.81 | CE23: 77.19 | CF23: 0.0289 | CG23: 4.53 | CH23: -0.247 | CI23: 26.64 | CJ23: 32.05 | CK23: 34.18 | CL23: 399.9 | CM23: 203.09 | CN23: 434.4 | CO23: 277.55 | CP23: 0 | CQ23: 0.34 | CR23: 1.61 | CS23: 0.42 | CT23: NA | CU23: NA | CV23: NA | CW23: NA | CX23: -2.21 | CY23: 31 | CZ23: 2.08 | DA23: 28.9 | DB23: 1292.1 | DC23: 23.8 | DD23: 1135.25 | DE23: 32.05 | DF23: 48.24 | DG23: 25.82 | DH23: 325.79 | DI23: 31.6 | DJ23: 0.071 | DK23: 0.0958 | DL23: 35.93 | DM23: 0.9 | DN23: NA | DO23: NA | DP23: NA | DQ23: -1.54 | DR23: 2.1 | DS23: 0 | DT23: #REF! | DU23: $ - | DV23: $ 22.90 | DW23: $ 0.10 | DX23: $ 2.68 | DY23: $ 176.00 | DZ23: 4 | EA23: -0.0339 | EB23: 1.0881 | EC23: -0.2867 | ED23: -0.1788 | EE23: 0.1816 | EF23: 0.1105 | EG23: 0.0075 | EH23: 0.009 | EI23: -1.54 | EJ23: 22.9 | EK23: 17.9 | EL23: $ 1,093.50 | EM23: $ 1,056.40 | EN23: $ 2,205.90 | EO23: $ 1,573.40 | EP23: $ 2,666.70 | EQ23: $ 1,292.10 | ER23: 1 | ES23: 0.2916 | ET23: NA | EU23: 2666.7 | EV23: NA | EW23: 0 | EX23: 1802.5 | EY23: 897.9 | EZ23: 1234.6 | FA23: 1093.5 | FB23: 957 | FC23: 0 | FD23: 0 | FE23: 0 | FF23: 0
A24: CTT - Correios De Portugal, S.A. (ENXTLS:CTT) | B24: ENXTLS:CTT | C24: Transportation | D24: Industrials | E24: 4210 | F24: Portugal | G24: Developed Europe | H24: EU & Environs | I24: 0.7474 | J24: 1.0358 | K24: 0.0578 | L24: 0.0994 | M24: NA | N24: 0.0191 | O24: 0.0586 | P24: 0.0401 | Q24: 0.078 | R24: 0.1208 | S24: 0.1985 | T24: 1157 | U24: 0 | V24: 651.8 | W24: 651.8 | X24: 1808.8 | Y24: 330.4 | Z24: 1478.4 | AA24: 0.1827 | AB24: 0.67 | AC24: 0.6417 | AD24: 0.3603 | AE24: 1.7912 | AF24: 0.5634 | AG24: 8.72 | AH24: 50.04 | AI24: 0.1621 | AJ24: 1.15 | AK24: 0.2214 | AL24: 0.2635 | AM24: 0.22 | AN24: 1.78 | AO24: 24.56 | AP24: 19.48 | AQ24: 21.53 | AR24: 13.6 | AS24: 1.73 | AT24: 3.18 | AU24: 3.18 | AV24: 0.95 | AW24: 8.7 | AX24: 7.6 | AY24: 3.01 | AZ24: 1.21 | BA24: 0.5 | BB24: 0.0257 | BC24: 0.1409 | BD24: 0.0781 | BE24: 0.365 | BF24: 0.128 | BG24: 0.12 | BH24: 0.142 | BI24: 0.145 | BJ24: 0.2202 | BK24: 0.2765 | BL24: 2.86 | BM24: 0.0395 | BN24: 0.1129 | BO24: 0.6444 | BP24: 0.315 | BQ24: 0.1442 | BR24: 0.1444 | BS24: 47.1 | BT24: 59.4 | BU24: 169.9 | BV24: 169.9 | BW24: 970.2 | BX24: 1218.6 | BY24: 1505.5 | BZ24: 180.5 | CA24: 194.5 | CB24: 145.4 | CC24: 21.3 | CD24: 0 | CE24: -5111.93 | CF24: -3.3955 | CG24: -71 | CH24: -0.4883 | CI24: 216.4 | CJ24: 109.1 | CK24: 130.4 | CL24: 269.8 | CM24: 525.9 | CN24: 363.9 | CO24: 490.5 | CP24: -29.7 | CQ24: 0.49 | CR24: 0.92 | CS24: 0.55 | CT24: 0.45 | CU24: 0.46 | CV24: 81.4 | CW24: 44.88 | CX24: -54 | CY24: 74.2 | CZ24: 10.7 | DA24: 59.4 | DB24: 1157 | DC24: 194.5 | DD24: 1478.4 | DE24: 109.1 | DF24: 0 | DG24: 169.9 | DH24: 490.5 | DI24: 180.5 | DJ24: 0.2202 | DK24: 0.2765 | DL24: 8.19 | DM24: 94.7 | DN24: -507.48 | DO24: 81.4 | DP24: -9.5878 | DQ24: $ 72.30 | DR24: 409.1 | DS24: 387.8 | DT24: #REF! | DU24: $ 29.30 | DV24: $ 169.90 | DW24: $ 95.30 | DX24: $ 1.07 | DY24: $ 338.60 | DZ24: 500 | EA24: 0.4301 | EB24: 0.0458 | EC24: -0.009 | ED24: 0.0255 | EE24: 0.52 | EF24: 0.0361 | EG24: 0.1149 | EH24: 0.113 | EI24: $ 72.30 | EJ24: 169.9 | EK24: 167 | EL24: $ 761.20 | EM24: $ 1,088.60 | EN24: $ 1,138.50 | EO24: $ 1,128.20 | EP24: $ 1,505.50 | EQ24: $ 1,157.00 | ER24: 1 | ES24: 0.1075 | ET24: 0.0544 | EU24: 1505.5 | EV24: $ 1,505.50 | EW24: 1016.4 | EX24: 766.7 | EY24: 468.8 | EZ24: 544.6 | FA24: 761.2 | FB24: 1014.1 | FC24: 0 | FD24: 0.521 | FE24: 236.5 | FF24: 0
A25: Mullen Group Ltd. (TSX:MTL) | B25: TSX:MTL | C25: Trucking | D25: Industrials | E25: 4210 | F25: Canada | G25: Australia, NZ and Canada | H25: Canada | I25: 0.6693 | J25: 1.0529 | K25: 0.0423 | L25: 0.084 | M25: NA | N25: 0.0055 | O25: 0.045 | P25: 0.0332 | Q25: 0.0618 | R25: 0.0071 | S25: 0.0266 | T25: 1097.7 | U25: 0 | V25: 851.8 | W25: 851.8 | X25: 1949.5 | Y25: 108.5 | Z25: 1841 | AA25: 0.0557 | AB25: 0.57 | AC25: 0.5356 | AD25: 0.4369 | AE25: 1.1534 | AF25: 0.776 | AG25: 11.48 | AH25: 16.54 | AI25: 0.0455 | AJ25: 0.99 | AK25: 0.3937 | AL25: 0.2176 | AM25: 0.16 | AN25: 3.35 | AO25: 14.07 | AP25: 16.05 | AQ25: 9.99 | AR25: 13.88 | AS25: NA | AT25: 1.49 | AU25: 1.1 | AV25: 0.79 | AW25: 13.48 | AX25: 9.03 | AY25: 1.59 | AZ25: 1.33 | BA25: 0.7705 | BB25: 0.048 | BC25: 0.4084 | BD25: -0.067 | BE25: 0.0889 | BF25: 0.0268 | BG25: 0.122 | BH25: NA | BI25: 0.0636 | BJ25: 0.0911 | BK25: 0.0884 | BL25: 1.33 | BM25: 0.0454 | BN25: 0.0907 | BO25: 0.301 | BP25: 0.2614 | BQ25: 0.2692 | BR25: 0.2324 | BS25: 78 | BT25: 68.4 | BU25: 136.6 | BV25: 136.6 | BW25: 453.6 | BX25: 1382.5 | BY25: 1506.8 | BZ25: 205.4 | CA25: 203.8 | CB25: 99.82 | CC25: 80.5 | CD25: 0 | CE25: 62.83 | CF25: 0.0417 | CG25: 111.7 | CH25: 1.119 | CI25: -11.88 | CJ25: -123.8 | CK25: -43.3 | CL25: 750.9 | CM25: 1129.2 | CN25: 738.5 | CO25: 1159.8 | CP25: -52.7 | CQ25: 0.71 | CR25: 0.92 | CS25: 0.79 | CT25: 0.39 | CU25: 0.75 | CV25: 100.44 | CW25: 50.25 | CX25: -60.21 | CY25: 93.6 | CZ25: 25.2 | DA25: 68.4 | DB25: 1097.7 | DC25: 203.8 | DD25: 1841 | DE25: -123.8 | DF25: 0 | DG25: 136.6 | DH25: 1159.8 | DI25: 205.4 | DJ25: 0.0911 | DK25: 0.0884 | DL25: 8.96 | DM25: 102.8 | DN25: 883.2 | DO25: 100.44 | DP25: 0.0983 | DQ25: -54.5 | DR25: 361.2 | DS25: 280.7 | DT25: #REF! | DU25: $ 0.71 | DV25: $ 136.60 | DW25: $ 40.80 | DX25: $ 4.40 | DY25: $ 173.00 | DZ25: 71 | EA25: -0.1416 | EB25: 0.1911 | EC25: -0.0412 | ED25: 0.2607 | EE25: 0.2359 | EF25: -0.0068 | EG25: 0.0924 | EH25: 0.091 | EI25: -54.5 | EJ25: 136.6 | EK25: 140.2 | EL25: $ 888.20 | EM25: $ 762.40 | EN25: $ 908.10 | EO25: $ 870.70 | EP25: $ - | EQ25: $ - | ER25: 1 | ES25: 0.1052 | ET25: 0.0268 | EU25: 1506.8 | EV25: $ 1,506.80 | EW25: 1530.3 | EX25: 862.5 | EY25: 998.9 | EZ25: 938.1 | FA25: 888.2 | FB25: 779.4 | FC25: 0 | FD25: 0.654 | FE25: 0 | FF25: 855.5
A26: Fukuyama Transporting Co., Ltd. (TSE:9075) | B26: TSE:9075 | C26: Trucking | D26: Industrials | E26: 4210 | F26: Japan | G26: Japan | H26: Japan | I26: 0.6693 | J26: 1.0734 | K26: 0.0514 | L26: 0.0947 | M26: NA | N26: 0.0115 | O26: 0.051 | P26: 0.0358 | Q26: 0.0675 | R26: -0.0733 | S26: -0.0584 | T26: 1037.3 | U26: 60.44 | V26: 830.9 | W26: 891.34 | X26: 1928.64 | Y26: 211.2 | Z26: 1717.44 | AA26: 0.1095 | AB26: 0.52 | AC26: 0.3189 | AD26: 0.4622 | AE26: 0.4683 | AF26: 0.8593 | AG26: 28.28 | AH26: 24.3 | AI26: -0.012 | AJ26: 0.35 | AK26: 0.0775 | AL26: 0.1766 | AM26: 0.17 | AN26: 8.66 | AO26: 17.76 | AP26: 24.24 | AQ26: 14.99 | AR26: 14.21 | AS26: NA | AT26: 0.55 | AU26: 0.51 | AV26: 0.51 | AW26: 36.38 | AX26: 8.68 | AY26: 0.66 | AZ26: 0.85 | BA26: 0.4439 | BB26: 0.0183 | BC26: 0.0849 | BD26: -0.284 | BE26: -0.125 | BF26: 0.0163 | BG26: 0.0154 | BH26: NA | BI26: 0.0346 | BJ26: 0.0213 | BK26: 0.0091 | BL26: 0.81 | BM26: 0.0205 | BN26: 0.0226 | BO26: 0.0524 | BP26: 0.2974 | BQ26: 0.5 | BR26: 0.3208 | BS26: 58.4 | BT26: 42.8 | BU26: 43.9 | BV26: 47.21 | BW26: 109.5 | BX26: 2020 | BY26: 2089.8 | BZ26: 174.8 | CA26: 197.9 | CB26: 23.61 | CC26: -128.9 | CD26: -27.13 | CE26: 98 | CF26: 0.0469 | CG26: 216.48 | CH26: 8.0214 | CI26: -165.74 | CJ26: -17.65 | CK26: -146.55 | CL26: 2004.9 | CM26: 2587.64 | CN26: 1903.3 | CO26: 2583.44 | CP26: -19 | CQ26: 0.11 | CR26: 0.22 | CS26: 0.43 | CT26: 0.37 | CU26: 0.32 | CV26: 139.94 | CW26: 113.96 | CX26: -97.8 | CY26: 88.6 | CZ26: 45.6 | DA26: 42.8 | DB26: 1037.3 | DC26: 197.9 | DD26: 1717.44 | DE26: -17.65 | DF26: 0 | DG26: 47.21 | DH26: 2583.44 | DI26: 174.8 | DJ26: 0.0213 | DK26: 0.0091 | DL26: 9.83 | DM26: 3.92 | DN26: 2326.9 | DO26: 139.94 | DP26: 0.057 | DQ26: $ 103.70 | DR26: 453.2 | DS26: 582.1 | DT26: #REF! | DU26: $ - | DV26: $ 43.90 | DW26: $ 5.07 | DX26: $ 11.50 | DY26: $ 102.30 | DZ26: 72 | EA26: 0.0193 | EB26: -0.1026 | EC26: 0.0646 | ED26: 0.1338 | EE26: 0.104 | EF26: -0.0154 | EG26: 0.022 | EH26: 0.023 | EI26: $ 103.70 | EJ26: 43.9 | EK26: 46.7 | EL26: $ 939.60 | EM26: $ 957.70 | EN26: $ 859.40 | EO26: $ 914.90 | EP26: $ 2,089.80 | EQ26: $ 1,037.30 | ER26: 1 | ES26: -0.0548 | ET26: 0.0053 | EU26: 2089.8 | EV26: $ 2,089.80 | EW26: 1388.5 | EX26: 1379.6 | EY26: 824.4 | EZ26: 1164.3 | FA26: 939.6 | FB26: 956.1 | FC26: 102.7 | FD26: 0 | FE26: 0 | FF26: 0
A27: Maruzen Showa Unyu Co., Ltd. (TSE:9068) | B27: TSE:9068 | C27: Trucking | D27: Industrials | E27: 4210 | F27: Japan | G27: Japan | H27: Japan | I27: 0.6693 | J27: 0.7753 | K27: 0.0514 | L27: 0.0794 | M27: NA | N27: 0.0115 | O27: 0.051 | P27: 0.0358 | Q27: 0.0713 | R27: -0.0058 | S27: -0.0003 | T27: 1021.4 | U27: 38.48 | V27: 191.8 | W27: 230.28 | X27: 1251.68 | Y27: 118.8 | Z27: 1132.88 | AA27: 0.0949 | AB27: 0.36 | AC27: 0.197 | AD27: 0.184 | AE27: 0.2453 | AF27: 0.2255 | AG27: 52.47 | AH27: 24.3 | AI27: 0.142 | AJ27: 1.01 | AK27: 0.2627 | AL27: 0.227 | AM27: 0.23 | AN27: 51.39 | AO27: 15.59 | AP27: 15.29 | AQ27: 11.97 | AR27: 13.42 | AS27: NA | AT27: 1.09 | AU27: 0.93 | AV27: 1.06 | AW27: 10.21 | AX27: 7.46 | AY27: 1.08 | AZ27: 1.17 | BA27: 0.3458 | BB27: 0.0226 | BC27: 0.287 | BD27: 0.0158 | BE27: 0.1 | BF27: 0.0105 | BG27: 0.0401 | BH27: NA | BI27: 0.0446 | BJ27: 0.0735 | BK27: 0.0711 | BL27: 0.98 | BM27: 0.0679 | BN27: 0.1128 | BO27: 0.1387 | BP27: 0.2974 | BQ27: 0.3579 | BR27: 0.355 | BS27: 65.5 | BT27: 66.8 | BU27: 103.3 | BV27: 111 | BW27: 136.4 | BX27: 965.4 | BY27: 983.7 | BZ27: 132 | CA27: 151.9 | CB27: 71.28 | CC27: 2.5 | CD27: 0.59 | CE27: 116.26 | CF27: 0.1182 | CG27: 58.91 | CH27: 0.8348 | CI27: 11.77 | CJ27: 4.8 | CK27: 7.3 | CL27: 908.4 | CM27: 1002.81 | CN27: 938.8 | CO27: 1050.28 | CP27: -23.1 | CQ27: 0.5 | CR27: 0.3 | CS27: 0.43 | CT27: 0.29 | CU27: 0.29 | CV27: 75.55 | CW27: 56.59 | CX27: -44.4 | CY27: 105.9 | CZ27: 37.9 | DA27: 66.8 | DB27: 1021.4 | DC27: 151.9 | DD27: 1132.88 | DE27: 4.8 | DF27: 0 | DG27: 111 | DH27: 1050.28 | DI27: 132 | DJ27: 0.0735 | DK27: 0.0711 | DL27: 8.58 | DM27: 2.13 | DN27: 706.4 | DO27: 75.55 | DP27: 0.086 | DQ27: $ 8.80 | DR27: 13.8 | DS27: 11.3 | DT27: #REF! | DU27: $ - | DV27: $ 103.30 | DW27: $ 2.01 | DX27: $ 7.53 | DY27: $ 83.40 | DZ27: 89 | EA27: 0.0225 | EB27: 0.1924 | EC27: -0.0348 | ED27: 0.1141 | EE27: 0.311 | EF27: -0.023 | EG27: 0.1032 | EH27: 0.113 | EI27: $ 8.80 | EJ27: 103.3 | EK27: 103.9 | EL27: $ 779.10 | EM27: $ 796.60 | EN27: $ 949.90 | EO27: $ 916.80 | EP27: $ - | EQ27: $ - | ER27: 1 | ES27: -0.0319 | ET27: 0.0166 | EU27: 983.7 | EV27: $ 983.70 | EW27: 349.4 | EX27: 563.6 | EY27: 466.8 | EZ27: 562.8 | FA27: 779.1 | FB27: 793.6 | FC27: 79.1 | FD27: 0.0351 | FE27: 0 | FF27: 6.76
A28: Evergreen International Storage & Transport Corporation (TWSE:2607) | B28: TWSE:2607 | C28: Shipbuilding & Marine | D28: Industrials | E28: 4210 | F28: Taiwan | G28: Emerging Markets | H28: Small Asia | I28: 0.7871 | J28: 0.8856 | K28: 0.0501 | L28: 0.0839 | M28: NA | N28: 0.0106 | O28: 0.0501 | P28: 0.0401 | Q28: 0.0779 | R28: 0.0137 | S28: -0.0141 | T28: 980.4 | U28: 0 | V28: 153.3 | W28: 153.3 | X28: 1133.7 | Y28: 280.7 | Z28: 853 | AA28: 0.2476 | AB28: 0.53 | AC28: 0.135 | AD28: 0.1352 | AE28: 0.1561 | AF28: 0.1564 | AG28: 1.84 | AH28: 69.06 | AI28: -0.031 | AJ28: 0.94 | AK28: 0.2 | AL28: 0.2424 | AM28: 0.2 | AN28: 21.1 | AO28: 11.57 | AP28: 9.39 | AQ28: 11.22 | AR28: NA | AS28: NA | AT28: 1 | AU28: 0.87 | AV28: 1.51 | AW28: 10.87 | AX28: 8.91 | AY28: 1 | AZ28: 1.32 | BA28: 0.4358 | BB28: 0.0464 | BC28: 0.032 | BD28: -0.0155 | BE28: 0.329 | BF28: 0.0087 | BG28: 0.203 | BH28: NA | BI28: NA | BJ28: 0.0976 | BK28: 0.0639 | BL28: 0.6 | BM28: 0.1762 | BN28: 0.1325 | BO28: 0.2216 | BP28: 0.2 | BQ28: 0.195 | BR28: 0.0559 | BS28: 84.7 | BT28: 104.4 | BU28: 78.5 | BV28: 78.5 | BW28: 131.3 | BX28: 648.2 | BY28: 592.6 | BZ28: 110.5 | CA28: 95.7 | CB28: 63.19 | CC28: 17.31 | CD28: -56.05 | CE28: -122.19 | CF28: -0.2062 | CG28: 17.8 | CH28: -0.6053 | CI28: 101.44 | CJ28: 125.34 | CK28: 142.65 | CL28: 1069.7 | CM28: 989.2 | CN28: 982.1 | CO28: 854.7 | CP28: -45.5 | CQ28: 0.4 | CR28: 0.38 | CS28: 0.42 | CT28: 0.61 | CU28: 0.68 | CV28: 48.34 | CW28: 44.78 | CX28: -45.5 | CY28: 132.8 | CZ28: 25.9 | DA28: 104.4 | DB28: 980.4 | DC28: 95.7 | DD28: 853 | DE28: 125.34 | DF28: 0 | DG28: 78.5 | DH28: 854.7 | DI28: 110.5 | DJ28: 0.0976 | DK28: 0.0639 | DL28: 7.72 | DM28: 17.2 | DN28: 776.7 | DO28: 48.34 | DP28: 0.0593 | DQ28: -10 | DR28: 20.8 | DS28: 3.5 | DT28: #REF! | DU28: $ - | DV28: $ 78.50 | DW28: $ 3.72 | DX28: $ 25.30 | DY28: $ 38.80 | DZ28: 47 | EA28: -0.0038 | EB28: 0.2189 | EC28: NA | ED28: NA | EE28: -0.0363 | EF28: -0.1493 | EG28: 0.1302 | EH28: 0.132 | EI28: -10 | EJ28: 78.5 | EK28: 90.7 | EL28: $ 1,017.30 | EM28: $ 1,013.40 | EN28: $ 1,235.20 | EO28: $ - | EP28: $ - | EQ28: $ - | ER28: 1 | ES28: 0.1903 | ET28: NA | EU28: 592.6 | EV28: NA | EW28: 421.5 | EX28: 1127.3 | EY28: 965.7 | EZ28: 1104.1 | FA28: 1017.3 | FB28: 950 | FC28: 8.52 | FD28: 0 | FE28: 21.7 | FF28: 8.52
A29: Transport Corporation of India Limited (NSEI:TCI) | B29: NSEI:TCI | C29: Transportation | D29: Industrials | E29: 4210 | F29: India | G29: Emerging Markets | H29: India | I29: 0.7474 | J29: 0.7636 | K29: 0.0708 | L29: 0.0936 | M29: NA | N29: 0.0276 | O29: 0.0671 | P29: 0.047 | Q29: 0.0922 | R29: 0.1116 | S29: 0.0606 | T29: 920.5 | U29: 0 | V29: 28.5 | W29: 28.5 | X29: 949 | Y29: 8.92 | Z29: 940.08 | AA29: 0.0094 | AB29: 0.09 | AC29: 0.0944 | AD29: 0.03 | AE29: 0.1043 | AF29: 0.031 | AG29: 12.07 | AH29: 69.06 | AI29: 0.2438 | AJ29: 0.86 | AK29: 0.2258 | AL29: 0.2954 | AM29: 0.19 | AN29: 16.98 | AO29: 19.06 | AP29: 18.82 | AQ29: 20.71 | AR29: 19.41 | AS29: 1.59 | AT29: 3.37 | AU29: 4.08 | AV29: 1.75 | AW29: 21.71 | AX29: 16.94 | AY29: 3.21 | AZ29: 1.78 | BA29: 0.1409 | BB29: 0.0075 | BC29: -0.0501 | BD29: 0.11 | BE29: 0.314 | BF29: 0.0926 | BG29: 0.135 | BH29: 0.12 | BI29: 0.0983 | BJ29: 0.2051 | BK29: 0.1527 | BL29: 2.05 | BM29: 0.0928 | BN29: 0.0822 | BO29: 0.1355 | BP29: 0.3 | BQ29: 0.0924 | BR29: 0.1282 | BS29: 48.3 | BT29: 48.9 | BU29: 43.3 | BV29: 43.3 | BW29: 71.4 | BX29: 527 | BY29: 527 | BZ29: 54.5 | CA29: 55.5 | CB29: 39.3 | CC29: 1.73 | CD29: 1.59 | CE29: 84.92 | CF29: 0.1611 | CG29: 36.2 | CH29: 0.9617 | CI29: 1.51 | CJ29: 9.38 | CK29: 11.11 | CL29: 238.4 | CM29: 257.31 | CN29: 273.3 | CO29: 292.88 | CP29: -6.89 | CQ29: 0.56 | CR29: -0.03 | CS29: 0.42 | CT29: NA | CU29: NA | CV29: NA | CW29: NA | CX29: -6.89 | CY29: 54.3 | CZ29: 5.02 | DA29: 48.9 | DB29: 920.5 | DC29: 55.5 | DD29: 940.08 | DE29: 9.38 | DF29: 0 | DG29: 43.3 | DH29: 292.88 | DI29: 54.5 | DJ29: 0.2051 | DK29: 0.1527 | DL29: 17.25 | DM29: 13.4 | DN29: 144.26 | DO29: NA | DP29: NA | DQ29: $ 2.00 | DR29: 7.2 | DS29: 5.5 | DT29: #REF! | DU29: $ 0.54 | DV29: $ 43.30 | DW29: $ 2.55 | DX29: $ 2.64 | DY29: $ 12.40 | DZ29: 62 | EA29: -0.0401 | EB29: 0.0226 | EC29: 0.0091 | ED29: -0.0975 | EE29: -0.1061 | EF29: -0.0168 | EG29: 0.0819 | EH29: 0.082 | EI29: $ 2.00 | EJ29: 43.3 | EK29: 43.9 | EL29: $ 1,029.70 | EM29: $ 988.40 | EN29: $ 1,010.70 | EO29: $ 1,019.90 | EP29: $ - | EQ29: $ - | ER29: 1 | ES29: 0.0825 | ET29: 0.064 | EU29: 527 | EV29: $ 527.00 | EW29: 169.2 | EX29: 790 | EY29: 579.8 | EZ29: 767.8 | FA29: 1029.7 | FB29: 969.1 | FC29: 0 | FD29: 0 | FE29: 0 | FF29: 0
A30: SIMPAR S.A. (BOVESPA:SIMH3) | B30: BOVESPA:SIMH3 | C30: Trucking | D30: Industrials | E30: 4210 | F30: Brazil | G30: Emerging Markets | H30: Latin America & Caribbean | I30: 0.6693 | J30: 6.6917 | K30: 0.0747 | L30: 0.5394 | M30: 0.023 | N30: 0.0443 | O30: 0.0838 | P30: 0.0553 | Q30: 0.0884 | R30: -0.7359 | S30: 0.0395 | T30: 804.3 | U30: 0 | V30: 10965.2 | W30: 10965.2 | X30: 11769.5 | Y30: 603.3 | Z30: 11166.2 | AA30: 0.0513 | AB30: 1.57 | AC30: 0.9045 | AD30: 0.9317 | AE30: 9.4674 | AF30: 13.6332 | AG30: 0.94 | AH30: 69.06 | AI30: -0.2219 | AJ30: 1.09 | AK30: 0.1414 | AL30: 0.4921 | AM30: 0.43 | AN30: 0.95 | AO30: NA | AP30: NA | AQ30: NA | AR30: 8.4 | AS30: NA | AT30: 0.69 | AU30: 0.74 | AV30: 0.12 | AW30: 8.43 | AX30: 5.39 | AY30: 0.99 | AZ30: 1.68 | BA30: NA | BB30: 0.0656 | BC30: 0.1745 | BD30: NA | BE30: NA | BF30: 0.275 | BG30: 0.346 | BH30: NA | BI30: 0.0925 | BJ30: -0.1965 | BK30: 0.1279 | BL30: 0.78 | BM30: -0.0148 | BN30: 0.1631 | BO30: 0.2619 | BP30: 0.34 | BQ30: 0 | BR30: 0.0421 | BS30: -32 | BT30: -119.8 | BU30: 1324.4 | BV30: 1324.4 | BW30: 2126.4 | BX30: 6639.2 | BY30: 8120.2 | BZ30: 1637.1 | CA30: 2071.5 | CB30: 1324.4 | CC30: -133.7 | CD30: 243.3 | CE30: 554.4 | CF30: 0.0683 | CG30: 260.95 | CH30: 0.3807 | CI30: 820.15 | CJ30: -490.35 | CK30: -624.05 | CL30: 609.6 | CM30: 10354.6 | CN30: 1158.2 | CO30: 11301.4 | CP30: -52.8 | CQ30: 0.58 | CR30: 0.21 | CS30: 0.42 | CT30: 0.77 | CU30: 1.4 | CV30: 486.72 | CW30: 25.28 | CX30: -83.3 | CY30: NA | CZ30: NA | DA30: NA | DB30: NA | DC30: 2071.5 | DD30: 11166.2 | DE30: -490.35 | DF30: 0 | DG30: 1324.4 | DH30: 11301.4 | DI30: 1637.1 | DJ30: -0.1965 | DK30: 0.1279 | DL30: 6.82 | DM30: 747.1 | DN30: 2183.8 | DO30: 486.72 | DP30: 0.0722 | DQ30: $ 645.20 | DR30: 2,091.7 | DS30: 2,225.4 | DT30: #REF! | DU30: $ 2.38 | DV30: $ 1,324.40 | DW30: $ 1,389.50 | DX30: $ 281.20 | DY30: $ 1,127.00 | DZ30: 64 | EA30: 0.2449 | EB30: 0.3066 | EC30: 0.0044 | ED30: 0.0064 | EE30: 0.6441 | EF30: 0.0349 | EG30: 0.1641 | EH30: 0.163 | EI30: $ 645.20 | EJ30: 1324.4 | EK30: 1287.3 | EL30: $ 489.20 | EM30: $ 609.00 | EN30: $ 795.70 | EO30: $ 799.20 | EP30: $ 8,120.20 | EQ30: $ 804.30 | ER30: 0 | ES30: 0.3387 | ET30: 0.0548 | EU30: 8120.2 | EV30: $ 8,120.20 | EW30: 0 | EX30: 1679 | EY30: 1056.5 | EZ30: 1641.4 | FA30: 489.2 | FB30: 684.8 | FC30: 188 | FD30: 0.874 | FE30: 8800.1 | FF30: 1688.6
A31: Forward Air Corporation (NasdaqGS:FWRD) | B31: NasdaqGS:FWRD | C31: Transportation | D31: Industrials | E31: 4210 | F31: United States | G31: United States | H31: United States | I31: 0.7474 | J31: 2.2726 | K31: 0.0446 | L31: 0.1409 | M31: 0.0321 | N31: 0.0344 | O31: 0.0739 | P31: 0.0554 | Q31: 0.0784 | R31: -0.6535 | S31: -0.0028 | T31: 781.2 | U31: 398.61 | V31: 1726.9 | W31: 2125.51 | X31: 2906.71 | Y31: 140.4 | Z31: 2766.31 | AA31: 0.0483 | AB31: 5.35 | AC31: 0.9157 | AD31: 0.7312 | AE31: 10.8555 | AF31: 2.7208 | AG31: 25 | AH31: 31.61 | AI31: -0.2883 | AJ31: 1.54 | AK31: 0.3661 | AL31: 0.6196 | AM31: 0.57 | AN31: 0.39 | AO31: NA | AP31: NA | AQ31: NA | AR31: NA | AS31: NA | AT31: 3.99 | AU31: 1.44 | AV31: 0.32 | AW31: 24.49 | AX31: 8.16 | AY31: 1.67 | AZ31: 1.12 | BA31: NA | BB31: 0 | BC31: 0.9007 | BD31: NA | BE31: NA | BF31: 0.0855 | BG31: 0.15 | BH31: NA | BI31: 0.0276 | BJ31: -0.5126 | BK31: 0.0756 | BL31: 1.67 | BM31: -0.0464 | BN31: 0.0453 | BO31: 0.1937 | BP31: 0.25 | BQ31: 0 | BR31: 0.7895 | BS31: -817 | BT31: -115.9 | BU31: 71.9 | BV31: 112.98 | BW31: 483.7 | BX31: 2474.3 | BY31: 2496.7 | BZ31: 187.5 | CA31: 338.9 | CB31: 112.98 | CC31: 16.1 | CD31: -2.2 | CE31: 186 | CF31: 0.0745 | CG31: -110.6 | CH31: -0.9984 | CI31: 225.78 | CJ31: -19.2 | CK31: -3.1 | CL31: 226.1 | CM31: 1494.81 | CN31: 195.8 | CO31: 1658.21 | CP31: 0 | CQ31: 1.89 | CR31: 1.37 | CS31: 1.12 | CT31: 0.44 | CU31: 0.35 | CV31: 120.78 | CW31: 93.31 | CX31: -0.92 | CY31: NA | CZ31: NA | DA31: NA | DB31: NA | DC31: 338.9 | DD31: 2766.31 | DE31: -19.2 | DF31: 0 | DG31: 112.98 | DH31: 1658.21 | DI31: 187.5 | DJ31: -0.5126 | DK31: 0.0756 | DL31: 14.75 | DM31: 149.6 | DN31: 279.35 | DO31: 120.78 | DP31: 0.1247 | DQ31: $ 68.10 | DR31: 176.1 | DS31: 160.0 | DT31: #REF! | DU31: $ 0.83 | DV31: $ 71.90 | DW31: $ 184.10 | DX31: $ - | DY31: $ 124.80 | DZ31: 39 | EA31: -0.3459 | EB31: 0.2223 | EC31: 0.0575 | ED31: -0.0105 | EE31: -0.1634 | EF31: -0.0096 | EG31: 0.0349 | EH31: 0.045 | EI31: $ 68.10 | EJ31: 71.9 | EK31: 87.9 | EL31: $ 933.80 | EM31: $ 610.80 | EN31: $ 746.60 | EO31: $ 789.50 | EP31: $ - | EQ31: $ - | ER31: 0 | ES31: 0.1448 | ET31: NA | EU31: 2496.7 | EV31: NA | EW31: 1446.2 | EX31: 3242.5 | EY31: 2789 | EZ31: 1613.4 | FA31: 933.8 | FB31: 411 | FC31: 0 | FD31: 0.338 | FE31: 1045 | FF31: 767.6
A32: Serve Robotics Inc. (NasdaqCM:SERV) | B32: NasdaqCM:SERV | C32: Restaurant/Dining | D32: Consumer Discretionary | E32: 4210 | F32: United States | G32: United States | H32: United States | I32: 0.6504 | J32: 0.6516 | K32: 0.0446 | L32: 0.0686 | M32: NA | N32: 0.0134 | O32: 0.0529 | P32: 0.0397 | Q32: 0.0685 | R32: -1.0686 | S32: -1.0685 | T32: 772.6 | U32: 1.82 | V32: 0 | W32: 1.82 | X32: 774.42 | Y32: 116.8 | Z32: 657.62 | AA32: 0.1508 | AB32: 26.85 | AC32: 0.0064 | AD32: 0.0023 | AE32: 0.0064 | AF32: 0.0024 | AG32: 10.38 | AH32: 31.61 | AI32: NA | AJ32: 0.79 | AK32: 0.0548 | AL32: NA | AM32: 0.68 | AN32: NA | AO32: NA | AP32: NA | AQ32: NA | AR32: NA | AS32: NA | AT32: 2.72 | AU32: 2.29 | AV32: 426.85 | AW32: NA | AX32: NA | AY32: 4.19 | AZ32: 363.32 | BA32: NA | BB32: 0 | BC32: 1.5608 | BD32: NA | BE32: NA | BF32: NA | BG32: NA | BH32: NA | BI32: 3.085 | BJ32: -1 | BK32: -1 | BL32: 0.24 | BM32: -41.3402 | BN32: -44.0986 | BO32: -4.8247 | BP32: 0.25 | BQ32: 0 | BR32: 0.3488 | BS32: -39.2 | BT32: -80.2 | BU32: -86 | BV32: -85.55 | BW32: -9.36 | BX32: 1.81 | BY32: 1.94 | BZ32: -38 | CA32: -82.49 | CB32: -85.55 | CC32: 0.65 | CD32: -2.03 | CE32: -6.81 | CF32: -3.5113 | CG32: 33.2 | CH32: NA | CI32: -116.73 | CJ32: -112.02 | CK32: -111.37 | CL32: 56.2 | CM32: 8.16 | CN32: 283.9 | CO32: 157.12 | CP32: 0 | CQ32: 0.82 | CR32: NA | CS32: 1.12 | CT32: NA | CU32: NA | CV32: NA | CW32: NA | CX32: 0 | CY32: NA | CZ32: NA | DA32: NA | DB32: NA | DC32: NA | DD32: NA | DE32: NA | DF32: 86.9 | DG32: -72.35 | DH32: 244.02 | DI32: -1.8 | DJ32: -0.4682 | DK32: -0.7611 | DL32: NA | DM32: 2.7 | DN32: NA | DO32: NA | DP32: NA | DQ32: $ 2.54 | DR32: 0.6 | DS32: 0 | DT32: #REF! | DU32: $ 254.60 | DV32: -86 | DW32: $ - | DX32: $ 5.75 | DY32: $ 7.75 | DZ32: 3 | EA32: -0.4497 | EB32: 0.9957 | EC32: 0.0965 | ED32: 0.0807 | EE32: 0.3013 | EF32: 0.3108 | EG32: -40.3378 | EH32: -44.099 | EI32: $ 2.54 | EJ32: -86 | EK32: -59.7 | EL32: $ 593.70 | EM32: $ 326.70 | EN32: $ 652.00 | EO32: $ 714.90 | EP32: $ - | EQ32: $ - | ER32: 0 | ES32: NA | ET32: 1.3334 | EU32: NA | EV32: $ 1.94 | EW32: 0 | EX32: 0 | EY32: 0 | EZ32: 0 | FA32: 593.7 | FB32: 301.7 | FC32: 0 | FD32: 0 | FE32: 0 | FF32: 0
